[
    {
        "%vlocity_namespace%__Alias__c": "PDlimit",
        "%vlocity_namespace%__CalculationProcedureVersionId__c": {
            "%vlocity_namespace%__CalculationProcedureId__r.Name": "autoRateVehicles",
            "%vlocity_namespace%__VersionNumber__c": 2,
            "VlocityDataPackType": "VlocityMatchingKeyObject",
            "VlocityMatchingRecordSourceKey": "%vlocity_namespace%__CalculationProcedureVersion__c/2/%vlocity_namespace%__CalculationProcedure__c/autoRateVehicles",
            "VlocityRecordSObjectType": "%vlocity_namespace%__CalculationProcedureVersion__c"
        },
        "%vlocity_namespace%__DataType__c": "Number",
        "%vlocity_namespace%__DefaultValue__c": "",
        "%vlocity_namespace%__DuplicateAlias__c": false,
        "%vlocity_namespace%__Index__c": 22,
        "%vlocity_namespace%__IsEditable__c": false,
        "%vlocity_namespace%__IsSelected__c": false,
        "%vlocity_namespace%__MatrixName__c": "autoLimitBIPD",
        "%vlocity_namespace%__Precision__c": "",
        "%vlocity_namespace%__TypeaheadDisplayName__c": "PDlimit",
        "%vlocity_namespace%__UserDefined__c": false,
        "Name": "PDlimit",
        "VlocityDataPackType": "SObject",
        "VlocityRecordSObjectType": "%vlocity_namespace%__CalculationProcedureVariable__c",
        "VlocityRecordSourceKey": "%vlocity_namespace%__CalculationProcedureVariable__c/Generated669607315"
    },
    {
        "%vlocity_namespace%__Alias__c": "autoBIPD",
        "%vlocity_namespace%__CalculationProcedureVersionId__c": {
            "%vlocity_namespace%__CalculationProcedureId__r.Name": "autoRateVehicles",
            "%vlocity_namespace%__VersionNumber__c": 2,
            "VlocityDataPackType": "VlocityMatchingKeyObject",
            "VlocityMatchingRecordSourceKey": "%vlocity_namespace%__CalculationProcedureVersion__c/2/%vlocity_namespace%__CalculationProcedure__c/autoRateVehicles",
            "VlocityRecordSObjectType": "%vlocity_namespace%__CalculationProcedureVersion__c"
        },
        "%vlocity_namespace%__DataType__c": "Number",
        "%vlocity_namespace%__DefaultValue__c": "1",
        "%vlocity_namespace%__DuplicateAlias__c": false,
        "%vlocity_namespace%__Index__c": "",
        "%vlocity_namespace%__IsEditable__c": false,
        "%vlocity_namespace%__IsSelected__c": false,
        "%vlocity_namespace%__MatrixName__c": "",
        "%vlocity_namespace%__Precision__c": 2,
        "%vlocity_namespace%__TypeaheadDisplayName__c": "",
        "%vlocity_namespace%__UserDefined__c": true,
        "Name": "autoBIPD",
        "VlocityDataPackType": "SObject",
        "VlocityRecordSObjectType": "%vlocity_namespace%__CalculationProcedureVariable__c",
        "VlocityRecordSourceKey": "%vlocity_namespace%__CalculationProcedureVariable__c/Generated722406123"
    },
    {
        "%vlocity_namespace%__Alias__c": "autoCCD",
        "%vlocity_namespace%__CalculationProcedureVersionId__c": {
            "%vlocity_namespace%__CalculationProcedureId__r.Name": "autoRateVehicles",
            "%vlocity_namespace%__VersionNumber__c": 2,
            "VlocityDataPackType": "VlocityMatchingKeyObject",
            "VlocityMatchingRecordSourceKey": "%vlocity_namespace%__CalculationProcedureVersion__c/2/%vlocity_namespace%__CalculationProcedure__c/autoRateVehicles",
            "VlocityRecordSObjectType": "%vlocity_namespace%__CalculationProcedureVersion__c"
        },
        "%vlocity_namespace%__DataType__c": "Number",
        "%vlocity_namespace%__DefaultValue__c": "1",
        "%vlocity_namespace%__DuplicateAlias__c": false,
        "%vlocity_namespace%__Index__c": "",
        "%vlocity_namespace%__IsEditable__c": false,
        "%vlocity_namespace%__IsSelected__c": false,
        "%vlocity_namespace%__MatrixName__c": "",
        "%vlocity_namespace%__Precision__c": 2,
        "%vlocity_namespace%__TypeaheadDisplayName__c": "",
        "%vlocity_namespace%__UserDefined__c": true,
        "Name": "autoCCD",
        "VlocityDataPackType": "SObject",
        "VlocityRecordSObjectType": "%vlocity_namespace%__CalculationProcedureVariable__c",
        "VlocityRecordSourceKey": "%vlocity_namespace%__CalculationProcedureVariable__c/Generated-1614158461"
    },
    {
        "%vlocity_namespace%__Alias__c": "autoCOLL",
        "%vlocity_namespace%__CalculationProcedureVersionId__c": {
            "%vlocity_namespace%__CalculationProcedureId__r.Name": "autoRateVehicles",
            "%vlocity_namespace%__VersionNumber__c": 2,
            "VlocityDataPackType": "VlocityMatchingKeyObject",
            "VlocityMatchingRecordSourceKey": "%vlocity_namespace%__CalculationProcedureVersion__c/2/%vlocity_namespace%__CalculationProcedure__c/autoRateVehicles",
            "VlocityRecordSObjectType": "%vlocity_namespace%__CalculationProcedureVersion__c"
        },
        "%vlocity_namespace%__DataType__c": "Number",
        "%vlocity_namespace%__DefaultValue__c": "1",
        "%vlocity_namespace%__DuplicateAlias__c": false,
        "%vlocity_namespace%__Index__c": "",
        "%vlocity_namespace%__IsEditable__c": false,
        "%vlocity_namespace%__IsSelected__c": false,
        "%vlocity_namespace%__MatrixName__c": "",
        "%vlocity_namespace%__Precision__c": 2,
        "%vlocity_namespace%__TypeaheadDisplayName__c": "",
        "%vlocity_namespace%__UserDefined__c": true,
        "Name": "autoCOLL",
        "VlocityDataPackType": "SObject",
        "VlocityRecordSObjectType": "%vlocity_namespace%__CalculationProcedureVariable__c",
        "VlocityRecordSourceKey": "%vlocity_namespace%__CalculationProcedureVariable__c/Generated2067411789"
    },
    {
        "%vlocity_namespace%__Alias__c": "autoLimitBIPD__factorBIPD",
        "%vlocity_namespace%__CalculationProcedureVersionId__c": {
            "%vlocity_namespace%__CalculationProcedureId__r.Name": "autoRateVehicles",
            "%vlocity_namespace%__VersionNumber__c": 2,
            "VlocityDataPackType": "VlocityMatchingKeyObject",
            "VlocityMatchingRecordSourceKey": "%vlocity_namespace%__CalculationProcedureVersion__c/2/%vlocity_namespace%__CalculationProcedure__c/autoRateVehicles",
            "VlocityRecordSObjectType": "%vlocity_namespace%__CalculationProcedureVersion__c"
        },
        "%vlocity_namespace%__DataType__c": "Number",
        "%vlocity_namespace%__DefaultValue__c": "",
        "%vlocity_namespace%__DuplicateAlias__c": false,
        "%vlocity_namespace%__Index__c": 22,
        "%vlocity_namespace%__IsEditable__c": false,
        "%vlocity_namespace%__IsSelected__c": false,
        "%vlocity_namespace%__MatrixName__c": "autoLimitBIPD",
        "%vlocity_namespace%__Precision__c": "",
        "%vlocity_namespace%__TypeaheadDisplayName__c": "factorBIPD ( autoLimitBIPD )",
        "%vlocity_namespace%__UserDefined__c": false,
        "Name": "factorBIPD",
        "VlocityDataPackType": "SObject",
        "VlocityRecordSObjectType": "%vlocity_namespace%__CalculationProcedureVariable__c",
        "VlocityRecordSourceKey": "%vlocity_namespace%__CalculationProcedureVariable__c/Generated-753092237"
    },
    {
        "%vlocity_namespace%__Alias__c": "autoMED",
        "%vlocity_namespace%__CalculationProcedureVersionId__c": {
            "%vlocity_namespace%__CalculationProcedureId__r.Name": "autoRateVehicles",
            "%vlocity_namespace%__VersionNumber__c": 2,
            "VlocityDataPackType": "VlocityMatchingKeyObject",
            "VlocityMatchingRecordSourceKey": "%vlocity_namespace%__CalculationProcedureVersion__c/2/%vlocity_namespace%__CalculationProcedure__c/autoRateVehicles",
            "VlocityRecordSObjectType": "%vlocity_namespace%__CalculationProcedureVersion__c"
        },
        "%vlocity_namespace%__DataType__c": "Number",
        "%vlocity_namespace%__DefaultValue__c": "1",
        "%vlocity_namespace%__DuplicateAlias__c": false,
        "%vlocity_namespace%__Index__c": "",
        "%vlocity_namespace%__IsEditable__c": false,
        "%vlocity_namespace%__IsSelected__c": false,
        "%vlocity_namespace%__MatrixName__c": "",
        "%vlocity_namespace%__Precision__c": 2,
        "%vlocity_namespace%__TypeaheadDisplayName__c": "",
        "%vlocity_namespace%__UserDefined__c": true,
        "Name": "autoMED",
        "VlocityDataPackType": "SObject",
        "VlocityRecordSObjectType": "%vlocity_namespace%__CalculationProcedureVariable__c",
        "VlocityRecordSourceKey": "%vlocity_namespace%__CalculationProcedureVariable__c/Generated2049681539"
    },
    {
        "%vlocity_namespace%__Alias__c": "autoUM",
        "%vlocity_namespace%__CalculationProcedureVersionId__c": {
            "%vlocity_namespace%__CalculationProcedureId__r.Name": "autoRateVehicles",
            "%vlocity_namespace%__VersionNumber__c": 2,
            "VlocityDataPackType": "VlocityMatchingKeyObject",
            "VlocityMatchingRecordSourceKey": "%vlocity_namespace%__CalculationProcedureVersion__c/2/%vlocity_namespace%__CalculationProcedure__c/autoRateVehicles",
            "VlocityRecordSObjectType": "%vlocity_namespace%__CalculationProcedureVersion__c"
        },
        "%vlocity_namespace%__DataType__c": "Number",
        "%vlocity_namespace%__DefaultValue__c": "1",
        "%vlocity_namespace%__DuplicateAlias__c": false,
        "%vlocity_namespace%__Index__c": "",
        "%vlocity_namespace%__IsEditable__c": false,
        "%vlocity_namespace%__IsSelected__c": false,
        "%vlocity_namespace%__MatrixName__c": "",
        "%vlocity_namespace%__Precision__c": 2,
        "%vlocity_namespace%__TypeaheadDisplayName__c": "",
        "%vlocity_namespace%__UserDefined__c": true,
        "Name": "autoUM",
        "VlocityDataPackType": "SObject",
        "VlocityRecordSObjectType": "%vlocity_namespace%__CalculationProcedureVariable__c",
        "VlocityRecordSourceKey": "%vlocity_namespace%__CalculationProcedureVariable__c/Generated1927869029"
    },
    {
        "%vlocity_namespace%__Alias__c": "carAltFuel",
        "%vlocity_namespace%__CalculationProcedureVersionId__c": {
            "%vlocity_namespace%__CalculationProcedureId__r.Name": "autoRateVehicles",
            "%vlocity_namespace%__VersionNumber__c": 2,
            "VlocityDataPackType": "VlocityMatchingKeyObject",
            "VlocityMatchingRecordSourceKey": "%vlocity_namespace%__CalculationProcedureVersion__c/2/%vlocity_namespace%__CalculationProcedure__c/autoRateVehicles",
            "VlocityRecordSObjectType": "%vlocity_namespace%__CalculationProcedureVersion__c"
        },
        "%vlocity_namespace%__DataType__c": "Boolean",
        "%vlocity_namespace%__DefaultValue__c": "",
        "%vlocity_namespace%__DuplicateAlias__c": false,
        "%vlocity_namespace%__Index__c": 2,
        "%vlocity_namespace%__IsEditable__c": false,
        "%vlocity_namespace%__IsSelected__c": false,
        "%vlocity_namespace%__MatrixName__c": "carAltFuel",
        "%vlocity_namespace%__Precision__c": "",
        "%vlocity_namespace%__TypeaheadDisplayName__c": "carAltFuel",
        "%vlocity_namespace%__UserDefined__c": false,
        "Name": "carAltFuel",
        "VlocityDataPackType": "SObject",
        "VlocityRecordSObjectType": "%vlocity_namespace%__CalculationProcedureVariable__c",
        "VlocityRecordSourceKey": "%vlocity_namespace%__CalculationProcedureVariable__c/Generated-231340172"
    },
    {
        "%vlocity_namespace%__Alias__c": "carAltFuel__carAltFuelBIPD",
        "%vlocity_namespace%__CalculationProcedureVersionId__c": {
            "%vlocity_namespace%__CalculationProcedureId__r.Name": "autoRateVehicles",
            "%vlocity_namespace%__VersionNumber__c": 2,
            "VlocityDataPackType": "VlocityMatchingKeyObject",
            "VlocityMatchingRecordSourceKey": "%vlocity_namespace%__CalculationProcedureVersion__c/2/%vlocity_namespace%__CalculationProcedure__c/autoRateVehicles",
            "VlocityRecordSObjectType": "%vlocity_namespace%__CalculationProcedureVersion__c"
        },
        "%vlocity_namespace%__DataType__c": "Number",
        "%vlocity_namespace%__DefaultValue__c": "",
        "%vlocity_namespace%__DuplicateAlias__c": false,
        "%vlocity_namespace%__Index__c": 2,
        "%vlocity_namespace%__IsEditable__c": false,
        "%vlocity_namespace%__IsSelected__c": false,
        "%vlocity_namespace%__MatrixName__c": "carAltFuel",
        "%vlocity_namespace%__Precision__c": "",
        "%vlocity_namespace%__TypeaheadDisplayName__c": "carAltFuelBIPD ( carAltFuel )",
        "%vlocity_namespace%__UserDefined__c": false,
        "Name": "carAltFuelBIPD",
        "VlocityDataPackType": "SObject",
        "VlocityRecordSObjectType": "%vlocity_namespace%__CalculationProcedureVariable__c",
        "VlocityRecordSourceKey": "%vlocity_namespace%__CalculationProcedureVariable__c/Generated-1393571349"
    },
    {
        "%vlocity_namespace%__Alias__c": "carAltFuel__carAltFuelCCD",
        "%vlocity_namespace%__CalculationProcedureVersionId__c": {
            "%vlocity_namespace%__CalculationProcedureId__r.Name": "autoRateVehicles",
            "%vlocity_namespace%__VersionNumber__c": 2,
            "VlocityDataPackType": "VlocityMatchingKeyObject",
            "VlocityMatchingRecordSourceKey": "%vlocity_namespace%__CalculationProcedureVersion__c/2/%vlocity_namespace%__CalculationProcedure__c/autoRateVehicles",
            "VlocityRecordSObjectType": "%vlocity_namespace%__CalculationProcedureVersion__c"
        },
        "%vlocity_namespace%__DataType__c": "Number",
        "%vlocity_namespace%__DefaultValue__c": "",
        "%vlocity_namespace%__DuplicateAlias__c": false,
        "%vlocity_namespace%__Index__c": 2,
        "%vlocity_namespace%__IsEditable__c": false,
        "%vlocity_namespace%__IsSelected__c": false,
        "%vlocity_namespace%__MatrixName__c": "carAltFuel",
        "%vlocity_namespace%__Precision__c": "",
        "%vlocity_namespace%__TypeaheadDisplayName__c": "carAltFuelCCD ( carAltFuel )",
        "%vlocity_namespace%__UserDefined__c": false,
        "Name": "carAltFuelCCD",
        "VlocityDataPackType": "SObject",
        "VlocityRecordSObjectType": "%vlocity_namespace%__CalculationProcedureVariable__c",
        "VlocityRecordSourceKey": "%vlocity_namespace%__CalculationProcedureVariable__c/Generated-1179027066"
    },
    {
        "%vlocity_namespace%__Alias__c": "carAltFuel__carAltFuelCOLL",
        "%vlocity_namespace%__CalculationProcedureVersionId__c": {
            "%vlocity_namespace%__CalculationProcedureId__r.Name": "autoRateVehicles",
            "%vlocity_namespace%__VersionNumber__c": 2,
            "VlocityDataPackType": "VlocityMatchingKeyObject",
            "VlocityMatchingRecordSourceKey": "%vlocity_namespace%__CalculationProcedureVersion__c/2/%vlocity_namespace%__CalculationProcedure__c/autoRateVehicles",
            "VlocityRecordSObjectType": "%vlocity_namespace%__CalculationProcedureVersion__c"
        },
        "%vlocity_namespace%__DataType__c": "Number",
        "%vlocity_namespace%__DefaultValue__c": "",
        "%vlocity_namespace%__DuplicateAlias__c": false,
        "%vlocity_namespace%__Index__c": 2,
        "%vlocity_namespace%__IsEditable__c": false,
        "%vlocity_namespace%__IsSelected__c": false,
        "%vlocity_namespace%__MatrixName__c": "carAltFuel",
        "%vlocity_namespace%__Precision__c": "",
        "%vlocity_namespace%__TypeaheadDisplayName__c": "carAltFuelCOLL ( carAltFuel )",
        "%vlocity_namespace%__UserDefined__c": false,
        "Name": "carAltFuelCOLL",
        "VlocityDataPackType": "SObject",
        "VlocityRecordSObjectType": "%vlocity_namespace%__CalculationProcedureVariable__c",
        "VlocityRecordSourceKey": "%vlocity_namespace%__CalculationProcedureVariable__c/Generated769686906"
    },
    {
        "%vlocity_namespace%__Alias__c": "carAltFuel__carAltFuelMED",
        "%vlocity_namespace%__CalculationProcedureVersionId__c": {
            "%vlocity_namespace%__CalculationProcedureId__r.Name": "autoRateVehicles",
            "%vlocity_namespace%__VersionNumber__c": 2,
            "VlocityDataPackType": "VlocityMatchingKeyObject",
            "VlocityMatchingRecordSourceKey": "%vlocity_namespace%__CalculationProcedureVersion__c/2/%vlocity_namespace%__CalculationProcedure__c/autoRateVehicles",
            "VlocityRecordSObjectType": "%vlocity_namespace%__CalculationProcedureVersion__c"
        },
        "%vlocity_namespace%__DataType__c": "Number",
        "%vlocity_namespace%__DefaultValue__c": "",
        "%vlocity_namespace%__DuplicateAlias__c": false,
        "%vlocity_namespace%__Index__c": 2,
        "%vlocity_namespace%__IsEditable__c": false,
        "%vlocity_namespace%__IsSelected__c": false,
        "%vlocity_namespace%__MatrixName__c": "carAltFuel",
        "%vlocity_namespace%__Precision__c": "",
        "%vlocity_namespace%__TypeaheadDisplayName__c": "carAltFuelMED ( carAltFuel )",
        "%vlocity_namespace%__UserDefined__c": false,
        "Name": "carAltFuelMED",
        "VlocityDataPackType": "SObject",
        "VlocityRecordSObjectType": "%vlocity_namespace%__CalculationProcedureVariable__c",
        "VlocityRecordSourceKey": "%vlocity_namespace%__CalculationProcedureVariable__c/Generated53041230"
    },
    {
        "%vlocity_namespace%__Alias__c": "carAltFuel__carAltFuelUM",
        "%vlocity_namespace%__CalculationProcedureVersionId__c": {
            "%vlocity_namespace%__CalculationProcedureId__r.Name": "autoRateVehicles",
            "%vlocity_namespace%__VersionNumber__c": 2,
            "VlocityDataPackType": "VlocityMatchingKeyObject",
            "VlocityMatchingRecordSourceKey": "%vlocity_namespace%__CalculationProcedureVersion__c/2/%vlocity_namespace%__CalculationProcedure__c/autoRateVehicles",
            "VlocityRecordSObjectType": "%vlocity_namespace%__CalculationProcedureVersion__c"
        },
        "%vlocity_namespace%__DataType__c": "Number",
        "%vlocity_namespace%__DefaultValue__c": "",
        "%vlocity_namespace%__DuplicateAlias__c": false,
        "%vlocity_namespace%__Index__c": 2,
        "%vlocity_namespace%__IsEditable__c": false,
        "%vlocity_namespace%__IsSelected__c": false,
        "%vlocity_namespace%__MatrixName__c": "carAltFuel",
        "%vlocity_namespace%__Precision__c": "",
        "%vlocity_namespace%__TypeaheadDisplayName__c": "carAltFuelUM ( carAltFuel )",
        "%vlocity_namespace%__UserDefined__c": false,
        "Name": "carAltFuelUM",
        "VlocityDataPackType": "SObject",
        "VlocityRecordSObjectType": "%vlocity_namespace%__CalculationProcedureVariable__c",
        "VlocityRecordSourceKey": "%vlocity_namespace%__CalculationProcedureVariable__c/Generated1250156750"
    },
    {
        "%vlocity_namespace%__Alias__c": "carBrake",
        "%vlocity_namespace%__CalculationProcedureVersionId__c": {
            "%vlocity_namespace%__CalculationProcedureId__r.Name": "autoRateVehicles",
            "%vlocity_namespace%__VersionNumber__c": 2,
            "VlocityDataPackType": "VlocityMatchingKeyObject",
            "VlocityMatchingRecordSourceKey": "%vlocity_namespace%__CalculationProcedureVersion__c/2/%vlocity_namespace%__CalculationProcedure__c/autoRateVehicles",
            "VlocityRecordSObjectType": "%vlocity_namespace%__CalculationProcedureVersion__c"
        },
        "%vlocity_namespace%__DataType__c": "Boolean",
        "%vlocity_namespace%__DefaultValue__c": "",
        "%vlocity_namespace%__DuplicateAlias__c": false,
        "%vlocity_namespace%__Index__c": 5,
        "%vlocity_namespace%__IsEditable__c": false,
        "%vlocity_namespace%__IsSelected__c": false,
        "%vlocity_namespace%__MatrixName__c": "carBrakes",
        "%vlocity_namespace%__Precision__c": "",
        "%vlocity_namespace%__TypeaheadDisplayName__c": "carBrake",
        "%vlocity_namespace%__UserDefined__c": false,
        "Name": "carBrake",
        "VlocityDataPackType": "SObject",
        "VlocityRecordSObjectType": "%vlocity_namespace%__CalculationProcedureVariable__c",
        "VlocityRecordSourceKey": "%vlocity_namespace%__CalculationProcedureVariable__c/Generated-601807598"
    },
    {
        "%vlocity_namespace%__Alias__c": "carBrakes__carBrakeBIPD",
        "%vlocity_namespace%__CalculationProcedureVersionId__c": {
            "%vlocity_namespace%__CalculationProcedureId__r.Name": "autoRateVehicles",
            "%vlocity_namespace%__VersionNumber__c": 2,
            "VlocityDataPackType": "VlocityMatchingKeyObject",
            "VlocityMatchingRecordSourceKey": "%vlocity_namespace%__CalculationProcedureVersion__c/2/%vlocity_namespace%__CalculationProcedure__c/autoRateVehicles",
            "VlocityRecordSObjectType": "%vlocity_namespace%__CalculationProcedureVersion__c"
        },
        "%vlocity_namespace%__DataType__c": "Number",
        "%vlocity_namespace%__DefaultValue__c": "",
        "%vlocity_namespace%__DuplicateAlias__c": false,
        "%vlocity_namespace%__Index__c": 5,
        "%vlocity_namespace%__IsEditable__c": false,
        "%vlocity_namespace%__IsSelected__c": false,
        "%vlocity_namespace%__MatrixName__c": "carBrakes",
        "%vlocity_namespace%__Precision__c": "",
        "%vlocity_namespace%__TypeaheadDisplayName__c": "carBrakeBIPD ( carBrakes )",
        "%vlocity_namespace%__UserDefined__c": false,
        "Name": "carBrakeBIPD",
        "VlocityDataPackType": "SObject",
        "VlocityRecordSObjectType": "%vlocity_namespace%__CalculationProcedureVariable__c",
        "VlocityRecordSourceKey": "%vlocity_namespace%__CalculationProcedureVariable__c/Generated13273621"
    },
    {
        "%vlocity_namespace%__Alias__c": "carBrakes__carBrakeCOLL",
        "%vlocity_namespace%__CalculationProcedureVersionId__c": {
            "%vlocity_namespace%__CalculationProcedureId__r.Name": "autoRateVehicles",
            "%vlocity_namespace%__VersionNumber__c": 2,
            "VlocityDataPackType": "VlocityMatchingKeyObject",
            "VlocityMatchingRecordSourceKey": "%vlocity_namespace%__CalculationProcedureVersion__c/2/%vlocity_namespace%__CalculationProcedure__c/autoRateVehicles",
            "VlocityRecordSObjectType": "%vlocity_namespace%__CalculationProcedureVersion__c"
        },
        "%vlocity_namespace%__DataType__c": "Number",
        "%vlocity_namespace%__DefaultValue__c": "",
        "%vlocity_namespace%__DuplicateAlias__c": false,
        "%vlocity_namespace%__Index__c": 5,
        "%vlocity_namespace%__IsEditable__c": false,
        "%vlocity_namespace%__IsSelected__c": false,
        "%vlocity_namespace%__MatrixName__c": "carBrakes",
        "%vlocity_namespace%__Precision__c": "",
        "%vlocity_namespace%__TypeaheadDisplayName__c": "carBrakeCOLL ( carBrakes )",
        "%vlocity_namespace%__UserDefined__c": false,
        "Name": "carBrakeCOLL",
        "VlocityDataPackType": "SObject",
        "VlocityRecordSObjectType": "%vlocity_namespace%__CalculationProcedureVariable__c",
        "VlocityRecordSourceKey": "%vlocity_namespace%__CalculationProcedureVariable__c/Generated1543850598"
    },
    {
        "%vlocity_namespace%__Alias__c": "carBrakes__carBrakeMED",
        "%vlocity_namespace%__CalculationProcedureVersionId__c": {
            "%vlocity_namespace%__CalculationProcedureId__r.Name": "autoRateVehicles",
            "%vlocity_namespace%__VersionNumber__c": 2,
            "VlocityDataPackType": "VlocityMatchingKeyObject",
            "VlocityMatchingRecordSourceKey": "%vlocity_namespace%__CalculationProcedureVersion__c/2/%vlocity_namespace%__CalculationProcedure__c/autoRateVehicles",
            "VlocityRecordSObjectType": "%vlocity_namespace%__CalculationProcedureVersion__c"
        },
        "%vlocity_namespace%__DataType__c": "Number",
        "%vlocity_namespace%__DefaultValue__c": "",
        "%vlocity_namespace%__DuplicateAlias__c": false,
        "%vlocity_namespace%__Index__c": 5,
        "%vlocity_namespace%__IsEditable__c": false,
        "%vlocity_namespace%__IsSelected__c": false,
        "%vlocity_namespace%__MatrixName__c": "carBrakes",
        "%vlocity_namespace%__Precision__c": "",
        "%vlocity_namespace%__TypeaheadDisplayName__c": "carBrakeMED ( carBrakes )",
        "%vlocity_namespace%__UserDefined__c": false,
        "Name": "carBrakeMED",
        "VlocityDataPackType": "SObject",
        "VlocityRecordSObjectType": "%vlocity_namespace%__CalculationProcedureVariable__c",
        "VlocityRecordSourceKey": "%vlocity_namespace%__CalculationProcedureVariable__c/Generated1199347610"
    },
    {
        "%vlocity_namespace%__Alias__c": "carStability",
        "%vlocity_namespace%__CalculationProcedureVersionId__c": {
            "%vlocity_namespace%__CalculationProcedureId__r.Name": "autoRateVehicles",
            "%vlocity_namespace%__VersionNumber__c": 2,
            "VlocityDataPackType": "VlocityMatchingKeyObject",
            "VlocityMatchingRecordSourceKey": "%vlocity_namespace%__CalculationProcedureVersion__c/2/%vlocity_namespace%__CalculationProcedure__c/autoRateVehicles",
            "VlocityRecordSObjectType": "%vlocity_namespace%__CalculationProcedureVersion__c"
        },
        "%vlocity_namespace%__DataType__c": "Boolean",
        "%vlocity_namespace%__DefaultValue__c": "",
        "%vlocity_namespace%__DuplicateAlias__c": false,
        "%vlocity_namespace%__Index__c": 3,
        "%vlocity_namespace%__IsEditable__c": false,
        "%vlocity_namespace%__IsSelected__c": false,
        "%vlocity_namespace%__MatrixName__c": "carStability",
        "%vlocity_namespace%__Precision__c": "",
        "%vlocity_namespace%__TypeaheadDisplayName__c": "carStability",
        "%vlocity_namespace%__UserDefined__c": false,
        "Name": "carStability",
        "VlocityDataPackType": "SObject",
        "VlocityRecordSObjectType": "%vlocity_namespace%__CalculationProcedureVariable__c",
        "VlocityRecordSourceKey": "%vlocity_namespace%__CalculationProcedureVariable__c/Generated-757694667"
    },
    {
        "%vlocity_namespace%__Alias__c": "carStability__carStabCOLL",
        "%vlocity_namespace%__CalculationProcedureVersionId__c": {
            "%vlocity_namespace%__CalculationProcedureId__r.Name": "autoRateVehicles",
            "%vlocity_namespace%__VersionNumber__c": 2,
            "VlocityDataPackType": "VlocityMatchingKeyObject",
            "VlocityMatchingRecordSourceKey": "%vlocity_namespace%__CalculationProcedureVersion__c/2/%vlocity_namespace%__CalculationProcedure__c/autoRateVehicles",
            "VlocityRecordSObjectType": "%vlocity_namespace%__CalculationProcedureVersion__c"
        },
        "%vlocity_namespace%__DataType__c": "Number",
        "%vlocity_namespace%__DefaultValue__c": "",
        "%vlocity_namespace%__DuplicateAlias__c": false,
        "%vlocity_namespace%__Index__c": 3,
        "%vlocity_namespace%__IsEditable__c": false,
        "%vlocity_namespace%__IsSelected__c": false,
        "%vlocity_namespace%__MatrixName__c": "carStability",
        "%vlocity_namespace%__Precision__c": "",
        "%vlocity_namespace%__TypeaheadDisplayName__c": "carStabCOLL ( carStability )",
        "%vlocity_namespace%__UserDefined__c": false,
        "Name": "carStabCOLL",
        "VlocityDataPackType": "SObject",
        "VlocityRecordSObjectType": "%vlocity_namespace%__CalculationProcedureVariable__c",
        "VlocityRecordSourceKey": "%vlocity_namespace%__CalculationProcedureVariable__c/Generated2120204376"
    },
    {
        "%vlocity_namespace%__Alias__c": "carSymbol__carSymbolBIPD",
        "%vlocity_namespace%__CalculationProcedureVersionId__c": {
            "%vlocity_namespace%__CalculationProcedureId__r.Name": "autoRateVehicles",
            "%vlocity_namespace%__VersionNumber__c": 2,
            "VlocityDataPackType": "VlocityMatchingKeyObject",
            "VlocityMatchingRecordSourceKey": "%vlocity_namespace%__CalculationProcedureVersion__c/2/%vlocity_namespace%__CalculationProcedure__c/autoRateVehicles",
            "VlocityRecordSObjectType": "%vlocity_namespace%__CalculationProcedureVersion__c"
        },
        "%vlocity_namespace%__DataType__c": "Number",
        "%vlocity_namespace%__DefaultValue__c": "",
        "%vlocity_namespace%__DuplicateAlias__c": false,
        "%vlocity_namespace%__Index__c": 6,
        "%vlocity_namespace%__IsEditable__c": false,
        "%vlocity_namespace%__IsSelected__c": false,
        "%vlocity_namespace%__MatrixName__c": "carSymbol",
        "%vlocity_namespace%__Precision__c": "",
        "%vlocity_namespace%__TypeaheadDisplayName__c": "carSymbolBIPD ( carSymbol )",
        "%vlocity_namespace%__UserDefined__c": false,
        "Name": "carSymbolBIPD",
        "VlocityDataPackType": "SObject",
        "VlocityRecordSObjectType": "%vlocity_namespace%__CalculationProcedureVariable__c",
        "VlocityRecordSourceKey": "%vlocity_namespace%__CalculationProcedureVariable__c/Generated-148517609"
    },
    {
        "%vlocity_namespace%__Alias__c": "carSymbol__carSymbolMED",
        "%vlocity_namespace%__CalculationProcedureVersionId__c": {
            "%vlocity_namespace%__CalculationProcedureId__r.Name": "autoRateVehicles",
            "%vlocity_namespace%__VersionNumber__c": 2,
            "VlocityDataPackType": "VlocityMatchingKeyObject",
            "VlocityMatchingRecordSourceKey": "%vlocity_namespace%__CalculationProcedureVersion__c/2/%vlocity_namespace%__CalculationProcedure__c/autoRateVehicles",
            "VlocityRecordSObjectType": "%vlocity_namespace%__CalculationProcedureVersion__c"
        },
        "%vlocity_namespace%__DataType__c": "Number",
        "%vlocity_namespace%__DefaultValue__c": "",
        "%vlocity_namespace%__DuplicateAlias__c": false,
        "%vlocity_namespace%__Index__c": 6,
        "%vlocity_namespace%__IsEditable__c": false,
        "%vlocity_namespace%__IsSelected__c": false,
        "%vlocity_namespace%__MatrixName__c": "carSymbol",
        "%vlocity_namespace%__Precision__c": "",
        "%vlocity_namespace%__TypeaheadDisplayName__c": "carSymbolMED ( carSymbol )",
        "%vlocity_namespace%__UserDefined__c": false,
        "Name": "carSymbolMED",
        "VlocityDataPackType": "SObject",
        "VlocityRecordSObjectType": "%vlocity_namespace%__CalculationProcedureVariable__c",
        "VlocityRecordSourceKey": "%vlocity_namespace%__CalculationProcedureVariable__c/Generated402603570"
    },
    {
        "%vlocity_namespace%__Alias__c": "carTheft",
        "%vlocity_namespace%__CalculationProcedureVersionId__c": {
            "%vlocity_namespace%__CalculationProcedureId__r.Name": "autoRateVehicles",
            "%vlocity_namespace%__VersionNumber__c": 2,
            "VlocityDataPackType": "VlocityMatchingKeyObject",
            "VlocityMatchingRecordSourceKey": "%vlocity_namespace%__CalculationProcedureVersion__c/2/%vlocity_namespace%__CalculationProcedure__c/autoRateVehicles",
            "VlocityRecordSObjectType": "%vlocity_namespace%__CalculationProcedureVersion__c"
        },
        "%vlocity_namespace%__DataType__c": "Boolean",
        "%vlocity_namespace%__DefaultValue__c": "",
        "%vlocity_namespace%__DuplicateAlias__c": false,
        "%vlocity_namespace%__Index__c": 4,
        "%vlocity_namespace%__IsEditable__c": false,
        "%vlocity_namespace%__IsSelected__c": false,
        "%vlocity_namespace%__MatrixName__c": "carTheft",
        "%vlocity_namespace%__Precision__c": "",
        "%vlocity_namespace%__TypeaheadDisplayName__c": "carTheft",
        "%vlocity_namespace%__UserDefined__c": false,
        "Name": "carTheft",
        "VlocityDataPackType": "SObject",
        "VlocityRecordSObjectType": "%vlocity_namespace%__CalculationProcedureVariable__c",
        "VlocityRecordSourceKey": "%vlocity_namespace%__CalculationProcedureVariable__c/Generated1345269430"
    },
    {
        "%vlocity_namespace%__Alias__c": "carTheft__carTheftCCD",
        "%vlocity_namespace%__CalculationProcedureVersionId__c": {
            "%vlocity_namespace%__CalculationProcedureId__r.Name": "autoRateVehicles",
            "%vlocity_namespace%__VersionNumber__c": 2,
            "VlocityDataPackType": "VlocityMatchingKeyObject",
            "VlocityMatchingRecordSourceKey": "%vlocity_namespace%__CalculationProcedureVersion__c/2/%vlocity_namespace%__CalculationProcedure__c/autoRateVehicles",
            "VlocityRecordSObjectType": "%vlocity_namespace%__CalculationProcedureVersion__c"
        },
        "%vlocity_namespace%__DataType__c": "Number",
        "%vlocity_namespace%__DefaultValue__c": "",
        "%vlocity_namespace%__DuplicateAlias__c": false,
        "%vlocity_namespace%__Index__c": 4,
        "%vlocity_namespace%__IsEditable__c": false,
        "%vlocity_namespace%__IsSelected__c": false,
        "%vlocity_namespace%__MatrixName__c": "carTheft",
        "%vlocity_namespace%__Precision__c": "",
        "%vlocity_namespace%__TypeaheadDisplayName__c": "carTheftCCD ( carTheft )",
        "%vlocity_namespace%__UserDefined__c": false,
        "Name": "carTheftCCD",
        "VlocityDataPackType": "SObject",
        "VlocityRecordSObjectType": "%vlocity_namespace%__CalculationProcedureVariable__c",
        "VlocityRecordSourceKey": "%vlocity_namespace%__CalculationProcedureVariable__c/Generated1101435140"
    },
    {
        "%vlocity_namespace%__Alias__c": "carValue",
        "%vlocity_namespace%__CalculationProcedureVersionId__c": {
            "%vlocity_namespace%__CalculationProcedureId__r.Name": "autoRateVehicles",
            "%vlocity_namespace%__VersionNumber__c": 2,
            "VlocityDataPackType": "VlocityMatchingKeyObject",
            "VlocityMatchingRecordSourceKey": "%vlocity_namespace%__CalculationProcedureVersion__c/2/%vlocity_namespace%__CalculationProcedure__c/autoRateVehicles",
            "VlocityRecordSObjectType": "%vlocity_namespace%__CalculationProcedureVersion__c"
        },
        "%vlocity_namespace%__DataType__c": "Number Range",
        "%vlocity_namespace%__DefaultValue__c": "",
        "%vlocity_namespace%__DuplicateAlias__c": false,
        "%vlocity_namespace%__Index__c": 0,
        "%vlocity_namespace%__IsEditable__c": false,
        "%vlocity_namespace%__IsSelected__c": false,
        "%vlocity_namespace%__MatrixName__c": "carValue",
        "%vlocity_namespace%__Precision__c": "",
        "%vlocity_namespace%__TypeaheadDisplayName__c": "carValue",
        "%vlocity_namespace%__UserDefined__c": false,
        "Name": "carValue",
        "VlocityDataPackType": "SObject",
        "VlocityRecordSObjectType": "%vlocity_namespace%__CalculationProcedureVariable__c",
        "VlocityRecordSourceKey": "%vlocity_namespace%__CalculationProcedureVariable__c/Generated-2076352852"
    },
    {
        "%vlocity_namespace%__Alias__c": "carValue__carSymbol",
        "%vlocity_namespace%__CalculationProcedureVersionId__c": {
            "%vlocity_namespace%__CalculationProcedureId__r.Name": "autoRateVehicles",
            "%vlocity_namespace%__VersionNumber__c": 2,
            "VlocityDataPackType": "VlocityMatchingKeyObject",
            "VlocityMatchingRecordSourceKey": "%vlocity_namespace%__CalculationProcedureVersion__c/2/%vlocity_namespace%__CalculationProcedure__c/autoRateVehicles",
            "VlocityRecordSObjectType": "%vlocity_namespace%__CalculationProcedureVersion__c"
        },
        "%vlocity_namespace%__DataType__c": "Text",
        "%vlocity_namespace%__DefaultValue__c": "",
        "%vlocity_namespace%__DuplicateAlias__c": false,
        "%vlocity_namespace%__Index__c": 0,
        "%vlocity_namespace%__IsEditable__c": false,
        "%vlocity_namespace%__IsSelected__c": false,
        "%vlocity_namespace%__MatrixName__c": "carValue",
        "%vlocity_namespace%__Precision__c": "",
        "%vlocity_namespace%__TypeaheadDisplayName__c": "carSymbol ( carValue )",
        "%vlocity_namespace%__UserDefined__c": false,
        "Name": "carSymbol",
        "VlocityDataPackType": "SObject",
        "VlocityRecordSObjectType": "%vlocity_namespace%__CalculationProcedureVariable__c",
        "VlocityRecordSourceKey": "%vlocity_namespace%__CalculationProcedureVariable__c/Generated-233448759"
    },
    {
        "%vlocity_namespace%__Alias__c": "carValue__carValueCCD",
        "%vlocity_namespace%__CalculationProcedureVersionId__c": {
            "%vlocity_namespace%__CalculationProcedureId__r.Name": "autoRateVehicles",
            "%vlocity_namespace%__VersionNumber__c": 2,
            "VlocityDataPackType": "VlocityMatchingKeyObject",
            "VlocityMatchingRecordSourceKey": "%vlocity_namespace%__CalculationProcedureVersion__c/2/%vlocity_namespace%__CalculationProcedure__c/autoRateVehicles",
            "VlocityRecordSObjectType": "%vlocity_namespace%__CalculationProcedureVersion__c"
        },
        "%vlocity_namespace%__DataType__c": "Number",
        "%vlocity_namespace%__DefaultValue__c": "",
        "%vlocity_namespace%__DuplicateAlias__c": false,
        "%vlocity_namespace%__Index__c": 0,
        "%vlocity_namespace%__IsEditable__c": false,
        "%vlocity_namespace%__IsSelected__c": false,
        "%vlocity_namespace%__MatrixName__c": "carValue",
        "%vlocity_namespace%__Precision__c": "",
        "%vlocity_namespace%__TypeaheadDisplayName__c": "carValueCCD ( carValue )",
        "%vlocity_namespace%__UserDefined__c": false,
        "Name": "carValueCCD",
        "VlocityDataPackType": "SObject",
        "VlocityRecordSObjectType": "%vlocity_namespace%__CalculationProcedureVariable__c",
        "VlocityRecordSourceKey": "%vlocity_namespace%__CalculationProcedureVariable__c/Generated-668593336"
    },
    {
        "%vlocity_namespace%__Alias__c": "carValue__carValueCOLL",
        "%vlocity_namespace%__CalculationProcedureVersionId__c": {
            "%vlocity_namespace%__CalculationProcedureId__r.Name": "autoRateVehicles",
            "%vlocity_namespace%__VersionNumber__c": 2,
            "VlocityDataPackType": "VlocityMatchingKeyObject",
            "VlocityMatchingRecordSourceKey": "%vlocity_namespace%__CalculationProcedureVersion__c/2/%vlocity_namespace%__CalculationProcedure__c/autoRateVehicles",
            "VlocityRecordSObjectType": "%vlocity_namespace%__CalculationProcedureVersion__c"
        },
        "%vlocity_namespace%__DataType__c": "Number",
        "%vlocity_namespace%__DefaultValue__c": "",
        "%vlocity_namespace%__DuplicateAlias__c": false,
        "%vlocity_namespace%__Index__c": 0,
        "%vlocity_namespace%__IsEditable__c": false,
        "%vlocity_namespace%__IsSelected__c": false,
        "%vlocity_namespace%__MatrixName__c": "carValue",
        "%vlocity_namespace%__Precision__c": "",
        "%vlocity_namespace%__TypeaheadDisplayName__c": "carValueCOLL ( carValue )",
        "%vlocity_namespace%__UserDefined__c": false,
        "Name": "carValueCOLL",
        "VlocityDataPackType": "SObject",
        "VlocityRecordSObjectType": "%vlocity_namespace%__CalculationProcedureVariable__c",
        "VlocityRecordSourceKey": "%vlocity_namespace%__CalculationProcedureVariable__c/Generated261597884"
    },
    {
        "%vlocity_namespace%__Alias__c": "carYear",
        "%vlocity_namespace%__CalculationProcedureVersionId__c": {
            "%vlocity_namespace%__CalculationProcedureId__r.Name": "autoRateVehicles",
            "%vlocity_namespace%__VersionNumber__c": 2,
            "VlocityDataPackType": "VlocityMatchingKeyObject",
            "VlocityMatchingRecordSourceKey": "%vlocity_namespace%__CalculationProcedureVersion__c/2/%vlocity_namespace%__CalculationProcedure__c/autoRateVehicles",
            "VlocityRecordSObjectType": "%vlocity_namespace%__CalculationProcedureVersion__c"
        },
        "%vlocity_namespace%__DataType__c": "Number Range",
        "%vlocity_namespace%__DefaultValue__c": "",
        "%vlocity_namespace%__DuplicateAlias__c": false,
        "%vlocity_namespace%__Index__c": 1,
        "%vlocity_namespace%__IsEditable__c": false,
        "%vlocity_namespace%__IsSelected__c": false,
        "%vlocity_namespace%__MatrixName__c": "carYear",
        "%vlocity_namespace%__Precision__c": "",
        "%vlocity_namespace%__TypeaheadDisplayName__c": "carYear",
        "%vlocity_namespace%__UserDefined__c": false,
        "Name": "carYear",
        "VlocityDataPackType": "SObject",
        "VlocityRecordSObjectType": "%vlocity_namespace%__CalculationProcedureVariable__c",
        "VlocityRecordSourceKey": "%vlocity_namespace%__CalculationProcedureVariable__c/Generated-1077851127"
    },
    {
        "%vlocity_namespace%__Alias__c": "carYear__carYearBIPD",
        "%vlocity_namespace%__CalculationProcedureVersionId__c": {
            "%vlocity_namespace%__CalculationProcedureId__r.Name": "autoRateVehicles",
            "%vlocity_namespace%__VersionNumber__c": 2,
            "VlocityDataPackType": "VlocityMatchingKeyObject",
            "VlocityMatchingRecordSourceKey": "%vlocity_namespace%__CalculationProcedureVersion__c/2/%vlocity_namespace%__CalculationProcedure__c/autoRateVehicles",
            "VlocityRecordSObjectType": "%vlocity_namespace%__CalculationProcedureVersion__c"
        },
        "%vlocity_namespace%__DataType__c": "Number",
        "%vlocity_namespace%__DefaultValue__c": "",
        "%vlocity_namespace%__DuplicateAlias__c": false,
        "%vlocity_namespace%__Index__c": 1,
        "%vlocity_namespace%__IsEditable__c": false,
        "%vlocity_namespace%__IsSelected__c": false,
        "%vlocity_namespace%__MatrixName__c": "carYear",
        "%vlocity_namespace%__Precision__c": "",
        "%vlocity_namespace%__TypeaheadDisplayName__c": "carYearBIPD ( carYear )",
        "%vlocity_namespace%__UserDefined__c": false,
        "Name": "carYearBIPD",
        "VlocityDataPackType": "SObject",
        "VlocityRecordSObjectType": "%vlocity_namespace%__CalculationProcedureVariable__c",
        "VlocityRecordSourceKey": "%vlocity_namespace%__CalculationProcedureVariable__c/Generated627491250"
    },
    {
        "%vlocity_namespace%__Alias__c": "carYear__carYearCCD",
        "%vlocity_namespace%__CalculationProcedureVersionId__c": {
            "%vlocity_namespace%__CalculationProcedureId__r.Name": "autoRateVehicles",
            "%vlocity_namespace%__VersionNumber__c": 2,
            "VlocityDataPackType": "VlocityMatchingKeyObject",
            "VlocityMatchingRecordSourceKey": "%vlocity_namespace%__CalculationProcedureVersion__c/2/%vlocity_namespace%__CalculationProcedure__c/autoRateVehicles",
            "VlocityRecordSObjectType": "%vlocity_namespace%__CalculationProcedureVersion__c"
        },
        "%vlocity_namespace%__DataType__c": "Number",
        "%vlocity_namespace%__DefaultValue__c": "",
        "%vlocity_namespace%__DuplicateAlias__c": false,
        "%vlocity_namespace%__Index__c": 1,
        "%vlocity_namespace%__IsEditable__c": false,
        "%vlocity_namespace%__IsSelected__c": false,
        "%vlocity_namespace%__MatrixName__c": "carYear",
        "%vlocity_namespace%__Precision__c": "",
        "%vlocity_namespace%__TypeaheadDisplayName__c": "carYearCCD ( carYear )",
        "%vlocity_namespace%__UserDefined__c": false,
        "Name": "carYearCCD",
        "VlocityDataPackType": "SObject",
        "VlocityRecordSObjectType": "%vlocity_namespace%__CalculationProcedureVariable__c",
        "VlocityRecordSourceKey": "%vlocity_namespace%__CalculationProcedureVariable__c/Generated-1809506619"
    },
    {
        "%vlocity_namespace%__Alias__c": "carYear__carYearCOLL",
        "%vlocity_namespace%__CalculationProcedureVersionId__c": {
            "%vlocity_namespace%__CalculationProcedureId__r.Name": "autoRateVehicles",
            "%vlocity_namespace%__VersionNumber__c": 2,
            "VlocityDataPackType": "VlocityMatchingKeyObject",
            "VlocityMatchingRecordSourceKey": "%vlocity_namespace%__CalculationProcedureVersion__c/2/%vlocity_namespace%__CalculationProcedure__c/autoRateVehicles",
            "VlocityRecordSObjectType": "%vlocity_namespace%__CalculationProcedureVersion__c"
        },
        "%vlocity_namespace%__DataType__c": "Number",
        "%vlocity_namespace%__DefaultValue__c": "",
        "%vlocity_namespace%__DuplicateAlias__c": false,
        "%vlocity_namespace%__Index__c": 1,
        "%vlocity_namespace%__IsEditable__c": false,
        "%vlocity_namespace%__IsSelected__c": false,
        "%vlocity_namespace%__MatrixName__c": "carYear",
        "%vlocity_namespace%__Precision__c": "",
        "%vlocity_namespace%__TypeaheadDisplayName__c": "carYearCOLL ( carYear )",
        "%vlocity_namespace%__UserDefined__c": false,
        "Name": "carYearCOLL",
        "VlocityDataPackType": "SObject",
        "VlocityRecordSObjectType": "%vlocity_namespace%__CalculationProcedureVariable__c",
        "VlocityRecordSourceKey": "%vlocity_namespace%__CalculationProcedureVariable__c/Generated-135904511"
    },
    {
        "%vlocity_namespace%__Alias__c": "carYear__carYearMED",
        "%vlocity_namespace%__CalculationProcedureVersionId__c": {
            "%vlocity_namespace%__CalculationProcedureId__r.Name": "autoRateVehicles",
            "%vlocity_namespace%__VersionNumber__c": 2,
            "VlocityDataPackType": "VlocityMatchingKeyObject",
            "VlocityMatchingRecordSourceKey": "%vlocity_namespace%__CalculationProcedureVersion__c/2/%vlocity_namespace%__CalculationProcedure__c/autoRateVehicles",
            "VlocityRecordSObjectType": "%vlocity_namespace%__CalculationProcedureVersion__c"
        },
        "%vlocity_namespace%__DataType__c": "Number",
        "%vlocity_namespace%__DefaultValue__c": "",
        "%vlocity_namespace%__DuplicateAlias__c": false,
        "%vlocity_namespace%__Index__c": 1,
        "%vlocity_namespace%__IsEditable__c": false,
        "%vlocity_namespace%__IsSelected__c": false,
        "%vlocity_namespace%__MatrixName__c": "carYear",
        "%vlocity_namespace%__Precision__c": "",
        "%vlocity_namespace%__TypeaheadDisplayName__c": "carYearMED ( carYear )",
        "%vlocity_namespace%__UserDefined__c": false,
        "Name": "carYearMED",
        "VlocityDataPackType": "SObject",
        "VlocityRecordSObjectType": "%vlocity_namespace%__CalculationProcedureVariable__c",
        "VlocityRecordSourceKey": "%vlocity_namespace%__CalculationProcedureVariable__c/Generated2110162829"
    },
    {
        "%vlocity_namespace%__Alias__c": "carYear__carYearUM",
        "%vlocity_namespace%__CalculationProcedureVersionId__c": {
            "%vlocity_namespace%__CalculationProcedureId__r.Name": "autoRateVehicles",
            "%vlocity_namespace%__VersionNumber__c": 2,
            "VlocityDataPackType": "VlocityMatchingKeyObject",
            "VlocityMatchingRecordSourceKey": "%vlocity_namespace%__CalculationProcedureVersion__c/2/%vlocity_namespace%__CalculationProcedure__c/autoRateVehicles",
            "VlocityRecordSObjectType": "%vlocity_namespace%__CalculationProcedureVersion__c"
        },
        "%vlocity_namespace%__DataType__c": "Number",
        "%vlocity_namespace%__DefaultValue__c": "",
        "%vlocity_namespace%__DuplicateAlias__c": false,
        "%vlocity_namespace%__Index__c": 1,
        "%vlocity_namespace%__IsEditable__c": false,
        "%vlocity_namespace%__IsSelected__c": false,
        "%vlocity_namespace%__MatrixName__c": "carYear",
        "%vlocity_namespace%__Precision__c": "",
        "%vlocity_namespace%__TypeaheadDisplayName__c": "carYearUM ( carYear )",
        "%vlocity_namespace%__UserDefined__c": false,
        "Name": "carYearUM",
        "VlocityDataPackType": "SObject",
        "VlocityRecordSObjectType": "%vlocity_namespace%__CalculationProcedureVariable__c",
        "VlocityRecordSourceKey": "%vlocity_namespace%__CalculationProcedureVariable__c/Generated-1545934635"
    },
    {
        "%vlocity_namespace%__Alias__c": "dedCCD",
        "%vlocity_namespace%__CalculationProcedureVersionId__c": {
            "%vlocity_namespace%__CalculationProcedureId__r.Name": "autoRateVehicles",
            "%vlocity_namespace%__VersionNumber__c": 2,
            "VlocityDataPackType": "VlocityMatchingKeyObject",
            "VlocityMatchingRecordSourceKey": "%vlocity_namespace%__CalculationProcedureVersion__c/2/%vlocity_namespace%__CalculationProcedure__c/autoRateVehicles",
            "VlocityRecordSObjectType": "%vlocity_namespace%__CalculationProcedureVersion__c"
        },
        "%vlocity_namespace%__DataType__c": "Number",
        "%vlocity_namespace%__DefaultValue__c": "",
        "%vlocity_namespace%__DuplicateAlias__c": false,
        "%vlocity_namespace%__Index__c": 17,
        "%vlocity_namespace%__IsEditable__c": false,
        "%vlocity_namespace%__IsSelected__c": false,
        "%vlocity_namespace%__MatrixName__c": "deductCCD",
        "%vlocity_namespace%__Precision__c": "",
        "%vlocity_namespace%__TypeaheadDisplayName__c": "dedCCD",
        "%vlocity_namespace%__UserDefined__c": false,
        "Name": "dedCCD",
        "VlocityDataPackType": "SObject",
        "VlocityRecordSObjectType": "%vlocity_namespace%__CalculationProcedureVariable__c",
        "VlocityRecordSourceKey": "%vlocity_namespace%__CalculationProcedureVariable__c/Generated-618055615"
    },
    {
        "%vlocity_namespace%__Alias__c": "dedCOLL",
        "%vlocity_namespace%__CalculationProcedureVersionId__c": {
            "%vlocity_namespace%__CalculationProcedureId__r.Name": "autoRateVehicles",
            "%vlocity_namespace%__VersionNumber__c": 2,
            "VlocityDataPackType": "VlocityMatchingKeyObject",
            "VlocityMatchingRecordSourceKey": "%vlocity_namespace%__CalculationProcedureVersion__c/2/%vlocity_namespace%__CalculationProcedure__c/autoRateVehicles",
            "VlocityRecordSObjectType": "%vlocity_namespace%__CalculationProcedureVersion__c"
        },
        "%vlocity_namespace%__DataType__c": "Number",
        "%vlocity_namespace%__DefaultValue__c": "",
        "%vlocity_namespace%__DuplicateAlias__c": false,
        "%vlocity_namespace%__Index__c": 15,
        "%vlocity_namespace%__IsEditable__c": false,
        "%vlocity_namespace%__IsSelected__c": false,
        "%vlocity_namespace%__MatrixName__c": "deductCOLL",
        "%vlocity_namespace%__Precision__c": "",
        "%vlocity_namespace%__TypeaheadDisplayName__c": "dedCOLL",
        "%vlocity_namespace%__UserDefined__c": false,
        "Name": "dedCOLL",
        "VlocityDataPackType": "SObject",
        "VlocityRecordSObjectType": "%vlocity_namespace%__CalculationProcedureVariable__c",
        "VlocityRecordSourceKey": "%vlocity_namespace%__CalculationProcedureVariable__c/Generated-1972152001"
    },
    {
        "%vlocity_namespace%__Alias__c": "deductCCD__dedCCD-Ded",
        "%vlocity_namespace%__CalculationProcedureVersionId__c": {
            "%vlocity_namespace%__CalculationProcedureId__r.Name": "autoRateVehicles",
            "%vlocity_namespace%__VersionNumber__c": 2,
            "VlocityDataPackType": "VlocityMatchingKeyObject",
            "VlocityMatchingRecordSourceKey": "%vlocity_namespace%__CalculationProcedureVersion__c/2/%vlocity_namespace%__CalculationProcedure__c/autoRateVehicles",
            "VlocityRecordSObjectType": "%vlocity_namespace%__CalculationProcedureVersion__c"
        },
        "%vlocity_namespace%__DataType__c": "Number",
        "%vlocity_namespace%__DefaultValue__c": "",
        "%vlocity_namespace%__DuplicateAlias__c": false,
        "%vlocity_namespace%__Index__c": 17,
        "%vlocity_namespace%__IsEditable__c": false,
        "%vlocity_namespace%__IsSelected__c": false,
        "%vlocity_namespace%__MatrixName__c": "deductCCD",
        "%vlocity_namespace%__Precision__c": "",
        "%vlocity_namespace%__TypeaheadDisplayName__c": "dedCCD-Ded ( deductCCD )",
        "%vlocity_namespace%__UserDefined__c": false,
        "Name": "dedCCD-Ded",
        "VlocityDataPackType": "SObject",
        "VlocityRecordSObjectType": "%vlocity_namespace%__CalculationProcedureVariable__c",
        "VlocityRecordSourceKey": "%vlocity_namespace%__CalculationProcedureVariable__c/Generated2136202158"
    },
    {
        "%vlocity_namespace%__Alias__c": "deductCOLL__dedCOLL-Ded",
        "%vlocity_namespace%__CalculationProcedureVersionId__c": {
            "%vlocity_namespace%__CalculationProcedureId__r.Name": "autoRateVehicles",
            "%vlocity_namespace%__VersionNumber__c": 2,
            "VlocityDataPackType": "VlocityMatchingKeyObject",
            "VlocityMatchingRecordSourceKey": "%vlocity_namespace%__CalculationProcedureVersion__c/2/%vlocity_namespace%__CalculationProcedure__c/autoRateVehicles",
            "VlocityRecordSObjectType": "%vlocity_namespace%__CalculationProcedureVersion__c"
        },
        "%vlocity_namespace%__DataType__c": "Number",
        "%vlocity_namespace%__DefaultValue__c": "",
        "%vlocity_namespace%__DuplicateAlias__c": false,
        "%vlocity_namespace%__Index__c": 15,
        "%vlocity_namespace%__IsEditable__c": false,
        "%vlocity_namespace%__IsSelected__c": false,
        "%vlocity_namespace%__MatrixName__c": "deductCOLL",
        "%vlocity_namespace%__Precision__c": "",
        "%vlocity_namespace%__TypeaheadDisplayName__c": "dedCOLL-Ded ( deductCOLL )",
        "%vlocity_namespace%__UserDefined__c": false,
        "Name": "dedCOLL-Ded",
        "VlocityDataPackType": "SObject",
        "VlocityRecordSObjectType": "%vlocity_namespace%__CalculationProcedureVariable__c",
        "VlocityRecordSourceKey": "%vlocity_namespace%__CalculationProcedureVariable__c/Generated-796462006"
    },
    {
        "%vlocity_namespace%__Alias__c": "limitBI",
        "%vlocity_namespace%__CalculationProcedureVersionId__c": {
            "%vlocity_namespace%__CalculationProcedureId__r.Name": "autoRateVehicles",
            "%vlocity_namespace%__VersionNumber__c": 2,
            "VlocityDataPackType": "VlocityMatchingKeyObject",
            "VlocityMatchingRecordSourceKey": "%vlocity_namespace%__CalculationProcedureVersion__c/2/%vlocity_namespace%__CalculationProcedure__c/autoRateVehicles",
            "VlocityRecordSObjectType": "%vlocity_namespace%__CalculationProcedureVersion__c"
        },
        "%vlocity_namespace%__DataType__c": "Text",
        "%vlocity_namespace%__DefaultValue__c": "",
        "%vlocity_namespace%__DuplicateAlias__c": false,
        "%vlocity_namespace%__Index__c": 12,
        "%vlocity_namespace%__IsEditable__c": false,
        "%vlocity_namespace%__IsSelected__c": false,
        "%vlocity_namespace%__MatrixName__c": "limitBI",
        "%vlocity_namespace%__Precision__c": "",
        "%vlocity_namespace%__TypeaheadDisplayName__c": "limitBI",
        "%vlocity_namespace%__UserDefined__c": false,
        "Name": "limitBI",
        "VlocityDataPackType": "SObject",
        "VlocityRecordSObjectType": "%vlocity_namespace%__CalculationProcedureVariable__c",
        "VlocityRecordSourceKey": "%vlocity_namespace%__CalculationProcedureVariable__c/Generated1781266550"
    },
    {
        "%vlocity_namespace%__Alias__c": "limitBI__factorLimitBI",
        "%vlocity_namespace%__CalculationProcedureVersionId__c": {
            "%vlocity_namespace%__CalculationProcedureId__r.Name": "autoRateVehicles",
            "%vlocity_namespace%__VersionNumber__c": 2,
            "VlocityDataPackType": "VlocityMatchingKeyObject",
            "VlocityMatchingRecordSourceKey": "%vlocity_namespace%__CalculationProcedureVersion__c/2/%vlocity_namespace%__CalculationProcedure__c/autoRateVehicles",
            "VlocityRecordSObjectType": "%vlocity_namespace%__CalculationProcedureVersion__c"
        },
        "%vlocity_namespace%__DataType__c": "Number",
        "%vlocity_namespace%__DefaultValue__c": "",
        "%vlocity_namespace%__DuplicateAlias__c": false,
        "%vlocity_namespace%__Index__c": 12,
        "%vlocity_namespace%__IsEditable__c": false,
        "%vlocity_namespace%__IsSelected__c": false,
        "%vlocity_namespace%__MatrixName__c": "limitBI",
        "%vlocity_namespace%__Precision__c": "",
        "%vlocity_namespace%__TypeaheadDisplayName__c": "factorLimitBI ( limitBI )",
        "%vlocity_namespace%__UserDefined__c": false,
        "Name": "factorLimitBI",
        "VlocityDataPackType": "SObject",
        "VlocityRecordSObjectType": "%vlocity_namespace%__CalculationProcedureVariable__c",
        "VlocityRecordSourceKey": "%vlocity_namespace%__CalculationProcedureVariable__c/Generated-1410227754"
    },
    {
        "%vlocity_namespace%__Alias__c": "limitMED",
        "%vlocity_namespace%__CalculationProcedureVersionId__c": {
            "%vlocity_namespace%__CalculationProcedureId__r.Name": "autoRateVehicles",
            "%vlocity_namespace%__VersionNumber__c": 2,
            "VlocityDataPackType": "VlocityMatchingKeyObject",
            "VlocityMatchingRecordSourceKey": "%vlocity_namespace%__CalculationProcedureVersion__c/2/%vlocity_namespace%__CalculationProcedure__c/autoRateVehicles",
            "VlocityRecordSObjectType": "%vlocity_namespace%__CalculationProcedureVersion__c"
        },
        "%vlocity_namespace%__DataType__c": "Number",
        "%vlocity_namespace%__DefaultValue__c": "",
        "%vlocity_namespace%__DuplicateAlias__c": false,
        "%vlocity_namespace%__Index__c": 16,
        "%vlocity_namespace%__IsEditable__c": false,
        "%vlocity_namespace%__IsSelected__c": false,
        "%vlocity_namespace%__MatrixName__c": "limitMED",
        "%vlocity_namespace%__Precision__c": "",
        "%vlocity_namespace%__TypeaheadDisplayName__c": "limitMED",
        "%vlocity_namespace%__UserDefined__c": false,
        "Name": "limitMED",
        "VlocityDataPackType": "SObject",
        "VlocityRecordSObjectType": "%vlocity_namespace%__CalculationProcedureVariable__c",
        "VlocityRecordSourceKey": "%vlocity_namespace%__CalculationProcedureVariable__c/Generated-1624008864"
    },
    {
        "%vlocity_namespace%__Alias__c": "limitMED__factorLimitMED",
        "%vlocity_namespace%__CalculationProcedureVersionId__c": {
            "%vlocity_namespace%__CalculationProcedureId__r.Name": "autoRateVehicles",
            "%vlocity_namespace%__VersionNumber__c": 2,
            "VlocityDataPackType": "VlocityMatchingKeyObject",
            "VlocityMatchingRecordSourceKey": "%vlocity_namespace%__CalculationProcedureVersion__c/2/%vlocity_namespace%__CalculationProcedure__c/autoRateVehicles",
            "VlocityRecordSObjectType": "%vlocity_namespace%__CalculationProcedureVersion__c"
        },
        "%vlocity_namespace%__DataType__c": "Number",
        "%vlocity_namespace%__DefaultValue__c": "",
        "%vlocity_namespace%__DuplicateAlias__c": false,
        "%vlocity_namespace%__Index__c": 16,
        "%vlocity_namespace%__IsEditable__c": false,
        "%vlocity_namespace%__IsSelected__c": false,
        "%vlocity_namespace%__MatrixName__c": "limitMED",
        "%vlocity_namespace%__Precision__c": "",
        "%vlocity_namespace%__TypeaheadDisplayName__c": "factorLimitMED ( limitMED )",
        "%vlocity_namespace%__UserDefined__c": false,
        "Name": "factorLimitMED",
        "VlocityDataPackType": "SObject",
        "VlocityRecordSObjectType": "%vlocity_namespace%__CalculationProcedureVariable__c",
        "VlocityRecordSourceKey": "%vlocity_namespace%__CalculationProcedureVariable__c/Generated-1246992304"
    },
    {
        "%vlocity_namespace%__Alias__c": "limitPD",
        "%vlocity_namespace%__CalculationProcedureVersionId__c": {
            "%vlocity_namespace%__CalculationProcedureId__r.Name": "autoRateVehicles",
            "%vlocity_namespace%__VersionNumber__c": 2,
            "VlocityDataPackType": "VlocityMatchingKeyObject",
            "VlocityMatchingRecordSourceKey": "%vlocity_namespace%__CalculationProcedureVersion__c/2/%vlocity_namespace%__CalculationProcedure__c/autoRateVehicles",
            "VlocityRecordSObjectType": "%vlocity_namespace%__CalculationProcedureVersion__c"
        },
        "%vlocity_namespace%__DataType__c": "Number",
        "%vlocity_namespace%__DefaultValue__c": "",
        "%vlocity_namespace%__DuplicateAlias__c": false,
        "%vlocity_namespace%__Index__c": 13,
        "%vlocity_namespace%__IsEditable__c": false,
        "%vlocity_namespace%__IsSelected__c": false,
        "%vlocity_namespace%__MatrixName__c": "limitPD",
        "%vlocity_namespace%__Precision__c": "",
        "%vlocity_namespace%__TypeaheadDisplayName__c": "limitPD",
        "%vlocity_namespace%__UserDefined__c": false,
        "Name": "limitPD",
        "VlocityDataPackType": "SObject",
        "VlocityRecordSObjectType": "%vlocity_namespace%__CalculationProcedureVariable__c",
        "VlocityRecordSourceKey": "%vlocity_namespace%__CalculationProcedureVariable__c/Generated769584497"
    },
    {
        "%vlocity_namespace%__Alias__c": "limitPD__factorPDDed",
        "%vlocity_namespace%__CalculationProcedureVersionId__c": {
            "%vlocity_namespace%__CalculationProcedureId__r.Name": "autoRateVehicles",
            "%vlocity_namespace%__VersionNumber__c": 2,
            "VlocityDataPackType": "VlocityMatchingKeyObject",
            "VlocityMatchingRecordSourceKey": "%vlocity_namespace%__CalculationProcedureVersion__c/2/%vlocity_namespace%__CalculationProcedure__c/autoRateVehicles",
            "VlocityRecordSObjectType": "%vlocity_namespace%__CalculationProcedureVersion__c"
        },
        "%vlocity_namespace%__DataType__c": "Number",
        "%vlocity_namespace%__DefaultValue__c": "",
        "%vlocity_namespace%__DuplicateAlias__c": false,
        "%vlocity_namespace%__Index__c": 13,
        "%vlocity_namespace%__IsEditable__c": false,
        "%vlocity_namespace%__IsSelected__c": false,
        "%vlocity_namespace%__MatrixName__c": "limitPD",
        "%vlocity_namespace%__Precision__c": "",
        "%vlocity_namespace%__TypeaheadDisplayName__c": "factorPDDed ( limitPD )",
        "%vlocity_namespace%__UserDefined__c": false,
        "Name": "factorPDDed",
        "VlocityDataPackType": "SObject",
        "VlocityRecordSObjectType": "%vlocity_namespace%__CalculationProcedureVariable__c",
        "VlocityRecordSourceKey": "%vlocity_namespace%__CalculationProcedureVariable__c/Generated-1164243333"
    },
    {
        "%vlocity_namespace%__Alias__c": "limitPerAcc",
        "%vlocity_namespace%__CalculationProcedureVersionId__c": {
            "%vlocity_namespace%__CalculationProcedureId__r.Name": "autoRateVehicles",
            "%vlocity_namespace%__VersionNumber__c": 2,
            "VlocityDataPackType": "VlocityMatchingKeyObject",
            "VlocityMatchingRecordSourceKey": "%vlocity_namespace%__CalculationProcedureVersion__c/2/%vlocity_namespace%__CalculationProcedure__c/autoRateVehicles",
            "VlocityRecordSObjectType": "%vlocity_namespace%__CalculationProcedureVersion__c"
        },
        "%vlocity_namespace%__DataType__c": "Number",
        "%vlocity_namespace%__DefaultValue__c": "",
        "%vlocity_namespace%__DuplicateAlias__c": false,
        "%vlocity_namespace%__Index__c": 22,
        "%vlocity_namespace%__IsEditable__c": false,
        "%vlocity_namespace%__IsSelected__c": false,
        "%vlocity_namespace%__MatrixName__c": "autoLimitBIPD",
        "%vlocity_namespace%__Precision__c": "",
        "%vlocity_namespace%__TypeaheadDisplayName__c": "limitPerAcc",
        "%vlocity_namespace%__UserDefined__c": false,
        "Name": "limitPerAcc",
        "VlocityDataPackType": "SObject",
        "VlocityRecordSObjectType": "%vlocity_namespace%__CalculationProcedureVariable__c",
        "VlocityRecordSourceKey": "%vlocity_namespace%__CalculationProcedureVariable__c/Generated393854219"
    },
    {
        "%vlocity_namespace%__Alias__c": "limitPerPerson",
        "%vlocity_namespace%__CalculationProcedureVersionId__c": {
            "%vlocity_namespace%__CalculationProcedureId__r.Name": "autoRateVehicles",
            "%vlocity_namespace%__VersionNumber__c": 2,
            "VlocityDataPackType": "VlocityMatchingKeyObject",
            "VlocityMatchingRecordSourceKey": "%vlocity_namespace%__CalculationProcedureVersion__c/2/%vlocity_namespace%__CalculationProcedure__c/autoRateVehicles",
            "VlocityRecordSObjectType": "%vlocity_namespace%__CalculationProcedureVersion__c"
        },
        "%vlocity_namespace%__DataType__c": "Number",
        "%vlocity_namespace%__DefaultValue__c": "",
        "%vlocity_namespace%__DuplicateAlias__c": false,
        "%vlocity_namespace%__Index__c": 22,
        "%vlocity_namespace%__IsEditable__c": false,
        "%vlocity_namespace%__IsSelected__c": false,
        "%vlocity_namespace%__MatrixName__c": "autoLimitBIPD",
        "%vlocity_namespace%__Precision__c": "",
        "%vlocity_namespace%__TypeaheadDisplayName__c": "limitPerPerson",
        "%vlocity_namespace%__UserDefined__c": false,
        "Name": "limitPerPerson",
        "VlocityDataPackType": "SObject",
        "VlocityRecordSObjectType": "%vlocity_namespace%__CalculationProcedureVariable__c",
        "VlocityRecordSourceKey": "%vlocity_namespace%__CalculationProcedureVariable__c/Generated-71288413"
    },
    {
        "%vlocity_namespace%__Alias__c": "limitRental",
        "%vlocity_namespace%__CalculationProcedureVersionId__c": {
            "%vlocity_namespace%__CalculationProcedureId__r.Name": "autoRateVehicles",
            "%vlocity_namespace%__VersionNumber__c": 2,
            "VlocityDataPackType": "VlocityMatchingKeyObject",
            "VlocityMatchingRecordSourceKey": "%vlocity_namespace%__CalculationProcedureVersion__c/2/%vlocity_namespace%__CalculationProcedure__c/autoRateVehicles",
            "VlocityRecordSObjectType": "%vlocity_namespace%__CalculationProcedureVersion__c"
        },
        "%vlocity_namespace%__DataType__c": "Number",
        "%vlocity_namespace%__DefaultValue__c": "",
        "%vlocity_namespace%__DuplicateAlias__c": false,
        "%vlocity_namespace%__Index__c": "",
        "%vlocity_namespace%__IsEditable__c": false,
        "%vlocity_namespace%__IsSelected__c": false,
        "%vlocity_namespace%__MatrixName__c": "",
        "%vlocity_namespace%__Precision__c": "",
        "%vlocity_namespace%__TypeaheadDisplayName__c": "",
        "%vlocity_namespace%__UserDefined__c": true,
        "Name": "limitRental",
        "VlocityDataPackType": "SObject",
        "VlocityRecordSObjectType": "%vlocity_namespace%__CalculationProcedureVariable__c",
        "VlocityRecordSourceKey": "%vlocity_namespace%__CalculationProcedureVariable__c/Generated829394658"
    },
    {
        "%vlocity_namespace%__Alias__c": "limitUM",
        "%vlocity_namespace%__CalculationProcedureVersionId__c": {
            "%vlocity_namespace%__CalculationProcedureId__r.Name": "autoRateVehicles",
            "%vlocity_namespace%__VersionNumber__c": 2,
            "VlocityDataPackType": "VlocityMatchingKeyObject",
            "VlocityMatchingRecordSourceKey": "%vlocity_namespace%__CalculationProcedureVersion__c/2/%vlocity_namespace%__CalculationProcedure__c/autoRateVehicles",
            "VlocityRecordSObjectType": "%vlocity_namespace%__CalculationProcedureVersion__c"
        },
        "%vlocity_namespace%__DataType__c": "Text",
        "%vlocity_namespace%__DefaultValue__c": "",
        "%vlocity_namespace%__DuplicateAlias__c": false,
        "%vlocity_namespace%__Index__c": 14,
        "%vlocity_namespace%__IsEditable__c": false,
        "%vlocity_namespace%__IsSelected__c": false,
        "%vlocity_namespace%__MatrixName__c": "limitUM",
        "%vlocity_namespace%__Precision__c": "",
        "%vlocity_namespace%__TypeaheadDisplayName__c": "limitUM",
        "%vlocity_namespace%__UserDefined__c": false,
        "Name": "limitUM",
        "VlocityDataPackType": "SObject",
        "VlocityRecordSObjectType": "%vlocity_namespace%__CalculationProcedureVariable__c",
        "VlocityRecordSourceKey": "%vlocity_namespace%__CalculationProcedureVariable__c/Generated-240075788"
    },
    {
        "%vlocity_namespace%__Alias__c": "limitUM__factorLimitUM",
        "%vlocity_namespace%__CalculationProcedureVersionId__c": {
            "%vlocity_namespace%__CalculationProcedureId__r.Name": "autoRateVehicles",
            "%vlocity_namespace%__VersionNumber__c": 2,
            "VlocityDataPackType": "VlocityMatchingKeyObject",
            "VlocityMatchingRecordSourceKey": "%vlocity_namespace%__CalculationProcedureVersion__c/2/%vlocity_namespace%__CalculationProcedure__c/autoRateVehicles",
            "VlocityRecordSObjectType": "%vlocity_namespace%__CalculationProcedureVersion__c"
        },
        "%vlocity_namespace%__DataType__c": "Number",
        "%vlocity_namespace%__DefaultValue__c": "",
        "%vlocity_namespace%__DuplicateAlias__c": false,
        "%vlocity_namespace%__Index__c": 14,
        "%vlocity_namespace%__IsEditable__c": false,
        "%vlocity_namespace%__IsSelected__c": false,
        "%vlocity_namespace%__MatrixName__c": "limitUM",
        "%vlocity_namespace%__Precision__c": "",
        "%vlocity_namespace%__TypeaheadDisplayName__c": "factorLimitUM ( limitUM )",
        "%vlocity_namespace%__UserDefined__c": false,
        "Name": "factorLimitUM",
        "VlocityDataPackType": "SObject",
        "VlocityRecordSObjectType": "%vlocity_namespace%__CalculationProcedureVariable__c",
        "VlocityRecordSourceKey": "%vlocity_namespace%__CalculationProcedureVariable__c/Generated-879169422"
    },
    {
        "%vlocity_namespace%__Alias__c": "premiumBIPD",
        "%vlocity_namespace%__CalculationProcedureVersionId__c": {
            "%vlocity_namespace%__CalculationProcedureId__r.Name": "autoRateVehicles",
            "%vlocity_namespace%__VersionNumber__c": 2,
            "VlocityDataPackType": "VlocityMatchingKeyObject",
            "VlocityMatchingRecordSourceKey": "%vlocity_namespace%__CalculationProcedureVersion__c/2/%vlocity_namespace%__CalculationProcedure__c/autoRateVehicles",
            "VlocityRecordSObjectType": "%vlocity_namespace%__CalculationProcedureVersion__c"
        },
        "%vlocity_namespace%__DataType__c": "Currency",
        "%vlocity_namespace%__DefaultValue__c": "0",
        "%vlocity_namespace%__DuplicateAlias__c": false,
        "%vlocity_namespace%__Index__c": "",
        "%vlocity_namespace%__IsEditable__c": false,
        "%vlocity_namespace%__IsSelected__c": false,
        "%vlocity_namespace%__MatrixName__c": "",
        "%vlocity_namespace%__Precision__c": 2,
        "%vlocity_namespace%__TypeaheadDisplayName__c": "",
        "%vlocity_namespace%__UserDefined__c": true,
        "Name": "premiumBIPD",
        "VlocityDataPackType": "SObject",
        "VlocityRecordSObjectType": "%vlocity_namespace%__CalculationProcedureVariable__c",
        "VlocityRecordSourceKey": "%vlocity_namespace%__CalculationProcedureVariable__c/Generated1454387674"
    },
    {
        "%vlocity_namespace%__Alias__c": "premiumCCD",
        "%vlocity_namespace%__CalculationProcedureVersionId__c": {
            "%vlocity_namespace%__CalculationProcedureId__r.Name": "autoRateVehicles",
            "%vlocity_namespace%__VersionNumber__c": 2,
            "VlocityDataPackType": "VlocityMatchingKeyObject",
            "VlocityMatchingRecordSourceKey": "%vlocity_namespace%__CalculationProcedureVersion__c/2/%vlocity_namespace%__CalculationProcedure__c/autoRateVehicles",
            "VlocityRecordSObjectType": "%vlocity_namespace%__CalculationProcedureVersion__c"
        },
        "%vlocity_namespace%__DataType__c": "Currency",
        "%vlocity_namespace%__DefaultValue__c": "0",
        "%vlocity_namespace%__DuplicateAlias__c": false,
        "%vlocity_namespace%__Index__c": "",
        "%vlocity_namespace%__IsEditable__c": false,
        "%vlocity_namespace%__IsSelected__c": false,
        "%vlocity_namespace%__MatrixName__c": "",
        "%vlocity_namespace%__Precision__c": 2,
        "%vlocity_namespace%__TypeaheadDisplayName__c": "",
        "%vlocity_namespace%__UserDefined__c": true,
        "Name": "premiumCCD",
        "VlocityDataPackType": "SObject",
        "VlocityRecordSObjectType": "%vlocity_namespace%__CalculationProcedureVariable__c",
        "VlocityRecordSourceKey": "%vlocity_namespace%__CalculationProcedureVariable__c/Generated-1818771302"
    },
    {
        "%vlocity_namespace%__Alias__c": "premiumCOLL",
        "%vlocity_namespace%__CalculationProcedureVersionId__c": {
            "%vlocity_namespace%__CalculationProcedureId__r.Name": "autoRateVehicles",
            "%vlocity_namespace%__VersionNumber__c": 2,
            "VlocityDataPackType": "VlocityMatchingKeyObject",
            "VlocityMatchingRecordSourceKey": "%vlocity_namespace%__CalculationProcedureVersion__c/2/%vlocity_namespace%__CalculationProcedure__c/autoRateVehicles",
            "VlocityRecordSObjectType": "%vlocity_namespace%__CalculationProcedureVersion__c"
        },
        "%vlocity_namespace%__DataType__c": "Currency",
        "%vlocity_namespace%__DefaultValue__c": "0",
        "%vlocity_namespace%__DuplicateAlias__c": false,
        "%vlocity_namespace%__Index__c": "",
        "%vlocity_namespace%__IsEditable__c": false,
        "%vlocity_namespace%__IsSelected__c": false,
        "%vlocity_namespace%__MatrixName__c": "",
        "%vlocity_namespace%__Precision__c": 2,
        "%vlocity_namespace%__TypeaheadDisplayName__c": "",
        "%vlocity_namespace%__UserDefined__c": true,
        "Name": "premiumCOLL",
        "VlocityDataPackType": "SObject",
        "VlocityRecordSObjectType": "%vlocity_namespace%__CalculationProcedureVariable__c",
        "VlocityRecordSourceKey": "%vlocity_namespace%__CalculationProcedureVariable__c/Generated1835886586"
    },
    {
        "%vlocity_namespace%__Alias__c": "premiumMED",
        "%vlocity_namespace%__CalculationProcedureVersionId__c": {
            "%vlocity_namespace%__CalculationProcedureId__r.Name": "autoRateVehicles",
            "%vlocity_namespace%__VersionNumber__c": 2,
            "VlocityDataPackType": "VlocityMatchingKeyObject",
            "VlocityMatchingRecordSourceKey": "%vlocity_namespace%__CalculationProcedureVersion__c/2/%vlocity_namespace%__CalculationProcedure__c/autoRateVehicles",
            "VlocityRecordSObjectType": "%vlocity_namespace%__CalculationProcedureVersion__c"
        },
        "%vlocity_namespace%__DataType__c": "Currency",
        "%vlocity_namespace%__DefaultValue__c": "0",
        "%vlocity_namespace%__DuplicateAlias__c": false,
        "%vlocity_namespace%__Index__c": "",
        "%vlocity_namespace%__IsEditable__c": false,
        "%vlocity_namespace%__IsSelected__c": false,
        "%vlocity_namespace%__MatrixName__c": "",
        "%vlocity_namespace%__Precision__c": 2,
        "%vlocity_namespace%__TypeaheadDisplayName__c": "",
        "%vlocity_namespace%__UserDefined__c": true,
        "Name": "premiumMED",
        "VlocityDataPackType": "SObject",
        "VlocityRecordSObjectType": "%vlocity_namespace%__CalculationProcedureVariable__c",
        "VlocityRecordSourceKey": "%vlocity_namespace%__CalculationProcedureVariable__c/Generated663381034"
    },
    {
        "%vlocity_namespace%__Alias__c": "premiumRental",
        "%vlocity_namespace%__CalculationProcedureVersionId__c": {
            "%vlocity_namespace%__CalculationProcedureId__r.Name": "autoRateVehicles",
            "%vlocity_namespace%__VersionNumber__c": 2,
            "VlocityDataPackType": "VlocityMatchingKeyObject",
            "VlocityMatchingRecordSourceKey": "%vlocity_namespace%__CalculationProcedureVersion__c/2/%vlocity_namespace%__CalculationProcedure__c/autoRateVehicles",
            "VlocityRecordSObjectType": "%vlocity_namespace%__CalculationProcedureVersion__c"
        },
        "%vlocity_namespace%__DataType__c": "Currency",
        "%vlocity_namespace%__DefaultValue__c": "0",
        "%vlocity_namespace%__DuplicateAlias__c": false,
        "%vlocity_namespace%__Index__c": "",
        "%vlocity_namespace%__IsEditable__c": false,
        "%vlocity_namespace%__IsSelected__c": false,
        "%vlocity_namespace%__MatrixName__c": "",
        "%vlocity_namespace%__Precision__c": 2,
        "%vlocity_namespace%__TypeaheadDisplayName__c": "",
        "%vlocity_namespace%__UserDefined__c": true,
        "Name": "premiumRental",
        "VlocityDataPackType": "SObject",
        "VlocityRecordSObjectType": "%vlocity_namespace%__CalculationProcedureVariable__c",
        "VlocityRecordSourceKey": "%vlocity_namespace%__CalculationProcedureVariable__c/Generated-1020694406"
    },
    {
        "%vlocity_namespace%__Alias__c": "premiumUM",
        "%vlocity_namespace%__CalculationProcedureVersionId__c": {
            "%vlocity_namespace%__CalculationProcedureId__r.Name": "autoRateVehicles",
            "%vlocity_namespace%__VersionNumber__c": 2,
            "VlocityDataPackType": "VlocityMatchingKeyObject",
            "VlocityMatchingRecordSourceKey": "%vlocity_namespace%__CalculationProcedureVersion__c/2/%vlocity_namespace%__CalculationProcedure__c/autoRateVehicles",
            "VlocityRecordSObjectType": "%vlocity_namespace%__CalculationProcedureVersion__c"
        },
        "%vlocity_namespace%__DataType__c": "Currency",
        "%vlocity_namespace%__DefaultValue__c": "0",
        "%vlocity_namespace%__DuplicateAlias__c": false,
        "%vlocity_namespace%__Index__c": "",
        "%vlocity_namespace%__IsEditable__c": false,
        "%vlocity_namespace%__IsSelected__c": false,
        "%vlocity_namespace%__MatrixName__c": "",
        "%vlocity_namespace%__Precision__c": 2,
        "%vlocity_namespace%__TypeaheadDisplayName__c": "",
        "%vlocity_namespace%__UserDefined__c": true,
        "Name": "premiumUM",
        "VlocityDataPackType": "SObject",
        "VlocityRecordSObjectType": "%vlocity_namespace%__CalculationProcedureVariable__c",
        "VlocityRecordSourceKey": "%vlocity_namespace%__CalculationProcedureVariable__c/Generated-1907696902"
    },
    {
        "%vlocity_namespace%__Alias__c": "ratedDriver-BIPD",
        "%vlocity_namespace%__CalculationProcedureVersionId__c": {
            "%vlocity_namespace%__CalculationProcedureId__r.Name": "autoRateVehicles",
            "%vlocity_namespace%__VersionNumber__c": 2,
            "VlocityDataPackType": "VlocityMatchingKeyObject",
            "VlocityMatchingRecordSourceKey": "%vlocity_namespace%__CalculationProcedureVersion__c/2/%vlocity_namespace%__CalculationProcedure__c/autoRateVehicles",
            "VlocityRecordSObjectType": "%vlocity_namespace%__CalculationProcedureVersion__c"
        },
        "%vlocity_namespace%__DataType__c": "Number",
        "%vlocity_namespace%__DefaultValue__c": "1",
        "%vlocity_namespace%__DuplicateAlias__c": false,
        "%vlocity_namespace%__Index__c": "",
        "%vlocity_namespace%__IsEditable__c": false,
        "%vlocity_namespace%__IsSelected__c": false,
        "%vlocity_namespace%__MatrixName__c": "",
        "%vlocity_namespace%__Precision__c": 2,
        "%vlocity_namespace%__TypeaheadDisplayName__c": "",
        "%vlocity_namespace%__UserDefined__c": true,
        "Name": "ratedDriver-BIPD",
        "VlocityDataPackType": "SObject",
        "VlocityRecordSObjectType": "%vlocity_namespace%__CalculationProcedureVariable__c",
        "VlocityRecordSourceKey": "%vlocity_namespace%__CalculationProcedureVariable__c/Generated1807331407"
    },
    {
        "%vlocity_namespace%__Alias__c": "ratedDriver-CCD",
        "%vlocity_namespace%__CalculationProcedureVersionId__c": {
            "%vlocity_namespace%__CalculationProcedureId__r.Name": "autoRateVehicles",
            "%vlocity_namespace%__VersionNumber__c": 2,
            "VlocityDataPackType": "VlocityMatchingKeyObject",
            "VlocityMatchingRecordSourceKey": "%vlocity_namespace%__CalculationProcedureVersion__c/2/%vlocity_namespace%__CalculationProcedure__c/autoRateVehicles",
            "VlocityRecordSObjectType": "%vlocity_namespace%__CalculationProcedureVersion__c"
        },
        "%vlocity_namespace%__DataType__c": "Number",
        "%vlocity_namespace%__DefaultValue__c": "1",
        "%vlocity_namespace%__DuplicateAlias__c": true,
        "%vlocity_namespace%__Index__c": "",
        "%vlocity_namespace%__IsEditable__c": false,
        "%vlocity_namespace%__IsSelected__c": false,
        "%vlocity_namespace%__MatrixName__c": "",
        "%vlocity_namespace%__Precision__c": 2,
        "%vlocity_namespace%__TypeaheadDisplayName__c": "",
        "%vlocity_namespace%__UserDefined__c": true,
        "Name": "ratedDriver-CCD",
        "VlocityDataPackType": "SObject",
        "VlocityRecordSObjectType": "%vlocity_namespace%__CalculationProcedureVariable__c",
        "VlocityRecordSourceKey": "%vlocity_namespace%__CalculationProcedureVariable__c/Generated-1627718672"
    },
    {
        "%vlocity_namespace%__Alias__c": "ratedDriver-COLL",
        "%vlocity_namespace%__CalculationProcedureVersionId__c": {
            "%vlocity_namespace%__CalculationProcedureId__r.Name": "autoRateVehicles",
            "%vlocity_namespace%__VersionNumber__c": 2,
            "VlocityDataPackType": "VlocityMatchingKeyObject",
            "VlocityMatchingRecordSourceKey": "%vlocity_namespace%__CalculationProcedureVersion__c/2/%vlocity_namespace%__CalculationProcedure__c/autoRateVehicles",
            "VlocityRecordSObjectType": "%vlocity_namespace%__CalculationProcedureVersion__c"
        },
        "%vlocity_namespace%__DataType__c": "Number",
        "%vlocity_namespace%__DefaultValue__c": "1",
        "%vlocity_namespace%__DuplicateAlias__c": true,
        "%vlocity_namespace%__Index__c": "",
        "%vlocity_namespace%__IsEditable__c": false,
        "%vlocity_namespace%__IsSelected__c": false,
        "%vlocity_namespace%__MatrixName__c": "",
        "%vlocity_namespace%__Precision__c": 2,
        "%vlocity_namespace%__TypeaheadDisplayName__c": "",
        "%vlocity_namespace%__UserDefined__c": true,
        "Name": "ratedDriver-COLL",
        "VlocityDataPackType": "SObject",
        "VlocityRecordSObjectType": "%vlocity_namespace%__CalculationProcedureVariable__c",
        "VlocityRecordSourceKey": "%vlocity_namespace%__CalculationProcedureVariable__c/Generated641617728"
    },
    {
        "%vlocity_namespace%__Alias__c": "ratedDriver-MED",
        "%vlocity_namespace%__CalculationProcedureVersionId__c": {
            "%vlocity_namespace%__CalculationProcedureId__r.Name": "autoRateVehicles",
            "%vlocity_namespace%__VersionNumber__c": 2,
            "VlocityDataPackType": "VlocityMatchingKeyObject",
            "VlocityMatchingRecordSourceKey": "%vlocity_namespace%__CalculationProcedureVersion__c/2/%vlocity_namespace%__CalculationProcedure__c/autoRateVehicles",
            "VlocityRecordSObjectType": "%vlocity_namespace%__CalculationProcedureVersion__c"
        },
        "%vlocity_namespace%__DataType__c": "Number",
        "%vlocity_namespace%__DefaultValue__c": "1",
        "%vlocity_namespace%__DuplicateAlias__c": true,
        "%vlocity_namespace%__Index__c": "",
        "%vlocity_namespace%__IsEditable__c": false,
        "%vlocity_namespace%__IsSelected__c": false,
        "%vlocity_namespace%__MatrixName__c": "",
        "%vlocity_namespace%__Precision__c": 2,
        "%vlocity_namespace%__TypeaheadDisplayName__c": "",
        "%vlocity_namespace%__UserDefined__c": true,
        "Name": "ratedDriver-MED",
        "VlocityDataPackType": "SObject",
        "VlocityRecordSObjectType": "%vlocity_namespace%__CalculationProcedureVariable__c",
        "VlocityRecordSourceKey": "%vlocity_namespace%__CalculationProcedureVariable__c/Generated-27767424"
    },
    {
        "%vlocity_namespace%__Alias__c": "ratedDriver-UM",
        "%vlocity_namespace%__CalculationProcedureVersionId__c": {
            "%vlocity_namespace%__CalculationProcedureId__r.Name": "autoRateVehicles",
            "%vlocity_namespace%__VersionNumber__c": 2,
            "VlocityDataPackType": "VlocityMatchingKeyObject",
            "VlocityMatchingRecordSourceKey": "%vlocity_namespace%__CalculationProcedureVersion__c/2/%vlocity_namespace%__CalculationProcedure__c/autoRateVehicles",
            "VlocityRecordSObjectType": "%vlocity_namespace%__CalculationProcedureVersion__c"
        },
        "%vlocity_namespace%__DataType__c": "Number",
        "%vlocity_namespace%__DefaultValue__c": "1",
        "%vlocity_namespace%__DuplicateAlias__c": true,
        "%vlocity_namespace%__Index__c": "",
        "%vlocity_namespace%__IsEditable__c": false,
        "%vlocity_namespace%__IsSelected__c": false,
        "%vlocity_namespace%__MatrixName__c": "",
        "%vlocity_namespace%__Precision__c": 2,
        "%vlocity_namespace%__TypeaheadDisplayName__c": "",
        "%vlocity_namespace%__UserDefined__c": true,
        "Name": "ratedDriver-UM",
        "VlocityDataPackType": "SObject",
        "VlocityRecordSObjectType": "%vlocity_namespace%__CalculationProcedureVariable__c",
        "VlocityRecordSourceKey": "%vlocity_namespace%__CalculationProcedureVariable__c/Generated109052480"
    }
]