[
    {
        "%vlocity_namespace%__DomainObjectAPIName__c": "Formula",
        "%vlocity_namespace%__DomainObjectCreationOrder__c": 0,
        "%vlocity_namespace%__DomainObjectFieldAPIName__c": "Formula",
        "%vlocity_namespace%__FormulaOrder__c": 1,
        "%vlocity_namespace%__FormulaResultPath__c": "GraceperiodStartDate",
        "%vlocity_namespace%__Formula__c": "ADDDAY(quoteDetails:quoteEffectiveDate,1)",
        "%vlocity_namespace%__GlobalKey__c": "a640c696-d906-73a9-0a05-76a00959e33f",
        "%vlocity_namespace%__IsDisabled__c": false,
        "%vlocity_namespace%__IsRequiredForUpsert__c": false,
        "%vlocity_namespace%__MapId__c": "Ins_TransToCreatePolicy_IssueOSCustom3815",
        "%vlocity_namespace%__UpsertKey__c": false,
        "Name": "Ins_TransToCreatePolicy_IssueOS",
        "VlocityDataPackType": "SObject",
        "VlocityRecordSObjectType": "%vlocity_namespace%__DRMapItem__c"
    },
    {
        "%vlocity_namespace%__DomainObjectAPIName__c": "Formula",
        "%vlocity_namespace%__DomainObjectCreationOrder__c": 0,
        "%vlocity_namespace%__DomainObjectFieldAPIName__c": "Formula",
        "%vlocity_namespace%__FormulaOrder__c": 2,
        "%vlocity_namespace%__FormulaResultPath__c": "GracePeriodEndDate",
        "%vlocity_namespace%__Formula__c": "ADDDAY(quoteDetails:quoteEffectiveDate,31)",
        "%vlocity_namespace%__GlobalKey__c": "7a097ca9-c25b-2041-959a-ee3dfc7bf077",
        "%vlocity_namespace%__IsDisabled__c": false,
        "%vlocity_namespace%__IsRequiredForUpsert__c": false,
        "%vlocity_namespace%__MapId__c": "Ins_TransToCreatePolicy_IssueOSCustom581",
        "%vlocity_namespace%__UpsertKey__c": false,
        "Name": "Ins_TransToCreatePolicy_IssueOS",
        "VlocityDataPackType": "SObject",
        "VlocityRecordSObjectType": "%vlocity_namespace%__DRMapItem__c"
    },
    {
        "%vlocity_namespace%__DomainObjectAPIName__c": "json",
        "%vlocity_namespace%__DomainObjectCreationOrder__c": 1,
        "%vlocity_namespace%__DomainObjectFieldAPIName__c": "quotepolicyJson:accountId",
        "%vlocity_namespace%__GlobalKey__c": "a265dbf4-b700-098b-390b-b3a0e9b0f23f",
        "%vlocity_namespace%__InterfaceFieldAPIName__c": "AccountId",
        "%vlocity_namespace%__IsDisabled__c": false,
        "%vlocity_namespace%__IsRequiredForUpsert__c": false,
        "%vlocity_namespace%__MapId__c": "Ins_TransToCreatePolicy_IssueOSCustoma1T3k000006n2g2EAAItem5",
        "%vlocity_namespace%__UpsertKey__c": false,
        "Name": "Ins_TransToCreatePolicy_IssueOS",
        "VlocityDataPackType": "SObject",
        "VlocityRecordSObjectType": "%vlocity_namespace%__DRMapItem__c"
    },
    {
        "%vlocity_namespace%__DomainObjectAPIName__c": "json",
        "%vlocity_namespace%__DomainObjectCreationOrder__c": 1,
        "%vlocity_namespace%__DomainObjectFieldAPIName__c": "quotepolicyJson:additionalFields:%vlocity_namespace%__AutomaticPaymentAmount__c",
        "%vlocity_namespace%__GlobalKey__c": "e1b0110e-da67-63b4-a48d-4f1ddfbc19e6",
        "%vlocity_namespace%__InterfaceFieldAPIName__c": "BalanceDueAmt",
        "%vlocity_namespace%__IsDisabled__c": false,
        "%vlocity_namespace%__IsRequiredForUpsert__c": false,
        "%vlocity_namespace%__MapId__c": "Ins_TransToCreatePolicy_IssueOSCustom1645",
        "%vlocity_namespace%__UpsertKey__c": false,
        "Name": "Ins_TransToCreatePolicy_IssueOS",
        "VlocityDataPackType": "SObject",
        "VlocityRecordSObjectType": "%vlocity_namespace%__DRMapItem__c"
    },
    {
        "%vlocity_namespace%__DomainObjectAPIName__c": "json",
        "%vlocity_namespace%__DomainObjectCreationOrder__c": 1,
        "%vlocity_namespace%__DomainObjectFieldAPIName__c": "quotepolicyJson:additionalFields:%vlocity_namespace%__AutomaticPaymentAmount__c",
        "%vlocity_namespace%__GlobalKey__c": "72a3f69c-7523-f38e-0c3f-9151cf3268bd",
        "%vlocity_namespace%__InterfaceFieldAPIName__c": "paymentDetails:BalanceDueAmt",
        "%vlocity_namespace%__IsDisabled__c": false,
        "%vlocity_namespace%__IsRequiredForUpsert__c": false,
        "%vlocity_namespace%__MapId__c": "Ins_TransToCreatePolicy_IssueOSCustom3219",
        "%vlocity_namespace%__UpsertKey__c": false,
        "Name": "Ins_TransToCreatePolicy_IssueOS",
        "VlocityDataPackType": "SObject",
        "VlocityRecordSObjectType": "%vlocity_namespace%__DRMapItem__c"
    },
    {
        "%vlocity_namespace%__DomainObjectAPIName__c": "json",
        "%vlocity_namespace%__DomainObjectCreationOrder__c": 1,
        "%vlocity_namespace%__DomainObjectFieldAPIName__c": "quotepolicyJson:additionalFields:%vlocity_namespace%__BillDeliveryMethod__c",
        "%vlocity_namespace%__GlobalKey__c": "786c70c1-7bef-dfda-2db8-6c92d93d5502",
        "%vlocity_namespace%__InterfaceFieldAPIName__c": "billMethod:billDeliveryMethod",
        "%vlocity_namespace%__IsDisabled__c": false,
        "%vlocity_namespace%__IsRequiredForUpsert__c": false,
        "%vlocity_namespace%__MapId__c": "Ins_TransToCreatePolicy_IssueOSCustom3457",
        "%vlocity_namespace%__UpsertKey__c": false,
        "Name": "Ins_TransToCreatePolicy_IssueOS",
        "VlocityDataPackType": "SObject",
        "VlocityRecordSObjectType": "%vlocity_namespace%__DRMapItem__c"
    },
    {
        "%vlocity_namespace%__DomainObjectAPIName__c": "json",
        "%vlocity_namespace%__DomainObjectCreationOrder__c": 1,
        "%vlocity_namespace%__DomainObjectFieldAPIName__c": "quotepolicyJson:additionalFields:%vlocity_namespace%__BillDueDate__c",
        "%vlocity_namespace%__GlobalKey__c": "564a5dfb-4358-2690-27db-7c036d1c66af",
        "%vlocity_namespace%__InterfaceFieldAPIName__c": "quoteDetails:quoteEffectiveDate",
        "%vlocity_namespace%__IsDisabled__c": false,
        "%vlocity_namespace%__IsRequiredForUpsert__c": false,
        "%vlocity_namespace%__MapId__c": "Ins_TransToCreatePolicy_IssueOSCustom114",
        "%vlocity_namespace%__UpsertKey__c": false,
        "Name": "Ins_TransToCreatePolicy_IssueOS",
        "VlocityDataPackType": "SObject",
        "VlocityRecordSObjectType": "%vlocity_namespace%__DRMapItem__c"
    },
    {
        "%vlocity_namespace%__DomainObjectAPIName__c": "json",
        "%vlocity_namespace%__DomainObjectCreationOrder__c": 1,
        "%vlocity_namespace%__DomainObjectFieldAPIName__c": "quotepolicyJson:additionalFields:%vlocity_namespace%__BillingAccountId__c",
        "%vlocity_namespace%__GlobalKey__c": "875521dc-1159-ac13-f4bc-32834d6d62a2",
        "%vlocity_namespace%__InterfaceFieldAPIName__c": "DRId_%vlocity_namespace%__BillingAccount__c",
        "%vlocity_namespace%__IsDisabled__c": false,
        "%vlocity_namespace%__IsRequiredForUpsert__c": false,
        "%vlocity_namespace%__MapId__c": "Ins_TransToCreatePolicy_IssueOSCustom6692",
        "%vlocity_namespace%__UpsertKey__c": false,
        "Name": "Ins_TransToCreatePolicy_IssueOS",
        "VlocityDataPackType": "SObject",
        "VlocityRecordSObjectType": "%vlocity_namespace%__DRMapItem__c"
    },
    {
        "%vlocity_namespace%__DomainObjectAPIName__c": "json",
        "%vlocity_namespace%__DomainObjectCreationOrder__c": 1,
        "%vlocity_namespace%__DomainObjectFieldAPIName__c": "quotepolicyJson:additionalFields:%vlocity_namespace%__BillingCity__c",
        "%vlocity_namespace%__GlobalKey__c": "495e0e3c-8ecc-2a60-c9d2-c8d8a82f6a59",
        "%vlocity_namespace%__InterfaceFieldAPIName__c": "billMethod:billAddress:billingAddress-Block:City",
        "%vlocity_namespace%__IsDisabled__c": false,
        "%vlocity_namespace%__IsRequiredForUpsert__c": false,
        "%vlocity_namespace%__MapId__c": "Ins_TransToCreatePolicy_IssueOSCustom5372",
        "%vlocity_namespace%__UpsertKey__c": false,
        "Name": "Ins_TransToCreatePolicy_IssueOS",
        "VlocityDataPackType": "SObject",
        "VlocityRecordSObjectType": "%vlocity_namespace%__DRMapItem__c"
    },
    {
        "%vlocity_namespace%__DomainObjectAPIName__c": "json",
        "%vlocity_namespace%__DomainObjectCreationOrder__c": 1,
        "%vlocity_namespace%__DomainObjectFieldAPIName__c": "quotepolicyJson:additionalFields:%vlocity_namespace%__BillingCity__c",
        "%vlocity_namespace%__GlobalKey__c": "3a812add-a5e1-f03a-885b-6423c44a6e41",
        "%vlocity_namespace%__InterfaceFieldAPIName__c": "billMethod:billingCity",
        "%vlocity_namespace%__IsDisabled__c": false,
        "%vlocity_namespace%__IsRequiredForUpsert__c": false,
        "%vlocity_namespace%__MapId__c": "Ins_TransToCreatePolicy_IssueOSCustom441",
        "%vlocity_namespace%__UpsertKey__c": false,
        "Name": "Ins_TransToCreatePolicy_IssueOS",
        "VlocityDataPackType": "SObject",
        "VlocityRecordSObjectType": "%vlocity_namespace%__DRMapItem__c"
    },
    {
        "%vlocity_namespace%__DomainObjectAPIName__c": "json",
        "%vlocity_namespace%__DomainObjectCreationOrder__c": 1,
        "%vlocity_namespace%__DomainObjectFieldAPIName__c": "quotepolicyJson:additionalFields:%vlocity_namespace%__BillingCountry__c",
        "%vlocity_namespace%__GlobalKey__c": "de8f0b71-913f-a506-4ff8-333219d867e5",
        "%vlocity_namespace%__InterfaceFieldAPIName__c": "billMethod:billAddress:billingAddress-Block:Country",
        "%vlocity_namespace%__IsDisabled__c": false,
        "%vlocity_namespace%__IsRequiredForUpsert__c": false,
        "%vlocity_namespace%__MapId__c": "Ins_TransToCreatePolicy_IssueOSCustom1471",
        "%vlocity_namespace%__UpsertKey__c": false,
        "Name": "Ins_TransToCreatePolicy_IssueOS",
        "VlocityDataPackType": "SObject",
        "VlocityRecordSObjectType": "%vlocity_namespace%__DRMapItem__c"
    },
    {
        "%vlocity_namespace%__DomainObjectAPIName__c": "json",
        "%vlocity_namespace%__DomainObjectCreationOrder__c": 1,
        "%vlocity_namespace%__DomainObjectFieldAPIName__c": "quotepolicyJson:additionalFields:%vlocity_namespace%__BillingEmail__c",
        "%vlocity_namespace%__GlobalKey__c": "4191a8a9-f501-1995-12b1-d8b42767a106",
        "%vlocity_namespace%__InterfaceFieldAPIName__c": "Email",
        "%vlocity_namespace%__IsDisabled__c": false,
        "%vlocity_namespace%__IsRequiredForUpsert__c": false,
        "%vlocity_namespace%__MapId__c": "Ins_TransToCreatePolicy_IssueOSCustom8217",
        "%vlocity_namespace%__UpsertKey__c": false,
        "Name": "Ins_TransToCreatePolicy_IssueOS",
        "VlocityDataPackType": "SObject",
        "VlocityRecordSObjectType": "%vlocity_namespace%__DRMapItem__c"
    },
    {
        "%vlocity_namespace%__DomainObjectAPIName__c": "json",
        "%vlocity_namespace%__DomainObjectCreationOrder__c": 1,
        "%vlocity_namespace%__DomainObjectFieldAPIName__c": "quotepolicyJson:additionalFields:%vlocity_namespace%__BillingFrequency__c",
        "%vlocity_namespace%__GlobalKey__c": "b6285a72-37ce-6511-5a50-46530e1f4a1d",
        "%vlocity_namespace%__InterfaceFieldAPIName__c": "BillFrequency",
        "%vlocity_namespace%__IsDisabled__c": false,
        "%vlocity_namespace%__IsRequiredForUpsert__c": false,
        "%vlocity_namespace%__MapId__c": "Ins_TransToCreatePolicy_IssueOSCustoma1T3k000006n2g2EAAItem1",
        "%vlocity_namespace%__UpsertKey__c": false,
        "Name": "Ins_TransToCreatePolicy_IssueOS",
        "VlocityDataPackType": "SObject",
        "VlocityRecordSObjectType": "%vlocity_namespace%__DRMapItem__c"
    },
    {
        "%vlocity_namespace%__DomainObjectAPIName__c": "json",
        "%vlocity_namespace%__DomainObjectCreationOrder__c": 1,
        "%vlocity_namespace%__DomainObjectFieldAPIName__c": "quotepolicyJson:additionalFields:%vlocity_namespace%__BillingMethod__c",
        "%vlocity_namespace%__GlobalKey__c": "216af53a-4b95-1180-e348-54cb37bb8655",
        "%vlocity_namespace%__InterfaceFieldAPIName__c": "billingOptionsSetUp:billingOptions",
        "%vlocity_namespace%__IsDisabled__c": false,
        "%vlocity_namespace%__IsRequiredForUpsert__c": false,
        "%vlocity_namespace%__MapId__c": "Ins_TransToCreatePolicy_IssueOSCustoma1T3k000006n2g2EAAItem4",
        "%vlocity_namespace%__UpsertKey__c": false,
        "Name": "Ins_TransToCreatePolicy_IssueOS",
        "VlocityDataPackType": "SObject",
        "VlocityRecordSObjectType": "%vlocity_namespace%__DRMapItem__c"
    },
    {
        "%vlocity_namespace%__DomainObjectAPIName__c": "json",
        "%vlocity_namespace%__DomainObjectCreationOrder__c": 1,
        "%vlocity_namespace%__DomainObjectFieldAPIName__c": "quotepolicyJson:additionalFields:%vlocity_namespace%__BillingPostalCode__c",
        "%vlocity_namespace%__GlobalKey__c": "f8d93848-71de-d2f8-78b5-79207890d756",
        "%vlocity_namespace%__InterfaceFieldAPIName__c": "billMethod:billAddress:billingAddress-Block:PostalCode",
        "%vlocity_namespace%__IsDisabled__c": false,
        "%vlocity_namespace%__IsRequiredForUpsert__c": false,
        "%vlocity_namespace%__MapId__c": "Ins_TransToCreatePolicy_IssueOSCustom5095",
        "%vlocity_namespace%__UpsertKey__c": false,
        "Name": "Ins_TransToCreatePolicy_IssueOS",
        "VlocityDataPackType": "SObject",
        "VlocityRecordSObjectType": "%vlocity_namespace%__DRMapItem__c"
    },
    {
        "%vlocity_namespace%__DomainObjectAPIName__c": "json",
        "%vlocity_namespace%__DomainObjectCreationOrder__c": 1,
        "%vlocity_namespace%__DomainObjectFieldAPIName__c": "quotepolicyJson:additionalFields:%vlocity_namespace%__BillingPostalCode__c",
        "%vlocity_namespace%__GlobalKey__c": "f8ede1c1-5dca-9dd0-de51-2475cab06781",
        "%vlocity_namespace%__InterfaceFieldAPIName__c": "billMethod:billingPostalCode",
        "%vlocity_namespace%__IsDisabled__c": false,
        "%vlocity_namespace%__IsRequiredForUpsert__c": false,
        "%vlocity_namespace%__MapId__c": "Ins_TransToCreatePolicy_IssueOSCustom2878",
        "%vlocity_namespace%__UpsertKey__c": false,
        "Name": "Ins_TransToCreatePolicy_IssueOS",
        "VlocityDataPackType": "SObject",
        "VlocityRecordSObjectType": "%vlocity_namespace%__DRMapItem__c"
    },
    {
        "%vlocity_namespace%__DomainObjectAPIName__c": "json",
        "%vlocity_namespace%__DomainObjectCreationOrder__c": 1,
        "%vlocity_namespace%__DomainObjectFieldAPIName__c": "quotepolicyJson:additionalFields:%vlocity_namespace%__BillingState__c",
        "%vlocity_namespace%__GlobalKey__c": "53c5d634-8ccb-bda8-e0a5-d74595e5a291",
        "%vlocity_namespace%__InterfaceFieldAPIName__c": "billMethod:billAddress:billingAddress-Block:State",
        "%vlocity_namespace%__IsDisabled__c": false,
        "%vlocity_namespace%__IsRequiredForUpsert__c": false,
        "%vlocity_namespace%__MapId__c": "Ins_TransToCreatePolicy_IssueOSCustoma1T3k000006n2g2EAAItem3",
        "%vlocity_namespace%__UpsertKey__c": false,
        "Name": "Ins_TransToCreatePolicy_IssueOS",
        "VlocityDataPackType": "SObject",
        "VlocityRecordSObjectType": "%vlocity_namespace%__DRMapItem__c"
    },
    {
        "%vlocity_namespace%__DomainObjectAPIName__c": "json",
        "%vlocity_namespace%__DomainObjectCreationOrder__c": 1,
        "%vlocity_namespace%__DomainObjectFieldAPIName__c": "quotepolicyJson:additionalFields:%vlocity_namespace%__BillingState__c",
        "%vlocity_namespace%__GlobalKey__c": "cbf58216-213c-e243-abec-04c747285b17",
        "%vlocity_namespace%__InterfaceFieldAPIName__c": "billMethod:billingState",
        "%vlocity_namespace%__IsDisabled__c": false,
        "%vlocity_namespace%__IsRequiredForUpsert__c": false,
        "%vlocity_namespace%__MapId__c": "Ins_TransToCreatePolicy_IssueOSCustom5387",
        "%vlocity_namespace%__UpsertKey__c": false,
        "Name": "Ins_TransToCreatePolicy_IssueOS",
        "VlocityDataPackType": "SObject",
        "VlocityRecordSObjectType": "%vlocity_namespace%__DRMapItem__c"
    },
    {
        "%vlocity_namespace%__DomainObjectAPIName__c": "json",
        "%vlocity_namespace%__DomainObjectCreationOrder__c": 1,
        "%vlocity_namespace%__DomainObjectFieldAPIName__c": "quotepolicyJson:additionalFields:%vlocity_namespace%__BillingStreet__c",
        "%vlocity_namespace%__GlobalKey__c": "1e354a95-18a0-f2f8-89be-24bd015e314e",
        "%vlocity_namespace%__InterfaceFieldAPIName__c": "billMethod:billAddress:billingAddress-Block:Street",
        "%vlocity_namespace%__IsDisabled__c": false,
        "%vlocity_namespace%__IsRequiredForUpsert__c": false,
        "%vlocity_namespace%__MapId__c": "Ins_TransToCreatePolicy_IssueOSCustom6815",
        "%vlocity_namespace%__UpsertKey__c": false,
        "Name": "Ins_TransToCreatePolicy_IssueOS",
        "VlocityDataPackType": "SObject",
        "VlocityRecordSObjectType": "%vlocity_namespace%__DRMapItem__c"
    },
    {
        "%vlocity_namespace%__DomainObjectAPIName__c": "json",
        "%vlocity_namespace%__DomainObjectCreationOrder__c": 1,
        "%vlocity_namespace%__DomainObjectFieldAPIName__c": "quotepolicyJson:additionalFields:%vlocity_namespace%__BillingStreet__c",
        "%vlocity_namespace%__GlobalKey__c": "b8f62e7d-5435-19c3-e7d6-90392e6f9f72",
        "%vlocity_namespace%__InterfaceFieldAPIName__c": "billMethod:billingStreet",
        "%vlocity_namespace%__IsDisabled__c": false,
        "%vlocity_namespace%__IsRequiredForUpsert__c": false,
        "%vlocity_namespace%__MapId__c": "Ins_TransToCreatePolicy_IssueOSCustom5526",
        "%vlocity_namespace%__UpsertKey__c": false,
        "Name": "Ins_TransToCreatePolicy_IssueOS",
        "VlocityDataPackType": "SObject",
        "VlocityRecordSObjectType": "%vlocity_namespace%__DRMapItem__c"
    },
    {
        "%vlocity_namespace%__DomainObjectAPIName__c": "json",
        "%vlocity_namespace%__DomainObjectCreationOrder__c": 1,
        "%vlocity_namespace%__DomainObjectFieldAPIName__c": "quotepolicyJson:additionalFields:%vlocity_namespace%__GracePeriodEndDate__c",
        "%vlocity_namespace%__GlobalKey__c": "398d7782-74d6-74e4-e4ac-9fccc1693fa3",
        "%vlocity_namespace%__InterfaceFieldAPIName__c": "GracePeriodEndDate",
        "%vlocity_namespace%__IsDisabled__c": false,
        "%vlocity_namespace%__IsRequiredForUpsert__c": false,
        "%vlocity_namespace%__MapId__c": "Ins_TransToCreatePolicy_IssueOSCustom987",
        "%vlocity_namespace%__UpsertKey__c": false,
        "Name": "Ins_TransToCreatePolicy_IssueOS",
        "VlocityDataPackType": "SObject",
        "VlocityRecordSObjectType": "%vlocity_namespace%__DRMapItem__c"
    },
    {
        "%vlocity_namespace%__DomainObjectAPIName__c": "json",
        "%vlocity_namespace%__DomainObjectCreationOrder__c": 1,
        "%vlocity_namespace%__DomainObjectFieldAPIName__c": "quotepolicyJson:additionalFields:%vlocity_namespace%__GracePeriodStartDate__c",
        "%vlocity_namespace%__GlobalKey__c": "6c22e74d-72bd-db2c-1751-3b97a6f66d33",
        "%vlocity_namespace%__InterfaceFieldAPIName__c": "GraceperiodStartDate",
        "%vlocity_namespace%__IsDisabled__c": false,
        "%vlocity_namespace%__IsRequiredForUpsert__c": false,
        "%vlocity_namespace%__MapId__c": "Ins_TransToCreatePolicy_IssueOSCustom6556",
        "%vlocity_namespace%__UpsertKey__c": false,
        "Name": "Ins_TransToCreatePolicy_IssueOS",
        "VlocityDataPackType": "SObject",
        "VlocityRecordSObjectType": "%vlocity_namespace%__DRMapItem__c"
    },
    {
        "%vlocity_namespace%__DomainObjectAPIName__c": "json",
        "%vlocity_namespace%__DomainObjectCreationOrder__c": 1,
        "%vlocity_namespace%__DomainObjectFieldAPIName__c": "quotepolicyJson:additionalFields:%vlocity_namespace%__PaymentMethodId__c",
        "%vlocity_namespace%__GlobalKey__c": "6e59912e-5936-6eea-a539-e7a7d803e83b",
        "%vlocity_namespace%__InterfaceFieldAPIName__c": "DRId_%vlocity_namespace%__PaymentMethod__c",
        "%vlocity_namespace%__IsDisabled__c": false,
        "%vlocity_namespace%__IsRequiredForUpsert__c": false,
        "%vlocity_namespace%__MapId__c": "Ins_TransToCreatePolicy_IssueOSCustoma1T3k000006n2g2EAAItem6",
        "%vlocity_namespace%__UpsertKey__c": false,
        "Name": "Ins_TransToCreatePolicy_IssueOS",
        "VlocityDataPackType": "SObject",
        "VlocityRecordSObjectType": "%vlocity_namespace%__DRMapItem__c"
    },
    {
        "%vlocity_namespace%__DomainObjectAPIName__c": "json",
        "%vlocity_namespace%__DomainObjectCreationOrder__c": 1,
        "%vlocity_namespace%__DomainObjectFieldAPIName__c": "quotepolicyJson:additionalFields:%vlocity_namespace%__PolicyPaidToDate__c",
        "%vlocity_namespace%__GlobalKey__c": "d71f611e-7731-d43a-ceb0-d98ed2b51026",
        "%vlocity_namespace%__InterfaceFieldAPIName__c": "quoteDetails:quoteEffectiveDate",
        "%vlocity_namespace%__IsDisabled__c": false,
        "%vlocity_namespace%__IsRequiredForUpsert__c": false,
        "%vlocity_namespace%__MapId__c": "Ins_TransToCreatePolicy_IssueOSCustom6208",
        "%vlocity_namespace%__UpsertKey__c": false,
        "Name": "Ins_TransToCreatePolicy_IssueOS",
        "VlocityDataPackType": "SObject",
        "VlocityRecordSObjectType": "%vlocity_namespace%__DRMapItem__c"
    },
    {
        "%vlocity_namespace%__DomainObjectAPIName__c": "json",
        "%vlocity_namespace%__DomainObjectCreationOrder__c": 1,
        "%vlocity_namespace%__DomainObjectFieldAPIName__c": "quotepolicyJson:additionalFields:%vlocity_namespace%__PrimaryProducerId__c",
        "%vlocity_namespace%__InterfaceFieldAPIName__c": "ProducerId",
        "%vlocity_namespace%__IsDisabled__c": false,
        "%vlocity_namespace%__IsRequiredForUpsert__c": false,
        "%vlocity_namespace%__MapId__c": "Ins_TransToCreatePolicy_IssueOSCustom8814",
        "%vlocity_namespace%__UpsertKey__c": false,
        "Name": "Ins_TransToCreatePolicy_IssueOS",
        "VlocityDataPackType": "SObject",
        "VlocityRecordSObjectType": "%vlocity_namespace%__DRMapItem__c"
    },
    {
        "%vlocity_namespace%__DomainObjectAPIName__c": "json",
        "%vlocity_namespace%__DomainObjectCreationOrder__c": 1,
        "%vlocity_namespace%__DomainObjectFieldAPIName__c": "quotepolicyJson:additionalFields:%vlocity_namespace%__Type__c",
        "%vlocity_namespace%__GlobalKey__c": "203ccbdc-1079-b480-5065-b89ea2497e9f",
        "%vlocity_namespace%__InterfaceFieldAPIName__c": "ProductType",
        "%vlocity_namespace%__IsDisabled__c": false,
        "%vlocity_namespace%__IsRequiredForUpsert__c": false,
        "%vlocity_namespace%__MapId__c": "Ins_TransToCreatePolicy_IssueOSCustoma1T3k000006n2g2EAAItem10",
        "%vlocity_namespace%__UpsertKey__c": false,
        "Name": "Ins_TransToCreatePolicy_IssueOS",
        "VlocityDataPackType": "SObject",
        "VlocityRecordSObjectType": "%vlocity_namespace%__DRMapItem__c"
    },
    {
        "%vlocity_namespace%__DefaultValue__c": "InForce",
        "%vlocity_namespace%__DomainObjectAPIName__c": "json",
        "%vlocity_namespace%__DomainObjectCreationOrder__c": 1,
        "%vlocity_namespace%__DomainObjectFieldAPIName__c": "quotepolicyJson:additionalFields:Status",
        "%vlocity_namespace%__GlobalKey__c": "c52f56f5-51c8-087d-522f-5e7df781503f",
        "%vlocity_namespace%__IsDisabled__c": false,
        "%vlocity_namespace%__IsRequiredForUpsert__c": false,
        "%vlocity_namespace%__MapId__c": "Ins_TransToCreatePolicy_IssueOSCustoma1T3k000006n2g2EAAItem2",
        "%vlocity_namespace%__UpsertKey__c": false,
        "Name": "Ins_TransToCreatePolicy_IssueOS",
        "VlocityDataPackType": "SObject",
        "VlocityRecordSObjectType": "%vlocity_namespace%__DRMapItem__c"
    },
    {
        "%vlocity_namespace%__DomainObjectAPIName__c": "json",
        "%vlocity_namespace%__DomainObjectCreationOrder__c": 1,
        "%vlocity_namespace%__DomainObjectFieldAPIName__c": "quotepolicyJson:insuredItems",
        "%vlocity_namespace%__GlobalKey__c": "5f187479-0230-318a-9ded-4af6be9e17e1",
        "%vlocity_namespace%__InterfaceFieldAPIName__c": "insuredItems",
        "%vlocity_namespace%__IsDisabled__c": false,
        "%vlocity_namespace%__IsRequiredForUpsert__c": false,
        "%vlocity_namespace%__MapId__c": "Ins_TransToCreatePolicy_IssueOSCustoma1T3k000006n2g2EAAItem7",
        "%vlocity_namespace%__UpsertKey__c": false,
        "Name": "Ins_TransToCreatePolicy_IssueOS",
        "VlocityDataPackType": "SObject",
        "VlocityRecordSObjectType": "%vlocity_namespace%__DRMapItem__c"
    },
    {
        "%vlocity_namespace%__DomainObjectAPIName__c": "json",
        "%vlocity_namespace%__DomainObjectCreationOrder__c": 1,
        "%vlocity_namespace%__DomainObjectFieldAPIName__c": "quotepolicyJson:productConfigurationDetail:records",
        "%vlocity_namespace%__GlobalKey__c": "1ae28f99-d081-52c9-ed71-9e039b9e2e26",
        "%vlocity_namespace%__InterfaceFieldAPIName__c": "productConfigurationDetail:records",
        "%vlocity_namespace%__IsDisabled__c": false,
        "%vlocity_namespace%__IsRequiredForUpsert__c": false,
        "%vlocity_namespace%__MapId__c": "Ins_TransToCreatePolicy_IssueOSCustoma1T3k000006n2g2EAAItem9",
        "%vlocity_namespace%__UpsertKey__c": false,
        "Name": "Ins_TransToCreatePolicy_IssueOS",
        "VlocityDataPackType": "SObject",
        "VlocityRecordSObjectType": "%vlocity_namespace%__DRMapItem__c"
    },
    {
        "%vlocity_namespace%__DomainObjectAPIName__c": "json",
        "%vlocity_namespace%__DomainObjectCreationOrder__c": 1,
        "%vlocity_namespace%__DomainObjectFieldAPIName__c": "quotepolicyJson:term",
        "%vlocity_namespace%__GlobalKey__c": "ff06cb68-ffde-1884-86ac-9cf46170b46e",
        "%vlocity_namespace%__InterfaceFieldAPIName__c": "quoteDetail:%vlocity_namespace%__Term__c",
        "%vlocity_namespace%__IsDisabled__c": false,
        "%vlocity_namespace%__IsRequiredForUpsert__c": false,
        "%vlocity_namespace%__MapId__c": "Ins_TransToCreatePolicy_IssueOSCustoma1T3k000006n2g2EAAItem12",
        "%vlocity_namespace%__UpsertKey__c": false,
        "Name": "Ins_TransToCreatePolicy_IssueOS",
        "VlocityDataPackType": "SObject",
        "VlocityRecordSObjectType": "%vlocity_namespace%__DRMapItem__c"
    },
    {
        "%vlocity_namespace%__DomainObjectAPIName__c": "json",
        "%vlocity_namespace%__DomainObjectCreationOrder__c": 1,
        "%vlocity_namespace%__DomainObjectFieldAPIName__c": "quotepolicyJson:totalSumInsured",
        "%vlocity_namespace%__GlobalKey__c": "0fbd69bb-85f1-8967-3c6a-1bce02557437",
        "%vlocity_namespace%__InterfaceFieldAPIName__c": "quoteDetail:%vlocity_namespace%__TotalSumInsured__c",
        "%vlocity_namespace%__IsDisabled__c": false,
        "%vlocity_namespace%__IsRequiredForUpsert__c": false,
        "%vlocity_namespace%__MapId__c": "Ins_TransToCreatePolicy_IssueOSCustoma1T3k000006n2g2EAAItem14",
        "%vlocity_namespace%__UpsertKey__c": false,
        "Name": "Ins_TransToCreatePolicy_IssueOS",
        "VlocityDataPackType": "SObject",
        "VlocityRecordSObjectType": "%vlocity_namespace%__DRMapItem__c"
    }
]