[
    {
        "%vlocity_namespace%__ActiveFlg__c": true,
        "%vlocity_namespace%__AttributeCategoryCode__c": "OUTMEDICALBENEFITS",
        "%vlocity_namespace%__AttributeCategoryId__c": {
            "%vlocity_namespace%__Code__c": "OUTMEDICALBENEFITS",
            "VlocityDataPackType": "VlocityMatchingKeyObject",
            "VlocityMatchingRecordSourceKey": "%vlocity_namespace%__AttributeCategory__c/OUTMEDICALBENEFITS",
            "VlocityRecordSObjectType": "%vlocity_namespace%__AttributeCategory__c"
        },
        "%vlocity_namespace%__AttributeCategoryName__c": "Medical Out of Network Benefits",
        "%vlocity_namespace%__AttributeGroupType__c": "",
        "%vlocity_namespace%__Code__c": "0f483831-e2b8-8769-a9d6-ce6738ee2e4f",
        "%vlocity_namespace%__Configurable__c": true,
        "%vlocity_namespace%__CustomConfigUiTemplate__c": "",
        "%vlocity_namespace%__Description__c": "",
        "%vlocity_namespace%__DisplaySequence__c": 18,
        "%vlocity_namespace%__EffectiveFromDate__c": "",
        "%vlocity_namespace%__EffectiveUntilDate__c": "",
        "%vlocity_namespace%__Filterable__c": false,
        "%vlocity_namespace%__GlobalKey__c": "1e7f6149-f7e7-0dee-830e-078003162796",
        "%vlocity_namespace%__HelpText__c": "",
        "%vlocity_namespace%__IsCloneable__c": true,
        "%vlocity_namespace%__IsEncrypted__c": false,
        "%vlocity_namespace%__IsNotAssetizable__c": false,
        "%vlocity_namespace%__IsPrivate__c": false,
        "%vlocity_namespace%__OwnerId__c": "",
        "%vlocity_namespace%__PicklistId__c": "",
        "%vlocity_namespace%__UniqueNameField__c": "",
        "%vlocity_namespace%__ValueType__c": "Text",
        "%vlocity_namespace%__Value__c": "",
        "%vlocity_namespace%__isDefaultHidden__c": false,
        "Name": "Mail Order Prescription Drugs–Tier 4 (90-Day Supply)",
        "VlocityDataPackType": "SObject",
        "VlocityRecordSObjectType": "%vlocity_namespace%__Attribute__c",
        "VlocityRecordSourceKey": "%vlocity_namespace%__Attribute__c/0f483831-e2b8-8769-a9d6-ce6738ee2e4f"
    },
    {
        "%vlocity_namespace%__ActiveFlg__c": true,
        "%vlocity_namespace%__AttributeCategoryCode__c": "OUTMEDICALBENEFITS",
        "%vlocity_namespace%__AttributeCategoryId__c": {
            "%vlocity_namespace%__Code__c": "OUTMEDICALBENEFITS",
            "VlocityDataPackType": "VlocityMatchingKeyObject",
            "VlocityMatchingRecordSourceKey": "%vlocity_namespace%__AttributeCategory__c/OUTMEDICALBENEFITS",
            "VlocityRecordSObjectType": "%vlocity_namespace%__AttributeCategory__c"
        },
        "%vlocity_namespace%__AttributeCategoryName__c": "Medical Out of Network Benefits",
        "%vlocity_namespace%__AttributeGroupType__c": "",
        "%vlocity_namespace%__Code__c": "0f89a03e-c10d-bfc6-f1ab-87dbba5f5afa",
        "%vlocity_namespace%__Configurable__c": true,
        "%vlocity_namespace%__CustomConfigUiTemplate__c": "",
        "%vlocity_namespace%__Description__c": "",
        "%vlocity_namespace%__DisplaySequence__c": 22,
        "%vlocity_namespace%__EffectiveFromDate__c": "",
        "%vlocity_namespace%__EffectiveUntilDate__c": "",
        "%vlocity_namespace%__Filterable__c": false,
        "%vlocity_namespace%__GlobalKey__c": "1cd5f6fc-a401-2511-3e2a-7ebc572f7c7c",
        "%vlocity_namespace%__HelpText__c": "",
        "%vlocity_namespace%__IsCloneable__c": true,
        "%vlocity_namespace%__IsEncrypted__c": false,
        "%vlocity_namespace%__IsNotAssetizable__c": false,
        "%vlocity_namespace%__IsPrivate__c": false,
        "%vlocity_namespace%__OwnerId__c": "",
        "%vlocity_namespace%__PicklistId__c": "",
        "%vlocity_namespace%__UniqueNameField__c": "",
        "%vlocity_namespace%__ValueType__c": "Text",
        "%vlocity_namespace%__Value__c": "",
        "%vlocity_namespace%__isDefaultHidden__c": false,
        "Name": "Outpatient Lab/X-Ray",
        "VlocityDataPackType": "SObject",
        "VlocityRecordSObjectType": "%vlocity_namespace%__Attribute__c",
        "VlocityRecordSourceKey": "%vlocity_namespace%__Attribute__c/0f89a03e-c10d-bfc6-f1ab-87dbba5f5afa"
    },
    {
        "%vlocity_namespace%__ActiveFlg__c": true,
        "%vlocity_namespace%__AttributeCategoryCode__c": "OUTMEDICALBENEFITS",
        "%vlocity_namespace%__AttributeCategoryId__c": {
            "%vlocity_namespace%__Code__c": "OUTMEDICALBENEFITS",
            "VlocityDataPackType": "VlocityMatchingKeyObject",
            "VlocityMatchingRecordSourceKey": "%vlocity_namespace%__AttributeCategory__c/OUTMEDICALBENEFITS",
            "VlocityRecordSObjectType": "%vlocity_namespace%__AttributeCategory__c"
        },
        "%vlocity_namespace%__AttributeCategoryName__c": "Medical Out of Network Benefits",
        "%vlocity_namespace%__AttributeGroupType__c": "",
        "%vlocity_namespace%__Code__c": "13f24dca-a189-ed6a-2947-242d0402ce9a",
        "%vlocity_namespace%__Configurable__c": true,
        "%vlocity_namespace%__CustomConfigUiTemplate__c": "",
        "%vlocity_namespace%__Description__c": "",
        "%vlocity_namespace%__DisplaySequence__c": 16,
        "%vlocity_namespace%__EffectiveFromDate__c": "",
        "%vlocity_namespace%__EffectiveUntilDate__c": "",
        "%vlocity_namespace%__Filterable__c": false,
        "%vlocity_namespace%__GlobalKey__c": "747daa6c-7e68-2eb9-2be5-64c81e66e7f4",
        "%vlocity_namespace%__HelpText__c": "",
        "%vlocity_namespace%__IsCloneable__c": true,
        "%vlocity_namespace%__IsEncrypted__c": false,
        "%vlocity_namespace%__IsNotAssetizable__c": false,
        "%vlocity_namespace%__IsPrivate__c": false,
        "%vlocity_namespace%__OwnerId__c": "",
        "%vlocity_namespace%__PicklistId__c": "",
        "%vlocity_namespace%__UniqueNameField__c": "",
        "%vlocity_namespace%__ValueType__c": "Text",
        "%vlocity_namespace%__Value__c": "",
        "%vlocity_namespace%__isDefaultHidden__c": false,
        "Name": "Mail Order Prescription Drugs–Tier 2 (90-Day Supply)",
        "VlocityDataPackType": "SObject",
        "VlocityRecordSObjectType": "%vlocity_namespace%__Attribute__c",
        "VlocityRecordSourceKey": "%vlocity_namespace%__Attribute__c/13f24dca-a189-ed6a-2947-242d0402ce9a"
    },
    {
        "%vlocity_namespace%__ActiveFlg__c": true,
        "%vlocity_namespace%__AttributeCategoryCode__c": "OUTMEDICALBENEFITS",
        "%vlocity_namespace%__AttributeCategoryId__c": {
            "%vlocity_namespace%__Code__c": "OUTMEDICALBENEFITS",
            "VlocityDataPackType": "VlocityMatchingKeyObject",
            "VlocityMatchingRecordSourceKey": "%vlocity_namespace%__AttributeCategory__c/OUTMEDICALBENEFITS",
            "VlocityRecordSObjectType": "%vlocity_namespace%__AttributeCategory__c"
        },
        "%vlocity_namespace%__AttributeCategoryName__c": "Medical Out of Network Benefits",
        "%vlocity_namespace%__AttributeGroupType__c": "",
        "%vlocity_namespace%__Code__c": "15a66a1b-dbb8-8e03-9d82-c6e605452f3f",
        "%vlocity_namespace%__Configurable__c": true,
        "%vlocity_namespace%__CustomConfigUiTemplate__c": "",
        "%vlocity_namespace%__Description__c": "",
        "%vlocity_namespace%__DisplaySequence__c": 8,
        "%vlocity_namespace%__EffectiveFromDate__c": "",
        "%vlocity_namespace%__EffectiveUntilDate__c": "",
        "%vlocity_namespace%__Filterable__c": false,
        "%vlocity_namespace%__GlobalKey__c": "8d31a163-547a-ddf3-5b1d-0f2ca71f95cd",
        "%vlocity_namespace%__HelpText__c": "",
        "%vlocity_namespace%__IsCloneable__c": true,
        "%vlocity_namespace%__IsEncrypted__c": false,
        "%vlocity_namespace%__IsNotAssetizable__c": false,
        "%vlocity_namespace%__IsPrivate__c": false,
        "%vlocity_namespace%__OwnerId__c": "",
        "%vlocity_namespace%__PicklistId__c": "",
        "%vlocity_namespace%__UniqueNameField__c": "",
        "%vlocity_namespace%__ValueType__c": "Text",
        "%vlocity_namespace%__Value__c": "",
        "%vlocity_namespace%__isDefaultHidden__c": false,
        "Name": "Health Savings Account (HSA) Eligible",
        "VlocityDataPackType": "SObject",
        "VlocityRecordSObjectType": "%vlocity_namespace%__Attribute__c",
        "VlocityRecordSourceKey": "%vlocity_namespace%__Attribute__c/15a66a1b-dbb8-8e03-9d82-c6e605452f3f"
    },
    {
        "%vlocity_namespace%__ActiveFlg__c": true,
        "%vlocity_namespace%__AttributeCategoryCode__c": "OUTMEDICALBENEFITS",
        "%vlocity_namespace%__AttributeCategoryId__c": {
            "%vlocity_namespace%__Code__c": "OUTMEDICALBENEFITS",
            "VlocityDataPackType": "VlocityMatchingKeyObject",
            "VlocityMatchingRecordSourceKey": "%vlocity_namespace%__AttributeCategory__c/OUTMEDICALBENEFITS",
            "VlocityRecordSObjectType": "%vlocity_namespace%__AttributeCategory__c"
        },
        "%vlocity_namespace%__AttributeCategoryName__c": "Medical Out of Network Benefits",
        "%vlocity_namespace%__AttributeGroupType__c": "",
        "%vlocity_namespace%__Code__c": "1d6af276-4804-1958-b693-a3d7b126afb0",
        "%vlocity_namespace%__Configurable__c": true,
        "%vlocity_namespace%__CustomConfigUiTemplate__c": "",
        "%vlocity_namespace%__Description__c": "",
        "%vlocity_namespace%__DisplaySequence__c": 37,
        "%vlocity_namespace%__EffectiveFromDate__c": "",
        "%vlocity_namespace%__EffectiveUntilDate__c": "",
        "%vlocity_namespace%__Filterable__c": false,
        "%vlocity_namespace%__GlobalKey__c": "67647dd9-f9be-455f-930c-e88df60dcb75",
        "%vlocity_namespace%__HelpText__c": "",
        "%vlocity_namespace%__IsCloneable__c": true,
        "%vlocity_namespace%__IsEncrypted__c": false,
        "%vlocity_namespace%__IsNotAssetizable__c": false,
        "%vlocity_namespace%__IsPrivate__c": false,
        "%vlocity_namespace%__OwnerId__c": "",
        "%vlocity_namespace%__PicklistId__c": "",
        "%vlocity_namespace%__UniqueNameField__c": "",
        "%vlocity_namespace%__ValueType__c": "Text",
        "%vlocity_namespace%__Value__c": "",
        "%vlocity_namespace%__isDefaultHidden__c": false,
        "Name": "Foot Care – Routine",
        "VlocityDataPackType": "SObject",
        "VlocityRecordSObjectType": "%vlocity_namespace%__Attribute__c",
        "VlocityRecordSourceKey": "%vlocity_namespace%__Attribute__c/1d6af276-4804-1958-b693-a3d7b126afb0"
    },
    {
        "%vlocity_namespace%__ActiveFlg__c": true,
        "%vlocity_namespace%__AttributeCategoryCode__c": "OUTMEDICALBENEFITS",
        "%vlocity_namespace%__AttributeCategoryId__c": {
            "%vlocity_namespace%__Code__c": "OUTMEDICALBENEFITS",
            "VlocityDataPackType": "VlocityMatchingKeyObject",
            "VlocityMatchingRecordSourceKey": "%vlocity_namespace%__AttributeCategory__c/OUTMEDICALBENEFITS",
            "VlocityRecordSObjectType": "%vlocity_namespace%__AttributeCategory__c"
        },
        "%vlocity_namespace%__AttributeCategoryName__c": "Medical Out of Network Benefits",
        "%vlocity_namespace%__AttributeGroupType__c": "",
        "%vlocity_namespace%__Code__c": "1e55deb7-2ede-83f3-fc48-0b91c1a5e071",
        "%vlocity_namespace%__Configurable__c": true,
        "%vlocity_namespace%__CustomConfigUiTemplate__c": "",
        "%vlocity_namespace%__Description__c": "",
        "%vlocity_namespace%__DisplaySequence__c": 24,
        "%vlocity_namespace%__EffectiveFromDate__c": "",
        "%vlocity_namespace%__EffectiveUntilDate__c": "",
        "%vlocity_namespace%__Filterable__c": false,
        "%vlocity_namespace%__GlobalKey__c": "37bff4dc-7776-e4ec-4153-f602e353ab02",
        "%vlocity_namespace%__HelpText__c": "",
        "%vlocity_namespace%__IsCloneable__c": true,
        "%vlocity_namespace%__IsEncrypted__c": false,
        "%vlocity_namespace%__IsNotAssetizable__c": false,
        "%vlocity_namespace%__IsPrivate__c": false,
        "%vlocity_namespace%__OwnerId__c": "",
        "%vlocity_namespace%__PicklistId__c": "",
        "%vlocity_namespace%__UniqueNameField__c": "",
        "%vlocity_namespace%__ValueType__c": "Text",
        "%vlocity_namespace%__Value__c": "",
        "%vlocity_namespace%__isDefaultHidden__c": false,
        "Name": "Emergency Room",
        "VlocityDataPackType": "SObject",
        "VlocityRecordSObjectType": "%vlocity_namespace%__Attribute__c",
        "VlocityRecordSourceKey": "%vlocity_namespace%__Attribute__c/1e55deb7-2ede-83f3-fc48-0b91c1a5e071"
    },
    {
        "%vlocity_namespace%__ActiveFlg__c": true,
        "%vlocity_namespace%__AttributeCategoryCode__c": "OUTMEDICALBENEFITS",
        "%vlocity_namespace%__AttributeCategoryId__c": {
            "%vlocity_namespace%__Code__c": "OUTMEDICALBENEFITS",
            "VlocityDataPackType": "VlocityMatchingKeyObject",
            "VlocityMatchingRecordSourceKey": "%vlocity_namespace%__AttributeCategory__c/OUTMEDICALBENEFITS",
            "VlocityRecordSObjectType": "%vlocity_namespace%__AttributeCategory__c"
        },
        "%vlocity_namespace%__AttributeCategoryName__c": "Medical Out of Network Benefits",
        "%vlocity_namespace%__AttributeGroupType__c": "",
        "%vlocity_namespace%__Code__c": "2fc8a5b3-56a0-bfa1-e368-48c192b1a04a",
        "%vlocity_namespace%__Configurable__c": true,
        "%vlocity_namespace%__CustomConfigUiTemplate__c": "",
        "%vlocity_namespace%__Description__c": "",
        "%vlocity_namespace%__DisplaySequence__c": 36,
        "%vlocity_namespace%__EffectiveFromDate__c": "",
        "%vlocity_namespace%__EffectiveUntilDate__c": "",
        "%vlocity_namespace%__Filterable__c": false,
        "%vlocity_namespace%__GlobalKey__c": "f600588b-4b57-b995-e739-cd73cf9dd469",
        "%vlocity_namespace%__HelpText__c": "",
        "%vlocity_namespace%__IsCloneable__c": true,
        "%vlocity_namespace%__IsEncrypted__c": false,
        "%vlocity_namespace%__IsNotAssetizable__c": false,
        "%vlocity_namespace%__IsPrivate__c": false,
        "%vlocity_namespace%__OwnerId__c": "",
        "%vlocity_namespace%__PicklistId__c": "",
        "%vlocity_namespace%__UniqueNameField__c": "",
        "%vlocity_namespace%__ValueType__c": "Text",
        "%vlocity_namespace%__Value__c": "",
        "%vlocity_namespace%__isDefaultHidden__c": false,
        "Name": "Dental",
        "VlocityDataPackType": "SObject",
        "VlocityRecordSObjectType": "%vlocity_namespace%__Attribute__c",
        "VlocityRecordSourceKey": "%vlocity_namespace%__Attribute__c/2fc8a5b3-56a0-bfa1-e368-48c192b1a04a"
    },
    {
        "%vlocity_namespace%__ActiveFlg__c": true,
        "%vlocity_namespace%__AttributeCategoryCode__c": "OUTMEDICALBENEFITS",
        "%vlocity_namespace%__AttributeCategoryId__c": {
            "%vlocity_namespace%__Code__c": "OUTMEDICALBENEFITS",
            "VlocityDataPackType": "VlocityMatchingKeyObject",
            "VlocityMatchingRecordSourceKey": "%vlocity_namespace%__AttributeCategory__c/OUTMEDICALBENEFITS",
            "VlocityRecordSObjectType": "%vlocity_namespace%__AttributeCategory__c"
        },
        "%vlocity_namespace%__AttributeCategoryName__c": "Medical Out of Network Benefits",
        "%vlocity_namespace%__AttributeGroupType__c": "",
        "%vlocity_namespace%__Code__c": "3095cacd-a784-4bb2-71b3-e3fec4be3e61",
        "%vlocity_namespace%__Configurable__c": true,
        "%vlocity_namespace%__CustomConfigUiTemplate__c": "",
        "%vlocity_namespace%__Description__c": "",
        "%vlocity_namespace%__DisplaySequence__c": 33,
        "%vlocity_namespace%__EffectiveFromDate__c": "",
        "%vlocity_namespace%__EffectiveUntilDate__c": "",
        "%vlocity_namespace%__Filterable__c": false,
        "%vlocity_namespace%__GlobalKey__c": "68286d60-b8ce-b327-7f76-17f3a96ce650",
        "%vlocity_namespace%__HelpText__c": "",
        "%vlocity_namespace%__IsCloneable__c": true,
        "%vlocity_namespace%__IsEncrypted__c": false,
        "%vlocity_namespace%__IsNotAssetizable__c": false,
        "%vlocity_namespace%__IsPrivate__c": false,
        "%vlocity_namespace%__OwnerId__c": "",
        "%vlocity_namespace%__PicklistId__c": "",
        "%vlocity_namespace%__UniqueNameField__c": "",
        "%vlocity_namespace%__ValueType__c": "Text",
        "%vlocity_namespace%__Value__c": "",
        "%vlocity_namespace%__isDefaultHidden__c": false,
        "Name": "Eyewear",
        "VlocityDataPackType": "SObject",
        "VlocityRecordSObjectType": "%vlocity_namespace%__Attribute__c",
        "VlocityRecordSourceKey": "%vlocity_namespace%__Attribute__c/3095cacd-a784-4bb2-71b3-e3fec4be3e61"
    },
    {
        "%vlocity_namespace%__ActiveFlg__c": true,
        "%vlocity_namespace%__AttributeCategoryCode__c": "OUTMEDICALBENEFITS",
        "%vlocity_namespace%__AttributeCategoryId__c": {
            "%vlocity_namespace%__Code__c": "OUTMEDICALBENEFITS",
            "VlocityDataPackType": "VlocityMatchingKeyObject",
            "VlocityMatchingRecordSourceKey": "%vlocity_namespace%__AttributeCategory__c/OUTMEDICALBENEFITS",
            "VlocityRecordSObjectType": "%vlocity_namespace%__AttributeCategory__c"
        },
        "%vlocity_namespace%__AttributeCategoryName__c": "Medical Out of Network Benefits",
        "%vlocity_namespace%__AttributeGroupType__c": "",
        "%vlocity_namespace%__Code__c": "3a4ae0e9-de3b-1fc4-6c69-e3e74a269be9",
        "%vlocity_namespace%__Configurable__c": true,
        "%vlocity_namespace%__CustomConfigUiTemplate__c": "",
        "%vlocity_namespace%__Description__c": "",
        "%vlocity_namespace%__DisplaySequence__c": 35,
        "%vlocity_namespace%__EffectiveFromDate__c": "",
        "%vlocity_namespace%__EffectiveUntilDate__c": "",
        "%vlocity_namespace%__Filterable__c": false,
        "%vlocity_namespace%__GlobalKey__c": "513e0d51-48fc-2180-70d3-6c69c0478fbb",
        "%vlocity_namespace%__HelpText__c": "",
        "%vlocity_namespace%__IsCloneable__c": true,
        "%vlocity_namespace%__IsEncrypted__c": false,
        "%vlocity_namespace%__IsNotAssetizable__c": false,
        "%vlocity_namespace%__IsPrivate__c": false,
        "%vlocity_namespace%__OwnerId__c": "",
        "%vlocity_namespace%__PicklistId__c": "",
        "%vlocity_namespace%__UniqueNameField__c": "",
        "%vlocity_namespace%__ValueType__c": "Text",
        "%vlocity_namespace%__Value__c": "",
        "%vlocity_namespace%__isDefaultHidden__c": false,
        "Name": "Hearing Aids",
        "VlocityDataPackType": "SObject",
        "VlocityRecordSObjectType": "%vlocity_namespace%__Attribute__c",
        "VlocityRecordSourceKey": "%vlocity_namespace%__Attribute__c/3a4ae0e9-de3b-1fc4-6c69-e3e74a269be9"
    },
    {
        "%vlocity_namespace%__ActiveFlg__c": true,
        "%vlocity_namespace%__AttributeCategoryCode__c": "OUTMEDICALBENEFITS",
        "%vlocity_namespace%__AttributeCategoryId__c": {
            "%vlocity_namespace%__Code__c": "OUTMEDICALBENEFITS",
            "VlocityDataPackType": "VlocityMatchingKeyObject",
            "VlocityMatchingRecordSourceKey": "%vlocity_namespace%__AttributeCategory__c/OUTMEDICALBENEFITS",
            "VlocityRecordSObjectType": "%vlocity_namespace%__AttributeCategory__c"
        },
        "%vlocity_namespace%__AttributeCategoryName__c": "Medical Out of Network Benefits",
        "%vlocity_namespace%__AttributeGroupType__c": "",
        "%vlocity_namespace%__Code__c": "3bcbfc85-8544-66a5-62f5-b7c6072677df",
        "%vlocity_namespace%__Configurable__c": true,
        "%vlocity_namespace%__CustomConfigUiTemplate__c": "",
        "%vlocity_namespace%__Description__c": "",
        "%vlocity_namespace%__DisplaySequence__c": 32,
        "%vlocity_namespace%__EffectiveFromDate__c": "",
        "%vlocity_namespace%__EffectiveUntilDate__c": "",
        "%vlocity_namespace%__Filterable__c": false,
        "%vlocity_namespace%__GlobalKey__c": "66c440d6-b8bd-f786-1fb2-7d17faf86d78",
        "%vlocity_namespace%__HelpText__c": "",
        "%vlocity_namespace%__IsCloneable__c": true,
        "%vlocity_namespace%__IsEncrypted__c": false,
        "%vlocity_namespace%__IsNotAssetizable__c": false,
        "%vlocity_namespace%__IsPrivate__c": false,
        "%vlocity_namespace%__OwnerId__c": "",
        "%vlocity_namespace%__PicklistId__c": "",
        "%vlocity_namespace%__UniqueNameField__c": "",
        "%vlocity_namespace%__ValueType__c": "Text",
        "%vlocity_namespace%__Value__c": "",
        "%vlocity_namespace%__isDefaultHidden__c": false,
        "Name": "Eye Exam",
        "VlocityDataPackType": "SObject",
        "VlocityRecordSObjectType": "%vlocity_namespace%__Attribute__c",
        "VlocityRecordSourceKey": "%vlocity_namespace%__Attribute__c/3bcbfc85-8544-66a5-62f5-b7c6072677df"
    },
    {
        "%vlocity_namespace%__ActiveFlg__c": true,
        "%vlocity_namespace%__AttributeCategoryCode__c": "OUTMEDICALBENEFITS",
        "%vlocity_namespace%__AttributeCategoryId__c": {
            "%vlocity_namespace%__Code__c": "OUTMEDICALBENEFITS",
            "VlocityDataPackType": "VlocityMatchingKeyObject",
            "VlocityMatchingRecordSourceKey": "%vlocity_namespace%__AttributeCategory__c/OUTMEDICALBENEFITS",
            "VlocityRecordSObjectType": "%vlocity_namespace%__AttributeCategory__c"
        },
        "%vlocity_namespace%__AttributeCategoryName__c": "Medical Out of Network Benefits",
        "%vlocity_namespace%__AttributeGroupType__c": "",
        "%vlocity_namespace%__Code__c": "88bd1f6b-8da7-a6af-1c13-8b2267fe83cb",
        "%vlocity_namespace%__Configurable__c": true,
        "%vlocity_namespace%__CustomConfigUiTemplate__c": "",
        "%vlocity_namespace%__Description__c": "",
        "%vlocity_namespace%__DisplaySequence__c": 5,
        "%vlocity_namespace%__EffectiveFromDate__c": "",
        "%vlocity_namespace%__EffectiveUntilDate__c": "",
        "%vlocity_namespace%__Filterable__c": false,
        "%vlocity_namespace%__GlobalKey__c": "d4344254-2c96-eb13-a228-fd4c16521964",
        "%vlocity_namespace%__HelpText__c": "",
        "%vlocity_namespace%__IsCloneable__c": true,
        "%vlocity_namespace%__IsEncrypted__c": false,
        "%vlocity_namespace%__IsNotAssetizable__c": false,
        "%vlocity_namespace%__IsPrivate__c": false,
        "%vlocity_namespace%__OwnerId__c": "",
        "%vlocity_namespace%__PicklistId__c": "",
        "%vlocity_namespace%__UniqueNameField__c": "",
        "%vlocity_namespace%__ValueType__c": "Text",
        "%vlocity_namespace%__Value__c": "",
        "%vlocity_namespace%__isDefaultHidden__c": false,
        "Name": "Coinsurance",
        "VlocityDataPackType": "SObject",
        "VlocityRecordSObjectType": "%vlocity_namespace%__Attribute__c",
        "VlocityRecordSourceKey": "%vlocity_namespace%__Attribute__c/88bd1f6b-8da7-a6af-1c13-8b2267fe83cb"
    },
    {
        "%vlocity_namespace%__ActiveFlg__c": true,
        "%vlocity_namespace%__AttributeCategoryCode__c": "OUTMEDICALBENEFITS",
        "%vlocity_namespace%__AttributeCategoryId__c": {
            "%vlocity_namespace%__Code__c": "OUTMEDICALBENEFITS",
            "VlocityDataPackType": "VlocityMatchingKeyObject",
            "VlocityMatchingRecordSourceKey": "%vlocity_namespace%__AttributeCategory__c/OUTMEDICALBENEFITS",
            "VlocityRecordSObjectType": "%vlocity_namespace%__AttributeCategory__c"
        },
        "%vlocity_namespace%__AttributeCategoryName__c": "Medical Out of Network Benefits",
        "%vlocity_namespace%__AttributeGroupType__c": "",
        "%vlocity_namespace%__Code__c": "8f19c043-fcf4-d193-1fbc-f23d5b36823a",
        "%vlocity_namespace%__Configurable__c": true,
        "%vlocity_namespace%__CustomConfigUiTemplate__c": "",
        "%vlocity_namespace%__Description__c": "",
        "%vlocity_namespace%__DisplaySequence__c": 7,
        "%vlocity_namespace%__EffectiveFromDate__c": "",
        "%vlocity_namespace%__EffectiveUntilDate__c": "",
        "%vlocity_namespace%__Filterable__c": false,
        "%vlocity_namespace%__GlobalKey__c": "48362286-eb12-f094-85fd-080d8608547d",
        "%vlocity_namespace%__HelpText__c": "",
        "%vlocity_namespace%__IsCloneable__c": true,
        "%vlocity_namespace%__IsEncrypted__c": false,
        "%vlocity_namespace%__IsNotAssetizable__c": false,
        "%vlocity_namespace%__IsPrivate__c": false,
        "%vlocity_namespace%__OwnerId__c": "",
        "%vlocity_namespace%__PicklistId__c": "",
        "%vlocity_namespace%__UniqueNameField__c": "",
        "%vlocity_namespace%__ValueType__c": "Text",
        "%vlocity_namespace%__Value__c": "",
        "%vlocity_namespace%__isDefaultHidden__c": false,
        "Name": "Lifetime Maximum",
        "VlocityDataPackType": "SObject",
        "VlocityRecordSObjectType": "%vlocity_namespace%__Attribute__c",
        "VlocityRecordSourceKey": "%vlocity_namespace%__Attribute__c/8f19c043-fcf4-d193-1fbc-f23d5b36823a"
    },
    {
        "%vlocity_namespace%__ActiveFlg__c": true,
        "%vlocity_namespace%__AttributeCategoryCode__c": "OUTMEDICALBENEFITS",
        "%vlocity_namespace%__AttributeCategoryId__c": {
            "%vlocity_namespace%__Code__c": "OUTMEDICALBENEFITS",
            "VlocityDataPackType": "VlocityMatchingKeyObject",
            "VlocityMatchingRecordSourceKey": "%vlocity_namespace%__AttributeCategory__c/OUTMEDICALBENEFITS",
            "VlocityRecordSObjectType": "%vlocity_namespace%__AttributeCategory__c"
        },
        "%vlocity_namespace%__AttributeCategoryName__c": "Medical Out of Network Benefits",
        "%vlocity_namespace%__AttributeGroupType__c": "",
        "%vlocity_namespace%__Code__c": "OON_RBS",
        "%vlocity_namespace%__Configurable__c": true,
        "%vlocity_namespace%__CustomConfigUiTemplate__c": "",
        "%vlocity_namespace%__Description__c": "",
        "%vlocity_namespace%__DisplaySequence__c": 1,
        "%vlocity_namespace%__EffectiveFromDate__c": "",
        "%vlocity_namespace%__EffectiveUntilDate__c": "",
        "%vlocity_namespace%__Filterable__c": true,
        "%vlocity_namespace%__GlobalKey__c": "e99f98c1-41e9-4bfd-b4b1-b36b646373b2",
        "%vlocity_namespace%__HelpText__c": "",
        "%vlocity_namespace%__IsCloneable__c": true,
        "%vlocity_namespace%__IsEncrypted__c": false,
        "%vlocity_namespace%__IsNotAssetizable__c": false,
        "%vlocity_namespace%__IsPrivate__c": false,
        "%vlocity_namespace%__OwnerId__c": "",
        "%vlocity_namespace%__PicklistId__c": "",
        "%vlocity_namespace%__UniqueNameField__c": "",
        "%vlocity_namespace%__ValueType__c": "Text",
        "%vlocity_namespace%__Value__c": "",
        "%vlocity_namespace%__isDefaultHidden__c": false,
        "Name": "Out-of-Network Reimbursement",
        "VlocityDataPackType": "SObject",
        "VlocityRecordSObjectType": "%vlocity_namespace%__Attribute__c",
        "VlocityRecordSourceKey": "%vlocity_namespace%__Attribute__c/OON_RBS"
    },
    {
        "%vlocity_namespace%__ActiveFlg__c": true,
        "%vlocity_namespace%__AttributeCategoryCode__c": "OUTMEDICALBENEFITS",
        "%vlocity_namespace%__AttributeCategoryId__c": {
            "%vlocity_namespace%__Code__c": "OUTMEDICALBENEFITS",
            "VlocityDataPackType": "VlocityMatchingKeyObject",
            "VlocityMatchingRecordSourceKey": "%vlocity_namespace%__AttributeCategory__c/OUTMEDICALBENEFITS",
            "VlocityRecordSObjectType": "%vlocity_namespace%__AttributeCategory__c"
        },
        "%vlocity_namespace%__AttributeCategoryName__c": "Medical Out of Network Benefits",
        "%vlocity_namespace%__AttributeGroupType__c": "",
        "%vlocity_namespace%__Code__c": "OPRS-oonb",
        "%vlocity_namespace%__Configurable__c": true,
        "%vlocity_namespace%__CustomConfigUiTemplate__c": "",
        "%vlocity_namespace%__Description__c": "",
        "%vlocity_namespace%__DisplaySequence__c": 28,
        "%vlocity_namespace%__EffectiveFromDate__c": "",
        "%vlocity_namespace%__EffectiveUntilDate__c": "",
        "%vlocity_namespace%__Filterable__c": false,
        "%vlocity_namespace%__GlobalKey__c": "927fbf4c-9369-0b22-e9e5-239bbd604273",
        "%vlocity_namespace%__HelpText__c": "",
        "%vlocity_namespace%__IsCloneable__c": true,
        "%vlocity_namespace%__IsEncrypted__c": false,
        "%vlocity_namespace%__IsNotAssetizable__c": false,
        "%vlocity_namespace%__IsPrivate__c": false,
        "%vlocity_namespace%__OwnerId__c": "",
        "%vlocity_namespace%__PicklistId__c": "",
        "%vlocity_namespace%__UniqueNameField__c": "",
        "%vlocity_namespace%__ValueType__c": "Text",
        "%vlocity_namespace%__Value__c": "",
        "%vlocity_namespace%__isDefaultHidden__c": false,
        "Name": "Outpatient Rehabilitation Services",
        "VlocityDataPackType": "SObject",
        "VlocityRecordSObjectType": "%vlocity_namespace%__Attribute__c",
        "VlocityRecordSourceKey": "%vlocity_namespace%__Attribute__c/OPRS-oonb"
    },
    {
        "%vlocity_namespace%__ActiveFlg__c": true,
        "%vlocity_namespace%__AttributeCategoryCode__c": "OUTMEDICALBENEFITS",
        "%vlocity_namespace%__AttributeCategoryId__c": {
            "%vlocity_namespace%__Code__c": "OUTMEDICALBENEFITS",
            "VlocityDataPackType": "VlocityMatchingKeyObject",
            "VlocityMatchingRecordSourceKey": "%vlocity_namespace%__AttributeCategory__c/OUTMEDICALBENEFITS",
            "VlocityRecordSObjectType": "%vlocity_namespace%__AttributeCategory__c"
        },
        "%vlocity_namespace%__AttributeCategoryName__c": "Medical Out of Network Benefits",
        "%vlocity_namespace%__AttributeGroupType__c": "",
        "%vlocity_namespace%__Code__c": "OTCI-oonb",
        "%vlocity_namespace%__Configurable__c": true,
        "%vlocity_namespace%__CustomConfigUiTemplate__c": "",
        "%vlocity_namespace%__Description__c": "",
        "%vlocity_namespace%__DisplaySequence__c": 41,
        "%vlocity_namespace%__EffectiveFromDate__c": "",
        "%vlocity_namespace%__EffectiveUntilDate__c": "",
        "%vlocity_namespace%__Filterable__c": false,
        "%vlocity_namespace%__GlobalKey__c": "bc8d0ec0-a2e9-7975-7da1-4ef37373f90b",
        "%vlocity_namespace%__HelpText__c": "",
        "%vlocity_namespace%__IsCloneable__c": true,
        "%vlocity_namespace%__IsEncrypted__c": false,
        "%vlocity_namespace%__IsNotAssetizable__c": false,
        "%vlocity_namespace%__IsPrivate__c": false,
        "%vlocity_namespace%__OwnerId__c": "",
        "%vlocity_namespace%__PicklistId__c": "",
        "%vlocity_namespace%__UniqueNameField__c": "",
        "%vlocity_namespace%__ValueType__c": "Text",
        "%vlocity_namespace%__Value__c": "",
        "%vlocity_namespace%__isDefaultHidden__c": false,
        "Name": "Over-the-Counter Items",
        "VlocityDataPackType": "SObject",
        "VlocityRecordSObjectType": "%vlocity_namespace%__Attribute__c",
        "VlocityRecordSourceKey": "%vlocity_namespace%__Attribute__c/OTCI-oonb"
    },
    {
        "%vlocity_namespace%__ActiveFlg__c": true,
        "%vlocity_namespace%__AttributeCategoryCode__c": "OUTMEDICALBENEFITS",
        "%vlocity_namespace%__AttributeCategoryId__c": {
            "%vlocity_namespace%__Code__c": "OUTMEDICALBENEFITS",
            "VlocityDataPackType": "VlocityMatchingKeyObject",
            "VlocityMatchingRecordSourceKey": "%vlocity_namespace%__AttributeCategory__c/OUTMEDICALBENEFITS",
            "VlocityRecordSObjectType": "%vlocity_namespace%__AttributeCategory__c"
        },
        "%vlocity_namespace%__AttributeCategoryName__c": "Medical Out of Network Benefits",
        "%vlocity_namespace%__AttributeGroupType__c": "",
        "%vlocity_namespace%__Code__c": "OTSY-oonb",
        "%vlocity_namespace%__Configurable__c": true,
        "%vlocity_namespace%__CustomConfigUiTemplate__c": "",
        "%vlocity_namespace%__Description__c": "",
        "%vlocity_namespace%__DisplaySequence__c": 21,
        "%vlocity_namespace%__EffectiveFromDate__c": "",
        "%vlocity_namespace%__EffectiveUntilDate__c": "",
        "%vlocity_namespace%__Filterable__c": false,
        "%vlocity_namespace%__GlobalKey__c": "6376d4e0-085f-c3ee-d86f-8775ed294c32",
        "%vlocity_namespace%__HelpText__c": "",
        "%vlocity_namespace%__IsCloneable__c": true,
        "%vlocity_namespace%__IsEncrypted__c": false,
        "%vlocity_namespace%__IsNotAssetizable__c": false,
        "%vlocity_namespace%__IsPrivate__c": false,
        "%vlocity_namespace%__OwnerId__c": "",
        "%vlocity_namespace%__PicklistId__c": "",
        "%vlocity_namespace%__UniqueNameField__c": "",
        "%vlocity_namespace%__ValueType__c": "Text",
        "%vlocity_namespace%__Value__c": "",
        "%vlocity_namespace%__isDefaultHidden__c": false,
        "Name": "Outpatient Surgery",
        "VlocityDataPackType": "SObject",
        "VlocityRecordSObjectType": "%vlocity_namespace%__Attribute__c",
        "VlocityRecordSourceKey": "%vlocity_namespace%__Attribute__c/OTSY-oonb"
    },
    {
        "%vlocity_namespace%__ActiveFlg__c": true,
        "%vlocity_namespace%__AttributeCategoryCode__c": "OUTMEDICALBENEFITS",
        "%vlocity_namespace%__AttributeCategoryId__c": {
            "%vlocity_namespace%__Code__c": "OUTMEDICALBENEFITS",
            "VlocityDataPackType": "VlocityMatchingKeyObject",
            "VlocityMatchingRecordSourceKey": "%vlocity_namespace%__AttributeCategory__c/OUTMEDICALBENEFITS",
            "VlocityRecordSObjectType": "%vlocity_namespace%__AttributeCategory__c"
        },
        "%vlocity_namespace%__AttributeCategoryName__c": "Medical Out of Network Benefits",
        "%vlocity_namespace%__AttributeGroupType__c": "",
        "%vlocity_namespace%__Code__c": "OUT-annu_oopl",
        "%vlocity_namespace%__Configurable__c": true,
        "%vlocity_namespace%__CustomConfigUiTemplate__c": "",
        "%vlocity_namespace%__Description__c": "",
        "%vlocity_namespace%__DisplaySequence__c": 992,
        "%vlocity_namespace%__EffectiveFromDate__c": "",
        "%vlocity_namespace%__EffectiveUntilDate__c": "",
        "%vlocity_namespace%__Filterable__c": false,
        "%vlocity_namespace%__GlobalKey__c": "",
        "%vlocity_namespace%__HelpText__c": "",
        "%vlocity_namespace%__IsCloneable__c": true,
        "%vlocity_namespace%__IsEncrypted__c": false,
        "%vlocity_namespace%__IsNotAssetizable__c": false,
        "%vlocity_namespace%__IsPrivate__c": false,
        "%vlocity_namespace%__OwnerId__c": "",
        "%vlocity_namespace%__PicklistId__c": "",
        "%vlocity_namespace%__UniqueNameField__c": "",
        "%vlocity_namespace%__ValueType__c": "Text",
        "%vlocity_namespace%__Value__c": "",
        "%vlocity_namespace%__isDefaultHidden__c": false,
        "Name": "Annual Out of Pocket Limit",
        "VlocityDataPackType": "SObject",
        "VlocityRecordSObjectType": "%vlocity_namespace%__Attribute__c",
        "VlocityRecordSourceKey": "%vlocity_namespace%__Attribute__c/OUT-annu_oopl"
    },
    {
        "%vlocity_namespace%__ActiveFlg__c": true,
        "%vlocity_namespace%__AttributeCategoryCode__c": "OUTMEDICALBENEFITS",
        "%vlocity_namespace%__AttributeCategoryId__c": {
            "%vlocity_namespace%__Code__c": "OUTMEDICALBENEFITS",
            "VlocityDataPackType": "VlocityMatchingKeyObject",
            "VlocityMatchingRecordSourceKey": "%vlocity_namespace%__AttributeCategory__c/OUTMEDICALBENEFITS",
            "VlocityRecordSObjectType": "%vlocity_namespace%__AttributeCategory__c"
        },
        "%vlocity_namespace%__AttributeCategoryName__c": "Medical Out of Network Benefits",
        "%vlocity_namespace%__AttributeGroupType__c": "",
        "%vlocity_namespace%__Code__c": "PRSV-oonb",
        "%vlocity_namespace%__Configurable__c": true,
        "%vlocity_namespace%__CustomConfigUiTemplate__c": "",
        "%vlocity_namespace%__Description__c": "",
        "%vlocity_namespace%__DisplaySequence__c": 3,
        "%vlocity_namespace%__EffectiveFromDate__c": "",
        "%vlocity_namespace%__EffectiveUntilDate__c": "",
        "%vlocity_namespace%__Filterable__c": false,
        "%vlocity_namespace%__GlobalKey__c": "3dc8f17a-f3e1-5d6b-1952-8b4ce10ef37d",
        "%vlocity_namespace%__HelpText__c": "",
        "%vlocity_namespace%__IsCloneable__c": true,
        "%vlocity_namespace%__IsEncrypted__c": false,
        "%vlocity_namespace%__IsNotAssetizable__c": false,
        "%vlocity_namespace%__IsPrivate__c": false,
        "%vlocity_namespace%__OwnerId__c": "",
        "%vlocity_namespace%__PicklistId__c": "",
        "%vlocity_namespace%__UniqueNameField__c": "",
        "%vlocity_namespace%__ValueType__c": "Text",
        "%vlocity_namespace%__Value__c": "",
        "%vlocity_namespace%__isDefaultHidden__c": false,
        "Name": "Preventive Services",
        "VlocityDataPackType": "SObject",
        "VlocityRecordSObjectType": "%vlocity_namespace%__Attribute__c",
        "VlocityRecordSourceKey": "%vlocity_namespace%__Attribute__c/PRSV-oonb"
    },
    {
        "%vlocity_namespace%__ActiveFlg__c": true,
        "%vlocity_namespace%__AttributeCategoryCode__c": "OUTMEDICALBENEFITS",
        "%vlocity_namespace%__AttributeCategoryId__c": {
            "%vlocity_namespace%__Code__c": "OUTMEDICALBENEFITS",
            "VlocityDataPackType": "VlocityMatchingKeyObject",
            "VlocityMatchingRecordSourceKey": "%vlocity_namespace%__AttributeCategory__c/OUTMEDICALBENEFITS",
            "VlocityRecordSObjectType": "%vlocity_namespace%__AttributeCategory__c"
        },
        "%vlocity_namespace%__AttributeCategoryName__c": "Medical Out of Network Benefits",
        "%vlocity_namespace%__AttributeGroupType__c": "",
        "%vlocity_namespace%__Code__c": "PRYCP-oonb",
        "%vlocity_namespace%__Configurable__c": true,
        "%vlocity_namespace%__CustomConfigUiTemplate__c": "",
        "%vlocity_namespace%__Description__c": "",
        "%vlocity_namespace%__DisplaySequence__c": 1,
        "%vlocity_namespace%__EffectiveFromDate__c": "",
        "%vlocity_namespace%__EffectiveUntilDate__c": "",
        "%vlocity_namespace%__Filterable__c": false,
        "%vlocity_namespace%__GlobalKey__c": "1957fec5-b4c4-14da-84b1-6057d4e21bf2",
        "%vlocity_namespace%__HelpText__c": "",
        "%vlocity_namespace%__IsCloneable__c": true,
        "%vlocity_namespace%__IsEncrypted__c": false,
        "%vlocity_namespace%__IsNotAssetizable__c": false,
        "%vlocity_namespace%__IsPrivate__c": false,
        "%vlocity_namespace%__OwnerId__c": "",
        "%vlocity_namespace%__PicklistId__c": "",
        "%vlocity_namespace%__UniqueNameField__c": "",
        "%vlocity_namespace%__ValueType__c": "Text",
        "%vlocity_namespace%__Value__c": "",
        "%vlocity_namespace%__isDefaultHidden__c": false,
        "Name": "Primary Care Provider",
        "VlocityDataPackType": "SObject",
        "VlocityRecordSObjectType": "%vlocity_namespace%__Attribute__c",
        "VlocityRecordSourceKey": "%vlocity_namespace%__Attribute__c/PRYCP-oonb"
    },
    {
        "%vlocity_namespace%__ActiveFlg__c": true,
        "%vlocity_namespace%__AttributeCategoryCode__c": "OUTMEDICALBENEFITS",
        "%vlocity_namespace%__AttributeCategoryId__c": {
            "%vlocity_namespace%__Code__c": "OUTMEDICALBENEFITS",
            "VlocityDataPackType": "VlocityMatchingKeyObject",
            "VlocityMatchingRecordSourceKey": "%vlocity_namespace%__AttributeCategory__c/OUTMEDICALBENEFITS",
            "VlocityRecordSObjectType": "%vlocity_namespace%__AttributeCategory__c"
        },
        "%vlocity_namespace%__AttributeCategoryName__c": "Medical Out of Network Benefits",
        "%vlocity_namespace%__AttributeGroupType__c": "",
        "%vlocity_namespace%__Code__c": "RPD1-oonb",
        "%vlocity_namespace%__Configurable__c": true,
        "%vlocity_namespace%__CustomConfigUiTemplate__c": "",
        "%vlocity_namespace%__Description__c": "",
        "%vlocity_namespace%__DisplaySequence__c": 10,
        "%vlocity_namespace%__EffectiveFromDate__c": "",
        "%vlocity_namespace%__EffectiveUntilDate__c": "",
        "%vlocity_namespace%__Filterable__c": false,
        "%vlocity_namespace%__GlobalKey__c": "367d6b48-54cd-d347-e3fb-e30bd0b6a811",
        "%vlocity_namespace%__HelpText__c": "",
        "%vlocity_namespace%__IsCloneable__c": true,
        "%vlocity_namespace%__IsEncrypted__c": false,
        "%vlocity_namespace%__IsNotAssetizable__c": false,
        "%vlocity_namespace%__IsPrivate__c": false,
        "%vlocity_namespace%__OwnerId__c": "",
        "%vlocity_namespace%__PicklistId__c": "",
        "%vlocity_namespace%__UniqueNameField__c": "",
        "%vlocity_namespace%__ValueType__c": "Text",
        "%vlocity_namespace%__Value__c": "",
        "%vlocity_namespace%__isDefaultHidden__c": false,
        "Name": "Retail Prescription Drugs–Tier 1",
        "VlocityDataPackType": "SObject",
        "VlocityRecordSObjectType": "%vlocity_namespace%__Attribute__c",
        "VlocityRecordSourceKey": "%vlocity_namespace%__Attribute__c/RPD1-oonb"
    },
    {
        "%vlocity_namespace%__ActiveFlg__c": true,
        "%vlocity_namespace%__AttributeCategoryCode__c": "OUTMEDICALBENEFITS",
        "%vlocity_namespace%__AttributeCategoryId__c": {
            "%vlocity_namespace%__Code__c": "OUTMEDICALBENEFITS",
            "VlocityDataPackType": "VlocityMatchingKeyObject",
            "VlocityMatchingRecordSourceKey": "%vlocity_namespace%__AttributeCategory__c/OUTMEDICALBENEFITS",
            "VlocityRecordSObjectType": "%vlocity_namespace%__AttributeCategory__c"
        },
        "%vlocity_namespace%__AttributeCategoryName__c": "Medical Out of Network Benefits",
        "%vlocity_namespace%__AttributeGroupType__c": "",
        "%vlocity_namespace%__Code__c": "RPD2-oonb",
        "%vlocity_namespace%__Configurable__c": true,
        "%vlocity_namespace%__CustomConfigUiTemplate__c": "",
        "%vlocity_namespace%__Description__c": "",
        "%vlocity_namespace%__DisplaySequence__c": 11,
        "%vlocity_namespace%__EffectiveFromDate__c": "",
        "%vlocity_namespace%__EffectiveUntilDate__c": "",
        "%vlocity_namespace%__Filterable__c": false,
        "%vlocity_namespace%__GlobalKey__c": "59e34f4e-16a9-b4df-015f-b9b8d455c144",
        "%vlocity_namespace%__HelpText__c": "",
        "%vlocity_namespace%__IsCloneable__c": true,
        "%vlocity_namespace%__IsEncrypted__c": false,
        "%vlocity_namespace%__IsNotAssetizable__c": false,
        "%vlocity_namespace%__IsPrivate__c": false,
        "%vlocity_namespace%__OwnerId__c": "",
        "%vlocity_namespace%__PicklistId__c": "",
        "%vlocity_namespace%__UniqueNameField__c": "",
        "%vlocity_namespace%__ValueType__c": "Text",
        "%vlocity_namespace%__Value__c": "",
        "%vlocity_namespace%__isDefaultHidden__c": false,
        "Name": "Retail Prescription Drugs–Tier 2",
        "VlocityDataPackType": "SObject",
        "VlocityRecordSObjectType": "%vlocity_namespace%__Attribute__c",
        "VlocityRecordSourceKey": "%vlocity_namespace%__Attribute__c/RPD2-oonb"
    },
    {
        "%vlocity_namespace%__ActiveFlg__c": true,
        "%vlocity_namespace%__AttributeCategoryCode__c": "OUTMEDICALBENEFITS",
        "%vlocity_namespace%__AttributeCategoryId__c": {
            "%vlocity_namespace%__Code__c": "OUTMEDICALBENEFITS",
            "VlocityDataPackType": "VlocityMatchingKeyObject",
            "VlocityMatchingRecordSourceKey": "%vlocity_namespace%__AttributeCategory__c/OUTMEDICALBENEFITS",
            "VlocityRecordSObjectType": "%vlocity_namespace%__AttributeCategory__c"
        },
        "%vlocity_namespace%__AttributeCategoryName__c": "Medical Out of Network Benefits",
        "%vlocity_namespace%__AttributeGroupType__c": "",
        "%vlocity_namespace%__Code__c": "RPD3-oonb",
        "%vlocity_namespace%__Configurable__c": true,
        "%vlocity_namespace%__CustomConfigUiTemplate__c": "",
        "%vlocity_namespace%__Description__c": "",
        "%vlocity_namespace%__DisplaySequence__c": 13,
        "%vlocity_namespace%__EffectiveFromDate__c": "",
        "%vlocity_namespace%__EffectiveUntilDate__c": "",
        "%vlocity_namespace%__Filterable__c": false,
        "%vlocity_namespace%__GlobalKey__c": "d27ef51b-02ab-d1e1-3246-16be0747e6ca",
        "%vlocity_namespace%__HelpText__c": "",
        "%vlocity_namespace%__IsCloneable__c": true,
        "%vlocity_namespace%__IsEncrypted__c": false,
        "%vlocity_namespace%__IsNotAssetizable__c": false,
        "%vlocity_namespace%__IsPrivate__c": false,
        "%vlocity_namespace%__OwnerId__c": "",
        "%vlocity_namespace%__PicklistId__c": "",
        "%vlocity_namespace%__UniqueNameField__c": "",
        "%vlocity_namespace%__ValueType__c": "Text",
        "%vlocity_namespace%__Value__c": "",
        "%vlocity_namespace%__isDefaultHidden__c": false,
        "Name": "Retail Prescription Drugs–Tier 3",
        "VlocityDataPackType": "SObject",
        "VlocityRecordSObjectType": "%vlocity_namespace%__Attribute__c",
        "VlocityRecordSourceKey": "%vlocity_namespace%__Attribute__c/RPD3-oonb"
    },
    {
        "%vlocity_namespace%__ActiveFlg__c": true,
        "%vlocity_namespace%__AttributeCategoryCode__c": "OUTMEDICALBENEFITS",
        "%vlocity_namespace%__AttributeCategoryId__c": {
            "%vlocity_namespace%__Code__c": "OUTMEDICALBENEFITS",
            "VlocityDataPackType": "VlocityMatchingKeyObject",
            "VlocityMatchingRecordSourceKey": "%vlocity_namespace%__AttributeCategory__c/OUTMEDICALBENEFITS",
            "VlocityRecordSObjectType": "%vlocity_namespace%__AttributeCategory__c"
        },
        "%vlocity_namespace%__AttributeCategoryName__c": "Medical Out of Network Benefits",
        "%vlocity_namespace%__AttributeGroupType__c": "",
        "%vlocity_namespace%__Code__c": "RPD4-oonb",
        "%vlocity_namespace%__Configurable__c": true,
        "%vlocity_namespace%__CustomConfigUiTemplate__c": "",
        "%vlocity_namespace%__Description__c": "",
        "%vlocity_namespace%__DisplaySequence__c": 12,
        "%vlocity_namespace%__EffectiveFromDate__c": "",
        "%vlocity_namespace%__EffectiveUntilDate__c": "",
        "%vlocity_namespace%__Filterable__c": false,
        "%vlocity_namespace%__GlobalKey__c": "2228ad34-7ebb-d35b-aaad-7cf8e9c00ac7",
        "%vlocity_namespace%__HelpText__c": "",
        "%vlocity_namespace%__IsCloneable__c": true,
        "%vlocity_namespace%__IsEncrypted__c": false,
        "%vlocity_namespace%__IsNotAssetizable__c": false,
        "%vlocity_namespace%__IsPrivate__c": false,
        "%vlocity_namespace%__OwnerId__c": "",
        "%vlocity_namespace%__PicklistId__c": "",
        "%vlocity_namespace%__UniqueNameField__c": "",
        "%vlocity_namespace%__ValueType__c": "Text",
        "%vlocity_namespace%__Value__c": "",
        "%vlocity_namespace%__isDefaultHidden__c": false,
        "Name": "Retail Prescription Drugs–Tier 4",
        "VlocityDataPackType": "SObject",
        "VlocityRecordSObjectType": "%vlocity_namespace%__Attribute__c",
        "VlocityRecordSourceKey": "%vlocity_namespace%__Attribute__c/RPD4-oonb"
    },
    {
        "%vlocity_namespace%__ActiveFlg__c": true,
        "%vlocity_namespace%__AttributeCategoryCode__c": "OUTMEDICALBENEFITS",
        "%vlocity_namespace%__AttributeCategoryId__c": {
            "%vlocity_namespace%__Code__c": "OUTMEDICALBENEFITS",
            "VlocityDataPackType": "VlocityMatchingKeyObject",
            "VlocityMatchingRecordSourceKey": "%vlocity_namespace%__AttributeCategory__c/OUTMEDICALBENEFITS",
            "VlocityRecordSObjectType": "%vlocity_namespace%__AttributeCategory__c"
        },
        "%vlocity_namespace%__AttributeCategoryName__c": "Medical Out of Network Benefits",
        "%vlocity_namespace%__AttributeGroupType__c": "",
        "%vlocity_namespace%__Code__c": "RPD5-oonb",
        "%vlocity_namespace%__Configurable__c": true,
        "%vlocity_namespace%__CustomConfigUiTemplate__c": "",
        "%vlocity_namespace%__Description__c": "",
        "%vlocity_namespace%__DisplaySequence__c": 14,
        "%vlocity_namespace%__EffectiveFromDate__c": "",
        "%vlocity_namespace%__EffectiveUntilDate__c": "",
        "%vlocity_namespace%__Filterable__c": false,
        "%vlocity_namespace%__GlobalKey__c": "1d36e37b-25cd-d81b-862d-16b1541bd57d",
        "%vlocity_namespace%__HelpText__c": "",
        "%vlocity_namespace%__IsCloneable__c": true,
        "%vlocity_namespace%__IsEncrypted__c": false,
        "%vlocity_namespace%__IsNotAssetizable__c": false,
        "%vlocity_namespace%__IsPrivate__c": false,
        "%vlocity_namespace%__OwnerId__c": "",
        "%vlocity_namespace%__PicklistId__c": "",
        "%vlocity_namespace%__UniqueNameField__c": "",
        "%vlocity_namespace%__ValueType__c": "Text",
        "%vlocity_namespace%__Value__c": "",
        "%vlocity_namespace%__isDefaultHidden__c": false,
        "Name": "Retail Prescription Drugs–Tier 5",
        "VlocityDataPackType": "SObject",
        "VlocityRecordSObjectType": "%vlocity_namespace%__Attribute__c",
        "VlocityRecordSourceKey": "%vlocity_namespace%__Attribute__c/RPD5-oonb"
    },
    {
        "%vlocity_namespace%__ActiveFlg__c": true,
        "%vlocity_namespace%__AttributeCategoryCode__c": "OUTMEDICALBENEFITS",
        "%vlocity_namespace%__AttributeCategoryId__c": {
            "%vlocity_namespace%__Code__c": "OUTMEDICALBENEFITS",
            "VlocityDataPackType": "VlocityMatchingKeyObject",
            "VlocityMatchingRecordSourceKey": "%vlocity_namespace%__AttributeCategory__c/OUTMEDICALBENEFITS",
            "VlocityRecordSObjectType": "%vlocity_namespace%__AttributeCategory__c"
        },
        "%vlocity_namespace%__AttributeCategoryName__c": "Medical Out of Network Benefits",
        "%vlocity_namespace%__AttributeGroupType__c": "",
        "%vlocity_namespace%__Code__c": "SNFC-oonb",
        "%vlocity_namespace%__Configurable__c": true,
        "%vlocity_namespace%__CustomConfigUiTemplate__c": "",
        "%vlocity_namespace%__Description__c": "",
        "%vlocity_namespace%__DisplaySequence__c": 29,
        "%vlocity_namespace%__EffectiveFromDate__c": "",
        "%vlocity_namespace%__EffectiveUntilDate__c": "",
        "%vlocity_namespace%__Filterable__c": false,
        "%vlocity_namespace%__GlobalKey__c": "f52ce1c4-2ad5-c757-a05d-af4f2943cb28",
        "%vlocity_namespace%__HelpText__c": "",
        "%vlocity_namespace%__IsCloneable__c": true,
        "%vlocity_namespace%__IsEncrypted__c": false,
        "%vlocity_namespace%__IsNotAssetizable__c": false,
        "%vlocity_namespace%__IsPrivate__c": false,
        "%vlocity_namespace%__OwnerId__c": "",
        "%vlocity_namespace%__PicklistId__c": "",
        "%vlocity_namespace%__UniqueNameField__c": "",
        "%vlocity_namespace%__ValueType__c": "Text",
        "%vlocity_namespace%__Value__c": "",
        "%vlocity_namespace%__isDefaultHidden__c": false,
        "Name": "Skilled Nursing Facility Care",
        "VlocityDataPackType": "SObject",
        "VlocityRecordSObjectType": "%vlocity_namespace%__Attribute__c",
        "VlocityRecordSourceKey": "%vlocity_namespace%__Attribute__c/SNFC-oonb"
    },
    {
        "%vlocity_namespace%__ActiveFlg__c": true,
        "%vlocity_namespace%__AttributeCategoryCode__c": "OUTMEDICALBENEFITS",
        "%vlocity_namespace%__AttributeCategoryId__c": {
            "%vlocity_namespace%__Code__c": "OUTMEDICALBENEFITS",
            "VlocityDataPackType": "VlocityMatchingKeyObject",
            "VlocityMatchingRecordSourceKey": "%vlocity_namespace%__AttributeCategory__c/OUTMEDICALBENEFITS",
            "VlocityRecordSObjectType": "%vlocity_namespace%__AttributeCategory__c"
        },
        "%vlocity_namespace%__AttributeCategoryName__c": "Medical Out of Network Benefits",
        "%vlocity_namespace%__AttributeGroupType__c": "",
        "%vlocity_namespace%__Code__c": "SPCP-oonb",
        "%vlocity_namespace%__Configurable__c": true,
        "%vlocity_namespace%__CustomConfigUiTemplate__c": "",
        "%vlocity_namespace%__Description__c": "",
        "%vlocity_namespace%__DisplaySequence__c": 2,
        "%vlocity_namespace%__EffectiveFromDate__c": "",
        "%vlocity_namespace%__EffectiveUntilDate__c": "",
        "%vlocity_namespace%__Filterable__c": false,
        "%vlocity_namespace%__GlobalKey__c": "ddab5a26-568b-5b16-6136-d136feee6255",
        "%vlocity_namespace%__HelpText__c": "",
        "%vlocity_namespace%__IsCloneable__c": true,
        "%vlocity_namespace%__IsEncrypted__c": false,
        "%vlocity_namespace%__IsNotAssetizable__c": false,
        "%vlocity_namespace%__IsPrivate__c": false,
        "%vlocity_namespace%__OwnerId__c": "",
        "%vlocity_namespace%__PicklistId__c": "",
        "%vlocity_namespace%__UniqueNameField__c": "",
        "%vlocity_namespace%__ValueType__c": "Text",
        "%vlocity_namespace%__Value__c": "",
        "%vlocity_namespace%__isDefaultHidden__c": false,
        "Name": "Specialist Co-Pay",
        "VlocityDataPackType": "SObject",
        "VlocityRecordSObjectType": "%vlocity_namespace%__Attribute__c",
        "VlocityRecordSourceKey": "%vlocity_namespace%__Attribute__c/SPCP-oonb"
    },
    {
        "%vlocity_namespace%__ActiveFlg__c": true,
        "%vlocity_namespace%__AttributeCategoryCode__c": "OUTMEDICALBENEFITS",
        "%vlocity_namespace%__AttributeCategoryId__c": {
            "%vlocity_namespace%__Code__c": "OUTMEDICALBENEFITS",
            "VlocityDataPackType": "VlocityMatchingKeyObject",
            "VlocityMatchingRecordSourceKey": "%vlocity_namespace%__AttributeCategory__c/OUTMEDICALBENEFITS",
            "VlocityRecordSObjectType": "%vlocity_namespace%__AttributeCategory__c"
        },
        "%vlocity_namespace%__AttributeCategoryName__c": "Medical Out of Network Benefits",
        "%vlocity_namespace%__AttributeGroupType__c": "",
        "%vlocity_namespace%__Code__c": "TRAN-oonb",
        "%vlocity_namespace%__Configurable__c": true,
        "%vlocity_namespace%__CustomConfigUiTemplate__c": "",
        "%vlocity_namespace%__Description__c": "",
        "%vlocity_namespace%__DisplaySequence__c": 38,
        "%vlocity_namespace%__EffectiveFromDate__c": "",
        "%vlocity_namespace%__EffectiveUntilDate__c": "",
        "%vlocity_namespace%__Filterable__c": false,
        "%vlocity_namespace%__GlobalKey__c": "ad11ae4e-fc5a-d15c-00a5-50929df65792",
        "%vlocity_namespace%__HelpText__c": "",
        "%vlocity_namespace%__IsCloneable__c": true,
        "%vlocity_namespace%__IsEncrypted__c": false,
        "%vlocity_namespace%__IsNotAssetizable__c": false,
        "%vlocity_namespace%__IsPrivate__c": false,
        "%vlocity_namespace%__OwnerId__c": "",
        "%vlocity_namespace%__PicklistId__c": "",
        "%vlocity_namespace%__UniqueNameField__c": "",
        "%vlocity_namespace%__ValueType__c": "Text",
        "%vlocity_namespace%__Value__c": "",
        "%vlocity_namespace%__isDefaultHidden__c": false,
        "Name": "Transportation",
        "VlocityDataPackType": "SObject",
        "VlocityRecordSObjectType": "%vlocity_namespace%__Attribute__c",
        "VlocityRecordSourceKey": "%vlocity_namespace%__Attribute__c/TRAN-oonb"
    },
    {
        "%vlocity_namespace%__ActiveFlg__c": true,
        "%vlocity_namespace%__AttributeCategoryCode__c": "OUTMEDICALBENEFITS",
        "%vlocity_namespace%__AttributeCategoryId__c": {
            "%vlocity_namespace%__Code__c": "OUTMEDICALBENEFITS",
            "VlocityDataPackType": "VlocityMatchingKeyObject",
            "VlocityMatchingRecordSourceKey": "%vlocity_namespace%__AttributeCategory__c/OUTMEDICALBENEFITS",
            "VlocityRecordSObjectType": "%vlocity_namespace%__AttributeCategory__c"
        },
        "%vlocity_namespace%__AttributeCategoryName__c": "Medical Out of Network Benefits",
        "%vlocity_namespace%__AttributeGroupType__c": "",
        "%vlocity_namespace%__Code__c": "TRAV-oonb",
        "%vlocity_namespace%__Configurable__c": true,
        "%vlocity_namespace%__CustomConfigUiTemplate__c": "",
        "%vlocity_namespace%__Description__c": "",
        "%vlocity_namespace%__DisplaySequence__c": 43,
        "%vlocity_namespace%__EffectiveFromDate__c": "",
        "%vlocity_namespace%__EffectiveUntilDate__c": "",
        "%vlocity_namespace%__Filterable__c": false,
        "%vlocity_namespace%__GlobalKey__c": "5c38896b-d89f-2095-4dee-a31c7e7acb27",
        "%vlocity_namespace%__HelpText__c": "",
        "%vlocity_namespace%__IsCloneable__c": true,
        "%vlocity_namespace%__IsEncrypted__c": false,
        "%vlocity_namespace%__IsNotAssetizable__c": false,
        "%vlocity_namespace%__IsPrivate__c": false,
        "%vlocity_namespace%__OwnerId__c": "",
        "%vlocity_namespace%__PicklistId__c": "",
        "%vlocity_namespace%__UniqueNameField__c": "",
        "%vlocity_namespace%__ValueType__c": "Text",
        "%vlocity_namespace%__Value__c": "",
        "%vlocity_namespace%__isDefaultHidden__c": false,
        "Name": "Travel Reimbursement",
        "VlocityDataPackType": "SObject",
        "VlocityRecordSObjectType": "%vlocity_namespace%__Attribute__c",
        "VlocityRecordSourceKey": "%vlocity_namespace%__Attribute__c/TRAV-oonb"
    },
    {
        "%vlocity_namespace%__ActiveFlg__c": true,
        "%vlocity_namespace%__AttributeCategoryCode__c": "OUTMEDICALBENEFITS",
        "%vlocity_namespace%__AttributeCategoryId__c": {
            "%vlocity_namespace%__Code__c": "OUTMEDICALBENEFITS",
            "VlocityDataPackType": "VlocityMatchingKeyObject",
            "VlocityMatchingRecordSourceKey": "%vlocity_namespace%__AttributeCategory__c/OUTMEDICALBENEFITS",
            "VlocityRecordSObjectType": "%vlocity_namespace%__AttributeCategory__c"
        },
        "%vlocity_namespace%__AttributeCategoryName__c": "Medical Out of Network Benefits",
        "%vlocity_namespace%__AttributeGroupType__c": "",
        "%vlocity_namespace%__Code__c": "UCCP-oonb",
        "%vlocity_namespace%__Configurable__c": true,
        "%vlocity_namespace%__CustomConfigUiTemplate__c": "",
        "%vlocity_namespace%__Description__c": "",
        "%vlocity_namespace%__DisplaySequence__c": 25,
        "%vlocity_namespace%__EffectiveFromDate__c": "",
        "%vlocity_namespace%__EffectiveUntilDate__c": "",
        "%vlocity_namespace%__Filterable__c": false,
        "%vlocity_namespace%__GlobalKey__c": "d6fc794f-f5c3-bdf1-3080-193a117629f3",
        "%vlocity_namespace%__HelpText__c": "",
        "%vlocity_namespace%__IsCloneable__c": true,
        "%vlocity_namespace%__IsEncrypted__c": false,
        "%vlocity_namespace%__IsNotAssetizable__c": false,
        "%vlocity_namespace%__IsPrivate__c": false,
        "%vlocity_namespace%__OwnerId__c": "",
        "%vlocity_namespace%__PicklistId__c": "",
        "%vlocity_namespace%__UniqueNameField__c": "",
        "%vlocity_namespace%__ValueType__c": "Text",
        "%vlocity_namespace%__Value__c": "",
        "%vlocity_namespace%__isDefaultHidden__c": false,
        "Name": "Urgent Care Co-Pay",
        "VlocityDataPackType": "SObject",
        "VlocityRecordSObjectType": "%vlocity_namespace%__Attribute__c",
        "VlocityRecordSourceKey": "%vlocity_namespace%__Attribute__c/UCCP-oonb"
    },
    {
        "%vlocity_namespace%__ActiveFlg__c": true,
        "%vlocity_namespace%__AttributeCategoryCode__c": "OUTMEDICALBENEFITS",
        "%vlocity_namespace%__AttributeCategoryId__c": {
            "%vlocity_namespace%__Code__c": "OUTMEDICALBENEFITS",
            "VlocityDataPackType": "VlocityMatchingKeyObject",
            "VlocityMatchingRecordSourceKey": "%vlocity_namespace%__AttributeCategory__c/OUTMEDICALBENEFITS",
            "VlocityRecordSObjectType": "%vlocity_namespace%__AttributeCategory__c"
        },
        "%vlocity_namespace%__AttributeCategoryName__c": "Medical Out of Network Benefits",
        "%vlocity_namespace%__AttributeGroupType__c": "",
        "%vlocity_namespace%__Code__c": "W&FM-oonb",
        "%vlocity_namespace%__Configurable__c": true,
        "%vlocity_namespace%__CustomConfigUiTemplate__c": "",
        "%vlocity_namespace%__Description__c": "",
        "%vlocity_namespace%__DisplaySequence__c": 30,
        "%vlocity_namespace%__EffectiveFromDate__c": "",
        "%vlocity_namespace%__EffectiveUntilDate__c": "",
        "%vlocity_namespace%__Filterable__c": false,
        "%vlocity_namespace%__GlobalKey__c": "3033460b-184e-fd8a-809a-753a3348a097",
        "%vlocity_namespace%__HelpText__c": "",
        "%vlocity_namespace%__IsCloneable__c": true,
        "%vlocity_namespace%__IsEncrypted__c": false,
        "%vlocity_namespace%__IsNotAssetizable__c": false,
        "%vlocity_namespace%__IsPrivate__c": false,
        "%vlocity_namespace%__OwnerId__c": "",
        "%vlocity_namespace%__PicklistId__c": "",
        "%vlocity_namespace%__UniqueNameField__c": "",
        "%vlocity_namespace%__ValueType__c": "Text",
        "%vlocity_namespace%__Value__c": "",
        "%vlocity_namespace%__isDefaultHidden__c": false,
        "Name": "Wellness & Fitness Membership",
        "VlocityDataPackType": "SObject",
        "VlocityRecordSObjectType": "%vlocity_namespace%__Attribute__c",
        "VlocityRecordSourceKey": "%vlocity_namespace%__Attribute__c/W&FM-oonb"
    },
    {
        "%vlocity_namespace%__ActiveFlg__c": true,
        "%vlocity_namespace%__AttributeCategoryCode__c": "OUTMEDICALBENEFITS",
        "%vlocity_namespace%__AttributeCategoryId__c": {
            "%vlocity_namespace%__Code__c": "OUTMEDICALBENEFITS",
            "VlocityDataPackType": "VlocityMatchingKeyObject",
            "VlocityMatchingRecordSourceKey": "%vlocity_namespace%__AttributeCategory__c/OUTMEDICALBENEFITS",
            "VlocityRecordSObjectType": "%vlocity_namespace%__AttributeCategory__c"
        },
        "%vlocity_namespace%__AttributeCategoryName__c": "Medical Out of Network Benefits",
        "%vlocity_namespace%__AttributeGroupType__c": "",
        "%vlocity_namespace%__Code__c": "a6ab9c7f-0d79-2d66-e6cb-49a6508c7ca0",
        "%vlocity_namespace%__Configurable__c": true,
        "%vlocity_namespace%__CustomConfigUiTemplate__c": "",
        "%vlocity_namespace%__Description__c": "",
        "%vlocity_namespace%__DisplaySequence__c": 20,
        "%vlocity_namespace%__EffectiveFromDate__c": "",
        "%vlocity_namespace%__EffectiveUntilDate__c": "",
        "%vlocity_namespace%__Filterable__c": false,
        "%vlocity_namespace%__GlobalKey__c": "8ffb3fe5-6556-6051-a482-01d10c2ebced",
        "%vlocity_namespace%__HelpText__c": "",
        "%vlocity_namespace%__IsCloneable__c": true,
        "%vlocity_namespace%__IsEncrypted__c": false,
        "%vlocity_namespace%__IsNotAssetizable__c": false,
        "%vlocity_namespace%__IsPrivate__c": false,
        "%vlocity_namespace%__OwnerId__c": "",
        "%vlocity_namespace%__PicklistId__c": "",
        "%vlocity_namespace%__UniqueNameField__c": "",
        "%vlocity_namespace%__ValueType__c": "Text",
        "%vlocity_namespace%__Value__c": "",
        "%vlocity_namespace%__isDefaultHidden__c": false,
        "Name": "In-Patient Hospital Care",
        "VlocityDataPackType": "SObject",
        "VlocityRecordSObjectType": "%vlocity_namespace%__Attribute__c",
        "VlocityRecordSourceKey": "%vlocity_namespace%__Attribute__c/a6ab9c7f-0d79-2d66-e6cb-49a6508c7ca0"
    },
    {
        "%vlocity_namespace%__ActiveFlg__c": true,
        "%vlocity_namespace%__AttributeCategoryCode__c": "OUTMEDICALBENEFITS",
        "%vlocity_namespace%__AttributeCategoryId__c": {
            "%vlocity_namespace%__Code__c": "OUTMEDICALBENEFITS",
            "VlocityDataPackType": "VlocityMatchingKeyObject",
            "VlocityMatchingRecordSourceKey": "%vlocity_namespace%__AttributeCategory__c/OUTMEDICALBENEFITS",
            "VlocityRecordSObjectType": "%vlocity_namespace%__AttributeCategory__c"
        },
        "%vlocity_namespace%__AttributeCategoryName__c": "Medical Out of Network Benefits",
        "%vlocity_namespace%__AttributeGroupType__c": "",
        "%vlocity_namespace%__Code__c": "a6ec2174-1f6c-43da-9de5-816d5c0e583b",
        "%vlocity_namespace%__Configurable__c": true,
        "%vlocity_namespace%__CustomConfigUiTemplate__c": "",
        "%vlocity_namespace%__Description__c": "",
        "%vlocity_namespace%__DisplaySequence__c": 6,
        "%vlocity_namespace%__EffectiveFromDate__c": "",
        "%vlocity_namespace%__EffectiveUntilDate__c": "",
        "%vlocity_namespace%__Filterable__c": false,
        "%vlocity_namespace%__GlobalKey__c": "b6f80297-d00d-2464-5d3f-caa39740a821",
        "%vlocity_namespace%__HelpText__c": "",
        "%vlocity_namespace%__IsCloneable__c": true,
        "%vlocity_namespace%__IsEncrypted__c": false,
        "%vlocity_namespace%__IsNotAssetizable__c": false,
        "%vlocity_namespace%__IsPrivate__c": false,
        "%vlocity_namespace%__OwnerId__c": "",
        "%vlocity_namespace%__PicklistId__c": "",
        "%vlocity_namespace%__UniqueNameField__c": "",
        "%vlocity_namespace%__ValueType__c": "Text",
        "%vlocity_namespace%__Value__c": "",
        "%vlocity_namespace%__isDefaultHidden__c": false,
        "Name": "Annual Out-of-Pocket Limit",
        "VlocityDataPackType": "SObject",
        "VlocityRecordSObjectType": "%vlocity_namespace%__Attribute__c",
        "VlocityRecordSourceKey": "%vlocity_namespace%__Attribute__c/a6ec2174-1f6c-43da-9de5-816d5c0e583b"
    },
    {
        "%vlocity_namespace%__ActiveFlg__c": true,
        "%vlocity_namespace%__AttributeCategoryCode__c": "OUTMEDICALBENEFITS",
        "%vlocity_namespace%__AttributeCategoryId__c": {
            "%vlocity_namespace%__Code__c": "OUTMEDICALBENEFITS",
            "VlocityDataPackType": "VlocityMatchingKeyObject",
            "VlocityMatchingRecordSourceKey": "%vlocity_namespace%__AttributeCategory__c/OUTMEDICALBENEFITS",
            "VlocityRecordSObjectType": "%vlocity_namespace%__AttributeCategory__c"
        },
        "%vlocity_namespace%__AttributeCategoryName__c": "Medical Out of Network Benefits",
        "%vlocity_namespace%__AttributeGroupType__c": "",
        "%vlocity_namespace%__Code__c": "aa116023-1216-4c75-baca-2a7ba898f952",
        "%vlocity_namespace%__Configurable__c": true,
        "%vlocity_namespace%__CustomConfigUiTemplate__c": "",
        "%vlocity_namespace%__Description__c": "",
        "%vlocity_namespace%__DisplaySequence__c": 42,
        "%vlocity_namespace%__EffectiveFromDate__c": "",
        "%vlocity_namespace%__EffectiveUntilDate__c": "",
        "%vlocity_namespace%__Filterable__c": false,
        "%vlocity_namespace%__GlobalKey__c": "1c327fad-13c1-2b96-1ae4-dbb200b91472",
        "%vlocity_namespace%__HelpText__c": "",
        "%vlocity_namespace%__IsCloneable__c": true,
        "%vlocity_namespace%__IsEncrypted__c": false,
        "%vlocity_namespace%__IsNotAssetizable__c": false,
        "%vlocity_namespace%__IsPrivate__c": false,
        "%vlocity_namespace%__OwnerId__c": "",
        "%vlocity_namespace%__PicklistId__c": "",
        "%vlocity_namespace%__UniqueNameField__c": "",
        "%vlocity_namespace%__ValueType__c": "Text",
        "%vlocity_namespace%__Value__c": "",
        "%vlocity_namespace%__isDefaultHidden__c": false,
        "Name": "Nurse Hotline",
        "VlocityDataPackType": "SObject",
        "VlocityRecordSObjectType": "%vlocity_namespace%__Attribute__c",
        "VlocityRecordSourceKey": "%vlocity_namespace%__Attribute__c/aa116023-1216-4c75-baca-2a7ba898f952"
    },
    {
        "%vlocity_namespace%__ActiveFlg__c": true,
        "%vlocity_namespace%__AttributeCategoryCode__c": "OUTMEDICALBENEFITS",
        "%vlocity_namespace%__AttributeCategoryId__c": {
            "%vlocity_namespace%__Code__c": "OUTMEDICALBENEFITS",
            "VlocityDataPackType": "VlocityMatchingKeyObject",
            "VlocityMatchingRecordSourceKey": "%vlocity_namespace%__AttributeCategory__c/OUTMEDICALBENEFITS",
            "VlocityRecordSObjectType": "%vlocity_namespace%__AttributeCategory__c"
        },
        "%vlocity_namespace%__AttributeCategoryName__c": "Medical Out of Network Benefits",
        "%vlocity_namespace%__AttributeGroupType__c": "",
        "%vlocity_namespace%__Code__c": "ab46c92f-a59c-c12d-9fdc-2d96994dfe8b",
        "%vlocity_namespace%__Configurable__c": true,
        "%vlocity_namespace%__CustomConfigUiTemplate__c": "",
        "%vlocity_namespace%__Description__c": "",
        "%vlocity_namespace%__DisplaySequence__c": 39,
        "%vlocity_namespace%__EffectiveFromDate__c": "",
        "%vlocity_namespace%__EffectiveUntilDate__c": "",
        "%vlocity_namespace%__Filterable__c": false,
        "%vlocity_namespace%__GlobalKey__c": "78af39c2-79c0-b685-2a49-28a83658c414",
        "%vlocity_namespace%__HelpText__c": "",
        "%vlocity_namespace%__IsCloneable__c": true,
        "%vlocity_namespace%__IsEncrypted__c": false,
        "%vlocity_namespace%__IsNotAssetizable__c": false,
        "%vlocity_namespace%__IsPrivate__c": false,
        "%vlocity_namespace%__OwnerId__c": "",
        "%vlocity_namespace%__PicklistId__c": "",
        "%vlocity_namespace%__UniqueNameField__c": "",
        "%vlocity_namespace%__ValueType__c": "Text",
        "%vlocity_namespace%__Value__c": "",
        "%vlocity_namespace%__isDefaultHidden__c": false,
        "Name": "Chiropractic Care",
        "VlocityDataPackType": "SObject",
        "VlocityRecordSObjectType": "%vlocity_namespace%__Attribute__c",
        "VlocityRecordSourceKey": "%vlocity_namespace%__Attribute__c/ab46c92f-a59c-c12d-9fdc-2d96994dfe8b"
    },
    {
        "%vlocity_namespace%__ActiveFlg__c": true,
        "%vlocity_namespace%__AttributeCategoryCode__c": "OUTMEDICALBENEFITS",
        "%vlocity_namespace%__AttributeCategoryId__c": {
            "%vlocity_namespace%__Code__c": "OUTMEDICALBENEFITS",
            "VlocityDataPackType": "VlocityMatchingKeyObject",
            "VlocityMatchingRecordSourceKey": "%vlocity_namespace%__AttributeCategory__c/OUTMEDICALBENEFITS",
            "VlocityRecordSObjectType": "%vlocity_namespace%__AttributeCategory__c"
        },
        "%vlocity_namespace%__AttributeCategoryName__c": "Medical Out of Network Benefits",
        "%vlocity_namespace%__AttributeGroupType__c": "",
        "%vlocity_namespace%__Code__c": "bf9fd70a-a25a-e7b7-ab2d-eafd746f4115",
        "%vlocity_namespace%__Configurable__c": true,
        "%vlocity_namespace%__CustomConfigUiTemplate__c": "",
        "%vlocity_namespace%__Description__c": "",
        "%vlocity_namespace%__DisplaySequence__c": 31,
        "%vlocity_namespace%__EffectiveFromDate__c": "",
        "%vlocity_namespace%__EffectiveUntilDate__c": "",
        "%vlocity_namespace%__Filterable__c": false,
        "%vlocity_namespace%__GlobalKey__c": "91f15b8d-c53f-13e3-8080-42612f671ec1",
        "%vlocity_namespace%__HelpText__c": "",
        "%vlocity_namespace%__IsCloneable__c": true,
        "%vlocity_namespace%__IsEncrypted__c": false,
        "%vlocity_namespace%__IsNotAssetizable__c": false,
        "%vlocity_namespace%__IsPrivate__c": false,
        "%vlocity_namespace%__OwnerId__c": "",
        "%vlocity_namespace%__PicklistId__c": "",
        "%vlocity_namespace%__UniqueNameField__c": "",
        "%vlocity_namespace%__ValueType__c": "Text",
        "%vlocity_namespace%__Value__c": "",
        "%vlocity_namespace%__isDefaultHidden__c": false,
        "Name": "Annual Routine Physical",
        "VlocityDataPackType": "SObject",
        "VlocityRecordSObjectType": "%vlocity_namespace%__Attribute__c",
        "VlocityRecordSourceKey": "%vlocity_namespace%__Attribute__c/bf9fd70a-a25a-e7b7-ab2d-eafd746f4115"
    },
    {
        "%vlocity_namespace%__ActiveFlg__c": true,
        "%vlocity_namespace%__AttributeCategoryCode__c": "OUTMEDICALBENEFITS",
        "%vlocity_namespace%__AttributeCategoryId__c": {
            "%vlocity_namespace%__Code__c": "OUTMEDICALBENEFITS",
            "VlocityDataPackType": "VlocityMatchingKeyObject",
            "VlocityMatchingRecordSourceKey": "%vlocity_namespace%__AttributeCategory__c/OUTMEDICALBENEFITS",
            "VlocityRecordSObjectType": "%vlocity_namespace%__AttributeCategory__c"
        },
        "%vlocity_namespace%__AttributeCategoryName__c": "Medical Out of Network Benefits",
        "%vlocity_namespace%__AttributeGroupType__c": "",
        "%vlocity_namespace%__Code__c": "cafc327a-b441-2aee-a644-0194ec015310",
        "%vlocity_namespace%__Configurable__c": true,
        "%vlocity_namespace%__CustomConfigUiTemplate__c": "",
        "%vlocity_namespace%__Description__c": "",
        "%vlocity_namespace%__DisplaySequence__c": 15,
        "%vlocity_namespace%__EffectiveFromDate__c": "",
        "%vlocity_namespace%__EffectiveUntilDate__c": "",
        "%vlocity_namespace%__Filterable__c": false,
        "%vlocity_namespace%__GlobalKey__c": "34b8f748-89db-d68d-cd6f-48dbf447872b",
        "%vlocity_namespace%__HelpText__c": "",
        "%vlocity_namespace%__IsCloneable__c": true,
        "%vlocity_namespace%__IsEncrypted__c": false,
        "%vlocity_namespace%__IsNotAssetizable__c": false,
        "%vlocity_namespace%__IsPrivate__c": false,
        "%vlocity_namespace%__OwnerId__c": "",
        "%vlocity_namespace%__PicklistId__c": "",
        "%vlocity_namespace%__UniqueNameField__c": "",
        "%vlocity_namespace%__ValueType__c": "Text",
        "%vlocity_namespace%__Value__c": "",
        "%vlocity_namespace%__isDefaultHidden__c": false,
        "Name": "Mail Order Prescription Drugs–Tier 1 (90-Day Supply)",
        "VlocityDataPackType": "SObject",
        "VlocityRecordSObjectType": "%vlocity_namespace%__Attribute__c",
        "VlocityRecordSourceKey": "%vlocity_namespace%__Attribute__c/cafc327a-b441-2aee-a644-0194ec015310"
    },
    {
        "%vlocity_namespace%__ActiveFlg__c": true,
        "%vlocity_namespace%__AttributeCategoryCode__c": "OUTMEDICALBENEFITS",
        "%vlocity_namespace%__AttributeCategoryId__c": {
            "%vlocity_namespace%__Code__c": "OUTMEDICALBENEFITS",
            "VlocityDataPackType": "VlocityMatchingKeyObject",
            "VlocityMatchingRecordSourceKey": "%vlocity_namespace%__AttributeCategory__c/OUTMEDICALBENEFITS",
            "VlocityRecordSObjectType": "%vlocity_namespace%__AttributeCategory__c"
        },
        "%vlocity_namespace%__AttributeCategoryName__c": "Medical Out of Network Benefits",
        "%vlocity_namespace%__AttributeGroupType__c": "",
        "%vlocity_namespace%__Code__c": "d49a8449-393d-8ba9-ce1d-057702dced7f",
        "%vlocity_namespace%__Configurable__c": true,
        "%vlocity_namespace%__CustomConfigUiTemplate__c": "",
        "%vlocity_namespace%__Description__c": "",
        "%vlocity_namespace%__DisplaySequence__c": 9,
        "%vlocity_namespace%__EffectiveFromDate__c": "",
        "%vlocity_namespace%__EffectiveUntilDate__c": "",
        "%vlocity_namespace%__Filterable__c": false,
        "%vlocity_namespace%__GlobalKey__c": "b2bff206-862e-6f21-9a63-1928a1256146",
        "%vlocity_namespace%__HelpText__c": "",
        "%vlocity_namespace%__IsCloneable__c": true,
        "%vlocity_namespace%__IsEncrypted__c": false,
        "%vlocity_namespace%__IsNotAssetizable__c": false,
        "%vlocity_namespace%__IsPrivate__c": false,
        "%vlocity_namespace%__OwnerId__c": "",
        "%vlocity_namespace%__PicklistId__c": "",
        "%vlocity_namespace%__UniqueNameField__c": "",
        "%vlocity_namespace%__ValueType__c": "Text",
        "%vlocity_namespace%__Value__c": "",
        "%vlocity_namespace%__isDefaultHidden__c": false,
        "Name": "Annual Prescription Deductible",
        "VlocityDataPackType": "SObject",
        "VlocityRecordSObjectType": "%vlocity_namespace%__Attribute__c",
        "VlocityRecordSourceKey": "%vlocity_namespace%__Attribute__c/d49a8449-393d-8ba9-ce1d-057702dced7f"
    },
    {
        "%vlocity_namespace%__ActiveFlg__c": true,
        "%vlocity_namespace%__AttributeCategoryCode__c": "OUTMEDICALBENEFITS",
        "%vlocity_namespace%__AttributeCategoryId__c": {
            "%vlocity_namespace%__Code__c": "OUTMEDICALBENEFITS",
            "VlocityDataPackType": "VlocityMatchingKeyObject",
            "VlocityMatchingRecordSourceKey": "%vlocity_namespace%__AttributeCategory__c/OUTMEDICALBENEFITS",
            "VlocityRecordSObjectType": "%vlocity_namespace%__AttributeCategory__c"
        },
        "%vlocity_namespace%__AttributeCategoryName__c": "Medical Out of Network Benefits",
        "%vlocity_namespace%__AttributeGroupType__c": "",
        "%vlocity_namespace%__Code__c": "d5c00513-4110-063a-e537-e1506da737ec",
        "%vlocity_namespace%__Configurable__c": true,
        "%vlocity_namespace%__CustomConfigUiTemplate__c": "",
        "%vlocity_namespace%__Description__c": "",
        "%vlocity_namespace%__DisplaySequence__c": 19,
        "%vlocity_namespace%__EffectiveFromDate__c": "",
        "%vlocity_namespace%__EffectiveUntilDate__c": "",
        "%vlocity_namespace%__Filterable__c": false,
        "%vlocity_namespace%__GlobalKey__c": "793dc821-1876-1215-81ac-6cb630467ff6",
        "%vlocity_namespace%__HelpText__c": "",
        "%vlocity_namespace%__IsCloneable__c": true,
        "%vlocity_namespace%__IsEncrypted__c": false,
        "%vlocity_namespace%__IsNotAssetizable__c": false,
        "%vlocity_namespace%__IsPrivate__c": false,
        "%vlocity_namespace%__OwnerId__c": "",
        "%vlocity_namespace%__PicklistId__c": "",
        "%vlocity_namespace%__UniqueNameField__c": "",
        "%vlocity_namespace%__ValueType__c": "Text",
        "%vlocity_namespace%__Value__c": "",
        "%vlocity_namespace%__isDefaultHidden__c": false,
        "Name": "Mail Order Prescription Drugs–Tier 5 (90-Day Supply)",
        "VlocityDataPackType": "SObject",
        "VlocityRecordSObjectType": "%vlocity_namespace%__Attribute__c",
        "VlocityRecordSourceKey": "%vlocity_namespace%__Attribute__c/d5c00513-4110-063a-e537-e1506da737ec"
    },
    {
        "%vlocity_namespace%__ActiveFlg__c": true,
        "%vlocity_namespace%__AttributeCategoryCode__c": "OUTMEDICALBENEFITS",
        "%vlocity_namespace%__AttributeCategoryId__c": {
            "%vlocity_namespace%__Code__c": "OUTMEDICALBENEFITS",
            "VlocityDataPackType": "VlocityMatchingKeyObject",
            "VlocityMatchingRecordSourceKey": "%vlocity_namespace%__AttributeCategory__c/OUTMEDICALBENEFITS",
            "VlocityRecordSObjectType": "%vlocity_namespace%__AttributeCategory__c"
        },
        "%vlocity_namespace%__AttributeCategoryName__c": "Medical Out of Network Benefits",
        "%vlocity_namespace%__AttributeGroupType__c": "",
        "%vlocity_namespace%__Code__c": "df86b260-b183-ce3f-7c4b-1690dc0edff7",
        "%vlocity_namespace%__Configurable__c": true,
        "%vlocity_namespace%__CustomConfigUiTemplate__c": "",
        "%vlocity_namespace%__Description__c": "",
        "%vlocity_namespace%__DisplaySequence__c": 26,
        "%vlocity_namespace%__EffectiveFromDate__c": "",
        "%vlocity_namespace%__EffectiveUntilDate__c": "",
        "%vlocity_namespace%__Filterable__c": false,
        "%vlocity_namespace%__GlobalKey__c": "3a9f56f4-bc39-e255-118d-e99ac2fb01d9",
        "%vlocity_namespace%__HelpText__c": "",
        "%vlocity_namespace%__IsCloneable__c": true,
        "%vlocity_namespace%__IsEncrypted__c": false,
        "%vlocity_namespace%__IsNotAssetizable__c": false,
        "%vlocity_namespace%__IsPrivate__c": false,
        "%vlocity_namespace%__OwnerId__c": "",
        "%vlocity_namespace%__PicklistId__c": "",
        "%vlocity_namespace%__UniqueNameField__c": "",
        "%vlocity_namespace%__ValueType__c": "Text",
        "%vlocity_namespace%__Value__c": "",
        "%vlocity_namespace%__isDefaultHidden__c": false,
        "Name": "Inpatient Mental Health",
        "VlocityDataPackType": "SObject",
        "VlocityRecordSObjectType": "%vlocity_namespace%__Attribute__c",
        "VlocityRecordSourceKey": "%vlocity_namespace%__Attribute__c/df86b260-b183-ce3f-7c4b-1690dc0edff7"
    },
    {
        "%vlocity_namespace%__ActiveFlg__c": true,
        "%vlocity_namespace%__AttributeCategoryCode__c": "OUTMEDICALBENEFITS",
        "%vlocity_namespace%__AttributeCategoryId__c": {
            "%vlocity_namespace%__Code__c": "OUTMEDICALBENEFITS",
            "VlocityDataPackType": "VlocityMatchingKeyObject",
            "VlocityMatchingRecordSourceKey": "%vlocity_namespace%__AttributeCategory__c/OUTMEDICALBENEFITS",
            "VlocityRecordSObjectType": "%vlocity_namespace%__AttributeCategory__c"
        },
        "%vlocity_namespace%__AttributeCategoryName__c": "Medical Out of Network Benefits",
        "%vlocity_namespace%__AttributeGroupType__c": "",
        "%vlocity_namespace%__Code__c": "e6bfc567-85ab-6575-cee6-c4f9599de1d6",
        "%vlocity_namespace%__Configurable__c": true,
        "%vlocity_namespace%__CustomConfigUiTemplate__c": "",
        "%vlocity_namespace%__Description__c": "",
        "%vlocity_namespace%__DisplaySequence__c": 17,
        "%vlocity_namespace%__EffectiveFromDate__c": "",
        "%vlocity_namespace%__EffectiveUntilDate__c": "",
        "%vlocity_namespace%__Filterable__c": false,
        "%vlocity_namespace%__GlobalKey__c": "371f6212-c6f4-ef82-1dd2-d7db91a797dc",
        "%vlocity_namespace%__HelpText__c": "",
        "%vlocity_namespace%__IsCloneable__c": true,
        "%vlocity_namespace%__IsEncrypted__c": false,
        "%vlocity_namespace%__IsNotAssetizable__c": false,
        "%vlocity_namespace%__IsPrivate__c": false,
        "%vlocity_namespace%__OwnerId__c": "",
        "%vlocity_namespace%__PicklistId__c": "",
        "%vlocity_namespace%__UniqueNameField__c": "",
        "%vlocity_namespace%__ValueType__c": "Text",
        "%vlocity_namespace%__Value__c": "",
        "%vlocity_namespace%__isDefaultHidden__c": false,
        "Name": "Mail Order Prescription Drugs–Tier 3 (90-Day Supply)",
        "VlocityDataPackType": "SObject",
        "VlocityRecordSObjectType": "%vlocity_namespace%__Attribute__c",
        "VlocityRecordSourceKey": "%vlocity_namespace%__Attribute__c/e6bfc567-85ab-6575-cee6-c4f9599de1d6"
    },
    {
        "%vlocity_namespace%__ActiveFlg__c": true,
        "%vlocity_namespace%__AttributeCategoryCode__c": "OUTMEDICALBENEFITS",
        "%vlocity_namespace%__AttributeCategoryId__c": {
            "%vlocity_namespace%__Code__c": "OUTMEDICALBENEFITS",
            "VlocityDataPackType": "VlocityMatchingKeyObject",
            "VlocityMatchingRecordSourceKey": "%vlocity_namespace%__AttributeCategory__c/OUTMEDICALBENEFITS",
            "VlocityRecordSObjectType": "%vlocity_namespace%__AttributeCategory__c"
        },
        "%vlocity_namespace%__AttributeCategoryName__c": "Medical Out of Network Benefits",
        "%vlocity_namespace%__AttributeGroupType__c": "",
        "%vlocity_namespace%__Code__c": "e84bfd98-6579-8687-05f8-1358a9213495",
        "%vlocity_namespace%__Configurable__c": true,
        "%vlocity_namespace%__CustomConfigUiTemplate__c": "",
        "%vlocity_namespace%__Description__c": "",
        "%vlocity_namespace%__DisplaySequence__c": 34,
        "%vlocity_namespace%__EffectiveFromDate__c": "",
        "%vlocity_namespace%__EffectiveUntilDate__c": "",
        "%vlocity_namespace%__Filterable__c": false,
        "%vlocity_namespace%__GlobalKey__c": "90b0b020-d561-f671-0df2-a441ef9fb4c0",
        "%vlocity_namespace%__HelpText__c": "",
        "%vlocity_namespace%__IsCloneable__c": true,
        "%vlocity_namespace%__IsEncrypted__c": false,
        "%vlocity_namespace%__IsNotAssetizable__c": false,
        "%vlocity_namespace%__IsPrivate__c": false,
        "%vlocity_namespace%__OwnerId__c": "",
        "%vlocity_namespace%__PicklistId__c": "",
        "%vlocity_namespace%__UniqueNameField__c": "",
        "%vlocity_namespace%__ValueType__c": "Text",
        "%vlocity_namespace%__Value__c": "",
        "%vlocity_namespace%__isDefaultHidden__c": false,
        "Name": "Hearing Exam",
        "VlocityDataPackType": "SObject",
        "VlocityRecordSObjectType": "%vlocity_namespace%__Attribute__c",
        "VlocityRecordSourceKey": "%vlocity_namespace%__Attribute__c/e84bfd98-6579-8687-05f8-1358a9213495"
    },
    {
        "%vlocity_namespace%__ActiveFlg__c": true,
        "%vlocity_namespace%__AttributeCategoryCode__c": "OUTMEDICALBENEFITS",
        "%vlocity_namespace%__AttributeCategoryId__c": {
            "%vlocity_namespace%__Code__c": "OUTMEDICALBENEFITS",
            "VlocityDataPackType": "VlocityMatchingKeyObject",
            "VlocityMatchingRecordSourceKey": "%vlocity_namespace%__AttributeCategory__c/OUTMEDICALBENEFITS",
            "VlocityRecordSObjectType": "%vlocity_namespace%__AttributeCategory__c"
        },
        "%vlocity_namespace%__AttributeCategoryName__c": "Medical Out of Network Benefits",
        "%vlocity_namespace%__AttributeGroupType__c": "",
        "%vlocity_namespace%__Code__c": "ef306ed8-b626-b809-c7d0-ff61b38a63b6",
        "%vlocity_namespace%__Configurable__c": true,
        "%vlocity_namespace%__CustomConfigUiTemplate__c": "",
        "%vlocity_namespace%__Description__c": "",
        "%vlocity_namespace%__DisplaySequence__c": 4,
        "%vlocity_namespace%__EffectiveFromDate__c": "",
        "%vlocity_namespace%__EffectiveUntilDate__c": "",
        "%vlocity_namespace%__Filterable__c": false,
        "%vlocity_namespace%__GlobalKey__c": "7129faaa-cb7a-0f03-b41d-eb9bbc6ebbc1",
        "%vlocity_namespace%__HelpText__c": "",
        "%vlocity_namespace%__IsCloneable__c": true,
        "%vlocity_namespace%__IsEncrypted__c": false,
        "%vlocity_namespace%__IsNotAssetizable__c": false,
        "%vlocity_namespace%__IsPrivate__c": false,
        "%vlocity_namespace%__OwnerId__c": "",
        "%vlocity_namespace%__PicklistId__c": "",
        "%vlocity_namespace%__UniqueNameField__c": "",
        "%vlocity_namespace%__ValueType__c": "Text",
        "%vlocity_namespace%__Value__c": "",
        "%vlocity_namespace%__isDefaultHidden__c": false,
        "Name": "Annual Deductible",
        "VlocityDataPackType": "SObject",
        "VlocityRecordSObjectType": "%vlocity_namespace%__Attribute__c",
        "VlocityRecordSourceKey": "%vlocity_namespace%__Attribute__c/ef306ed8-b626-b809-c7d0-ff61b38a63b6"
    },
    {
        "%vlocity_namespace%__ActiveFlg__c": true,
        "%vlocity_namespace%__AttributeCategoryCode__c": "OUTMEDICALBENEFITS",
        "%vlocity_namespace%__AttributeCategoryId__c": {
            "%vlocity_namespace%__Code__c": "OUTMEDICALBENEFITS",
            "VlocityDataPackType": "VlocityMatchingKeyObject",
            "VlocityMatchingRecordSourceKey": "%vlocity_namespace%__AttributeCategory__c/OUTMEDICALBENEFITS",
            "VlocityRecordSObjectType": "%vlocity_namespace%__AttributeCategory__c"
        },
        "%vlocity_namespace%__AttributeCategoryName__c": "Medical Out of Network Benefits",
        "%vlocity_namespace%__AttributeGroupType__c": "",
        "%vlocity_namespace%__Code__c": "efa4aaf6-329b-e8ea-ea0d-a0e5d3eeed7a",
        "%vlocity_namespace%__Configurable__c": true,
        "%vlocity_namespace%__CustomConfigUiTemplate__c": "",
        "%vlocity_namespace%__Description__c": "",
        "%vlocity_namespace%__DisplaySequence__c": 23,
        "%vlocity_namespace%__EffectiveFromDate__c": "",
        "%vlocity_namespace%__EffectiveUntilDate__c": "",
        "%vlocity_namespace%__Filterable__c": false,
        "%vlocity_namespace%__GlobalKey__c": "33e474e3-0f4e-3fbb-bea0-c81134677770",
        "%vlocity_namespace%__HelpText__c": "",
        "%vlocity_namespace%__IsCloneable__c": true,
        "%vlocity_namespace%__IsEncrypted__c": false,
        "%vlocity_namespace%__IsNotAssetizable__c": false,
        "%vlocity_namespace%__IsPrivate__c": false,
        "%vlocity_namespace%__OwnerId__c": "",
        "%vlocity_namespace%__PicklistId__c": "",
        "%vlocity_namespace%__UniqueNameField__c": "",
        "%vlocity_namespace%__ValueType__c": "Text",
        "%vlocity_namespace%__Value__c": "",
        "%vlocity_namespace%__isDefaultHidden__c": false,
        "Name": "Imaging (CT and PET scans, MRIs)",
        "VlocityDataPackType": "SObject",
        "VlocityRecordSObjectType": "%vlocity_namespace%__Attribute__c",
        "VlocityRecordSourceKey": "%vlocity_namespace%__Attribute__c/efa4aaf6-329b-e8ea-ea0d-a0e5d3eeed7a"
    },
    {
        "%vlocity_namespace%__ActiveFlg__c": true,
        "%vlocity_namespace%__AttributeCategoryCode__c": "OUTMEDICALBENEFITS",
        "%vlocity_namespace%__AttributeCategoryId__c": {
            "%vlocity_namespace%__Code__c": "OUTMEDICALBENEFITS",
            "VlocityDataPackType": "VlocityMatchingKeyObject",
            "VlocityMatchingRecordSourceKey": "%vlocity_namespace%__AttributeCategory__c/OUTMEDICALBENEFITS",
            "VlocityRecordSObjectType": "%vlocity_namespace%__AttributeCategory__c"
        },
        "%vlocity_namespace%__AttributeCategoryName__c": "Medical Out of Network Benefits",
        "%vlocity_namespace%__AttributeGroupType__c": "",
        "%vlocity_namespace%__Code__c": "f0845bad-9ef5-f7ff-3509-455cd157bce5",
        "%vlocity_namespace%__Configurable__c": true,
        "%vlocity_namespace%__CustomConfigUiTemplate__c": "",
        "%vlocity_namespace%__Description__c": "",
        "%vlocity_namespace%__DisplaySequence__c": 40,
        "%vlocity_namespace%__EffectiveFromDate__c": "",
        "%vlocity_namespace%__EffectiveUntilDate__c": "",
        "%vlocity_namespace%__Filterable__c": false,
        "%vlocity_namespace%__GlobalKey__c": "c2d61699-e175-d019-0730-ccc502ff496e",
        "%vlocity_namespace%__HelpText__c": "",
        "%vlocity_namespace%__IsCloneable__c": true,
        "%vlocity_namespace%__IsEncrypted__c": false,
        "%vlocity_namespace%__IsNotAssetizable__c": false,
        "%vlocity_namespace%__IsPrivate__c": false,
        "%vlocity_namespace%__OwnerId__c": "",
        "%vlocity_namespace%__PicklistId__c": "",
        "%vlocity_namespace%__UniqueNameField__c": "",
        "%vlocity_namespace%__ValueType__c": "Text",
        "%vlocity_namespace%__Value__c": "",
        "%vlocity_namespace%__isDefaultHidden__c": false,
        "Name": "Accupuncture and Other Alternative Therapies",
        "VlocityDataPackType": "SObject",
        "VlocityRecordSObjectType": "%vlocity_namespace%__Attribute__c",
        "VlocityRecordSourceKey": "%vlocity_namespace%__Attribute__c/f0845bad-9ef5-f7ff-3509-455cd157bce5"
    },
    {
        "%vlocity_namespace%__ActiveFlg__c": true,
        "%vlocity_namespace%__AttributeCategoryCode__c": "OUTMEDICALBENEFITS",
        "%vlocity_namespace%__AttributeCategoryId__c": {
            "%vlocity_namespace%__Code__c": "OUTMEDICALBENEFITS",
            "VlocityDataPackType": "VlocityMatchingKeyObject",
            "VlocityMatchingRecordSourceKey": "%vlocity_namespace%__AttributeCategory__c/OUTMEDICALBENEFITS",
            "VlocityRecordSObjectType": "%vlocity_namespace%__AttributeCategory__c"
        },
        "%vlocity_namespace%__AttributeCategoryName__c": "Medical Out of Network Benefits",
        "%vlocity_namespace%__AttributeGroupType__c": "",
        "%vlocity_namespace%__Code__c": "fe2cba34-b58b-1f7c-dda7-9fe11eb108c6",
        "%vlocity_namespace%__Configurable__c": true,
        "%vlocity_namespace%__CustomConfigUiTemplate__c": "",
        "%vlocity_namespace%__Description__c": "",
        "%vlocity_namespace%__DisplaySequence__c": 27,
        "%vlocity_namespace%__EffectiveFromDate__c": "",
        "%vlocity_namespace%__EffectiveUntilDate__c": "",
        "%vlocity_namespace%__Filterable__c": false,
        "%vlocity_namespace%__GlobalKey__c": "9baa8356-69f7-ce4d-934a-3a8bc37df50f",
        "%vlocity_namespace%__HelpText__c": "",
        "%vlocity_namespace%__IsCloneable__c": true,
        "%vlocity_namespace%__IsEncrypted__c": false,
        "%vlocity_namespace%__IsNotAssetizable__c": false,
        "%vlocity_namespace%__IsPrivate__c": false,
        "%vlocity_namespace%__OwnerId__c": "",
        "%vlocity_namespace%__PicklistId__c": "",
        "%vlocity_namespace%__UniqueNameField__c": "",
        "%vlocity_namespace%__ValueType__c": "Text",
        "%vlocity_namespace%__Value__c": "",
        "%vlocity_namespace%__isDefaultHidden__c": false,
        "Name": "Outpatient Mental Health",
        "VlocityDataPackType": "SObject",
        "VlocityRecordSObjectType": "%vlocity_namespace%__Attribute__c",
        "VlocityRecordSourceKey": "%vlocity_namespace%__Attribute__c/fe2cba34-b58b-1f7c-dda7-9fe11eb108c6"
    },
    {
        "%vlocity_namespace%__ActiveFlg__c": true,
        "%vlocity_namespace%__AttributeCategoryCode__c": "OUTMEDICALBENEFITS",
        "%vlocity_namespace%__AttributeCategoryId__c": {
            "%vlocity_namespace%__Code__c": "OUTMEDICALBENEFITS",
            "VlocityDataPackType": "VlocityMatchingKeyObject",
            "VlocityMatchingRecordSourceKey": "%vlocity_namespace%__AttributeCategory__c/OUTMEDICALBENEFITS",
            "VlocityRecordSObjectType": "%vlocity_namespace%__AttributeCategory__c"
        },
        "%vlocity_namespace%__AttributeCategoryName__c": "Medical Out of Network Benefits",
        "%vlocity_namespace%__AttributeGroupType__c": "",
        "%vlocity_namespace%__Code__c": "oonDED",
        "%vlocity_namespace%__Configurable__c": true,
        "%vlocity_namespace%__CustomConfigUiTemplate__c": "",
        "%vlocity_namespace%__Description__c": "",
        "%vlocity_namespace%__DisplaySequence__c": 990,
        "%vlocity_namespace%__EffectiveFromDate__c": "",
        "%vlocity_namespace%__EffectiveUntilDate__c": "",
        "%vlocity_namespace%__Filterable__c": false,
        "%vlocity_namespace%__GlobalKey__c": "",
        "%vlocity_namespace%__HelpText__c": "",
        "%vlocity_namespace%__IsCloneable__c": true,
        "%vlocity_namespace%__IsEncrypted__c": false,
        "%vlocity_namespace%__IsNotAssetizable__c": false,
        "%vlocity_namespace%__IsPrivate__c": false,
        "%vlocity_namespace%__OwnerId__c": "",
        "%vlocity_namespace%__PicklistId__c": "",
        "%vlocity_namespace%__UniqueNameField__c": "",
        "%vlocity_namespace%__ValueType__c": "Text",
        "%vlocity_namespace%__Value__c": "",
        "%vlocity_namespace%__isDefaultHidden__c": false,
        "Name": "Deductible",
        "VlocityDataPackType": "SObject",
        "VlocityRecordSObjectType": "%vlocity_namespace%__Attribute__c",
        "VlocityRecordSourceKey": "%vlocity_namespace%__Attribute__c/oonDED"
    },
    {
        "%vlocity_namespace%__ActiveFlg__c": true,
        "%vlocity_namespace%__AttributeCategoryCode__c": "OUTMEDICALBENEFITS",
        "%vlocity_namespace%__AttributeCategoryId__c": {
            "%vlocity_namespace%__Code__c": "OUTMEDICALBENEFITS",
            "VlocityDataPackType": "VlocityMatchingKeyObject",
            "VlocityMatchingRecordSourceKey": "%vlocity_namespace%__AttributeCategory__c/OUTMEDICALBENEFITS",
            "VlocityRecordSObjectType": "%vlocity_namespace%__AttributeCategory__c"
        },
        "%vlocity_namespace%__AttributeCategoryName__c": "Medical Out of Network Benefits",
        "%vlocity_namespace%__AttributeGroupType__c": "",
        "%vlocity_namespace%__Code__c": "ooncoins",
        "%vlocity_namespace%__Configurable__c": true,
        "%vlocity_namespace%__CustomConfigUiTemplate__c": "",
        "%vlocity_namespace%__Description__c": "",
        "%vlocity_namespace%__DisplaySequence__c": 991,
        "%vlocity_namespace%__EffectiveFromDate__c": "",
        "%vlocity_namespace%__EffectiveUntilDate__c": "",
        "%vlocity_namespace%__Filterable__c": false,
        "%vlocity_namespace%__GlobalKey__c": "",
        "%vlocity_namespace%__HelpText__c": "",
        "%vlocity_namespace%__IsCloneable__c": true,
        "%vlocity_namespace%__IsEncrypted__c": false,
        "%vlocity_namespace%__IsNotAssetizable__c": false,
        "%vlocity_namespace%__IsPrivate__c": false,
        "%vlocity_namespace%__OwnerId__c": "",
        "%vlocity_namespace%__PicklistId__c": "",
        "%vlocity_namespace%__UniqueNameField__c": "",
        "%vlocity_namespace%__ValueType__c": "Text",
        "%vlocity_namespace%__Value__c": "",
        "%vlocity_namespace%__isDefaultHidden__c": false,
        "Name": "Coinsurance",
        "VlocityDataPackType": "SObject",
        "VlocityRecordSObjectType": "%vlocity_namespace%__Attribute__c",
        "VlocityRecordSourceKey": "%vlocity_namespace%__Attribute__c/ooncoins"
    }
]